Workbook

Sheet Monitor global
B1: Agro
B2: Delta neto* | C2: =+F5 -> -27289.275
B3: Delta neto Potencial* | C3: =MIN(C5:I5) -> -44435.355
B4: *Suma de posiciones netas vendidas de cada producto (SV-SC)+(MV-MC)+(TV-TC) | K4: Tablero de CONTROL
B5: Delta total | D5: =+D9 -> -27289.275 | E5: =+E9 -> -27289.275 | F5: =+F9 -> -27289.275 | G5: =+G9 -> -44435.355 | H5: =+H9 -> -44435.355 | I5: =+I9 -> -44435.355
B7: Delta Futuros | C7: =SUMIFS(Tabla3[[#All],[delta teorico ]],Tabla3[[#All],[Opcion??]],"no") -> -27289.275 | D7: =C7 -> -27289.275 | E7: =D7 -> -27289.275 | F7: =E7 -> -27289.275 | G7: =F7 -> -27289.275 | H7: =G7 -> -27289.275 | I7: =H7 -> -27289.275 | K7: VISUAL BOLSA | L7: =IF((TODAY())-M7>3,"Actualizar","") | M7: =INDEX(INDIRECT("'Saldo CC'!H:H"),1) -> 9/12/2025
B8: Delta Opciones | C8: =SUMIFS(Tabla3[[#All],[-30%22]],Tabla3[[#All],[Opcion??]],"si") -> 0 | D8: =SUMIFS(Tabla3[[#All],[-20%33]],Tabla3[[#All],[Opcion??]],"si") -> 0 | E8: =SUMIFS(Tabla3[[#All],[-10%44]],Tabla3[[#All],[Opcion??]],"si") -> 0 | F8: =SUMIFS(Tabla3[[#All],[0%55]],Tabla3[[#All],[Opcion??]],"si") -> 0 | G8: =SUMIFS(Tabla3[[#All],[10%66]],Tabla3[[#All],[Opcion??]],"si") -> -17146.08 | H8: =SUMIFS(Tabla3[[#All],[20%77]],Tabla3[[#All],[Opcion??]],"si") -> -17146.08 | I8: =SUMIFS(Tabla3[[#All],[30%88]],Tabla3[[#All],[Opcion??]],"si") -> -17146.08 | K8: Colocaciones | L8: =IF((TODAY())-M8>3,"Actualizar","") | M8: =DATE( LEFT(MID(N8,SEARCH("_",N8,SEARCH("_",N8)+1)+1,8),4), MID(MID(N8,SEARCH("_",N8,SEARCH("_",N8)+1)+1,8),5,2), RIGHT(MID(N8,SEARCH("_",N8,SEARCH("_",N8)+1)+1,8),2) ) -> 45999 | N8: ='Colocaciones base'!A27 -> csvnpos_npos_20251208.csv
B9: Delta Tot | C9: =+C7+C8 -> -27289.275 | D9: =+D7+D8 -> -27289.275 | E9: =+E7+E8 -> -27289.275 | F9: =+F7+F8 -> -27289.275 | G9: =+G7+G8 -> -44435.355 | H9: =+H7+H8 -> -44435.355 | I9: =IFERROR(+I7+I8,1) -> -44435.355 | K9: Estirar fórmulas de cartera clientes | M9: =IF(OR(I9=1,I13=1),"SI","NO") -> NO
B10: Var precios MatRfx | C10: -0.3 | D10: -0.2 | E10: -0.1 | F10: 0 | G10: 0.1 | H10: 0.2 | I10: 0.3 | K10: VER CLIENTES CARTERA | M10: =IF(COUNTIF(Tabla3[Columna1],"VER")>=1,"SI","NO") -> NO
B11: Diferencias a integrar Opciones | C11: =(SUMIFS('Cartera clientes'!BW:BW,'Cartera clientes'!$BF:$BF,"si")-SUMIFS('Cartera clientes'!$BZ:$BZ,'Cartera clientes'!$BF:$BF,"si"))/2 -> 0 | D11: =(SUMIFS('Cartera clientes'!BX:BX,'Cartera clientes'!$BF:$BF,"si")-SUMIFS('Cartera clientes'!$BZ:$BZ,'Cartera clientes'!$BF:$BF,"si"))/2 -> 0 | E11: =(SUMIFS('Cartera clientes'!BY:BY,'Cartera clientes'!$BF:$BF,"si")-SUMIFS('Cartera clientes'!$BZ:$BZ,'Cartera clientes'!$BF:$BF,"si"))/2 -> 0 | F11: =(SUMIFS('Cartera clientes'!BZ:BZ,'Cartera clientes'!$BF:$BF,"si")-SUMIFS('Cartera clientes'!$BZ:$BZ,'Cartera clientes'!$BF:$BF,"si"))/2 -> 0 | G11: =(SUMIFS('Cartera clientes'!CA:CA,'Cartera clientes'!$BF:$BF,"si")-SUMIFS('Cartera clientes'!$BZ:$BZ,'Cartera clientes'!$BF:$BF,"si"))/2 -> -96118.509 | H11: =(SUMIFS('Cartera clientes'!CB:CB,'Cartera clientes'!$BF:$BF,"si")-SUMIFS('Cartera clientes'!$BZ:$BZ,'Cartera clientes'!$BF:$BF,"si"))/2 -> -447673.88 | I11: =(SUMIFS('Cartera clientes'!CC:CC,'Cartera clientes'!$BF:$BF,"si")-SUMIFS('Cartera clientes'!$BZ:$BZ,'Cartera clientes'!$BF:$BF,"si"))/2 -> -799229.24 | K11: VER CLIENTES MONITOR | M11: =IF(COUNTIF('Stress test RJO'!AA4:AA13,"VER")>=1,"SI","NO") -> NO
B12: Diferencias a integrar Futuros | C12: =SUMIFS('Cartera clientes'!BP:BP,'Cartera clientes'!$BE:$BE,"futuro")/2 -> 2614631.1 | D12: =SUMIFS('Cartera clientes'!BQ:BQ,'Cartera clientes'!$BE:$BE,"futuro")/2 -> 1743087.4 | E12: =SUMIFS('Cartera clientes'!BR:BR,'Cartera clientes'!$BE:$BE,"futuro")/2 -> 871543.7 | F12: =SUMIFS('Cartera clientes'!BS:BS,'Cartera clientes'!$BE:$BE,"futuro")/2 -> 0 | G12: =SUMIFS('Cartera clientes'!BT:BT,'Cartera clientes'!$BE:$BE,"futuro")/2 -> -871543.7 | H12: =SUMIFS('Cartera clientes'!BU:BU,'Cartera clientes'!$BE:$BE,"futuro")/2 -> -1743087.4 | I12: =SUMIFS('Cartera clientes'!BV:BV,'Cartera clientes'!$BE:$BE,"futuro")/2 -> -2614631.1 | K12: Actualizar tablas dinamicas | M12: =IF(H14+H15=H13,"NO","SI") -> NO
B13: Usd a integrar | C13: =+C11+C12 -> 2614631.1 | D13: =+D11+D12 -> 1743087.4 | E13: =+E11+E12 -> 871543.7 | F13: =+F11+F12 -> 0 | G13: =+G11+G12 -> -967662.21 | H13: =+H11+H12 -> -2190761.3 | I13: =IFERROR(+I11+I12,1) -> -3413860.4 | K13: Statement | L13: =IF((TODAY())-M13>3,"Actualizar","") | M13: =DATE( LEFT(MID(N13,SEARCH("_",N13,SEARCH("_",N13)+1)+1,8),4), MID(MID(N13,SEARCH("_",N13,SEARCH("_",N13)+1)+1,8),5,2), RIGHT(MID(N13,SEARCH("_",N13,SEARCH("_",N13)+1)+1,8),2) ) -> 45999 | N13: ='Statement base'!AP2 -> csvnmny_nmny_20251208.csv
B14: Usd salida Agro | C14: =IF(C11<0,MIN(Tabla!I22:J22)+C11,MIN(Tabla!I22:J22)) -> 0 | D14: =IF(D11<0,MIN(Tabla!K22:L22)+D11,MIN(Tabla!K22:L22)) -> 0 | E14: =IF(E11<0,MIN(Tabla!M22:N22)+E11,MIN(Tabla!M22:N22)) -> 0 | F14: 0 | G14: =IF(G11<0,MIN(Tabla!O22:P22)+G11,MIN(Tabla!O22:P22)) -> -967662.21 | H14: =IF(H11<0,MIN(Tabla!Q22:R22)+H11,MIN(Tabla!Q22:R22)) -> -2190761.3 | I14: =IF(I11<0,MIN(Tabla!S22:T22)+I11,MIN(Tabla!S22:T22)) -> -3413860.4 | K14: Fact_AUM_FyoCapital | L14: =IF((TODAY())-M14>3,"Actualizar","") -> Actualizar | M14: =Fact_AUM_FyoCapital!H2 -> 45996
B15: Usd entrada Agro | C15: =IF(C11>0,MAX(Tabla!I22:J22)+C11,MAX(Tabla!I22:J22)) -> 2614631.1 | D15: =IF(D11>0,MAX(Tabla!K22:L22)+D11,MAX(Tabla!K22:L22)) -> 1743087.4 | E15: =IF(E11>0,MAX(Tabla!M22:N22)+E11,MAX(Tabla!M22:N22)) -> 871543.7 | F15: 0 | G15: =IF(G11>0,MAX(Tabla!O22:P22)+G11,MAX(Tabla!O22:P22)) -> 0 | H15: =IF(H11>0,MAX(Tabla!Q22:R22)+H11,MAX(Tabla!Q22:R22)) -> 0 | I15: =IF(I11>0,MAX(Tabla!S22:T22)+I11,MAX(Tabla!S22:T22)) -> 0 | K15: Ver Productos Colocaciones | M15: =IF(COUNTIF(Colocaciones[[#All],[Producto]],"VER")>=1,"SI","NO") -> NO
B16: Usd por tn a integrar | C16: =(C12+C11)/C9*-1 -> 95.811674 | D16: =(D12+D11)/D9*-1 -> 63.874449 | E16: =(E12+E11)/E9*-1 -> 31.937225 | F16: =(F12+F11)/F9*-1 -> 0 | G16: =(G12+G11)/G9*-1 -> -21.776853 | H16: =(H12+H11)/H9*-1 -> -49.302212 | I16: =(I12+I11)/I9*-1 -> -76.82757 | K16: Hay posicion con Harina de soja? | M16: =IF(COUNTIF(Colocaciones[[#All],[Producto]],"Harina de soja")>=1,"SI","NO") -> NO
B17: Usd a integrar sin FASA | C17: =C18+C19+C11 -> 0 | D17: =D18+D19+D11 -> 0 | E17: =E18+E19+E11 -> 0 | F17: =F18+F19+F11 -> 0 | G17: =G18+G19+G11 -> -192237.02 | H17: =H18+H19+H11 -> -895347.75 | I17: =I18+I19+I11 -> -1598458.5 | K17: Ver Precios | M17: =IF(MAX(Tabla3[[#All],[Precio]])>1000,"SI","NO") -> NO
B18: Usd salida Agro sin FASA | C18: =IF(C11<0,MIN(Tabla!I23:J23)+C11,MIN(Tabla!I23:J23)) -> 0 | D18: =IF(D11<0,MIN(Tabla!K23:L23)+D11,MIN(Tabla!K23:L23)) -> 0 | E18: =IF(E11<0,MIN(Tabla!M23:N23)+E11,MIN(Tabla!M23:N23)) -> 0 | F18: 0 | G18: =IF(G11<0,MIN(Tabla!O23:P25)+G11,MIN(Tabla!O23:P25)) -> -96118.509 | H18: =IF(H11<0,MIN(Tabla!Q23:R25)+H11,MIN(Tabla!Q23:R25)) -> -447673.88 | I18: =IF(I11<0,MIN(Tabla!S23:T25)+I11,MIN(Tabla!S23:T25)) -> -799229.24
B19: Usd entrada Agro sin FASA | C19: =IF(C11>0,MAX(Tabla!I23:J23)+C11,MAX(Tabla!I23:J23)) -> 0 | D19: =IF(D11>0,MAX(Tabla!K23:L23)+D11,MAX(Tabla!K23:L23)) -> 0 | E19: =IF(E11>0,MAX(Tabla!M23:N23)+E11,MAX(Tabla!M23:N23)) -> 0 | F19: 0 | G19: =IF(G11>0,MAX(Tabla!O23:P25)+G11,MAX(Tabla!O23:P25)) -> 0 | H19: =IF(H11>0,MAX(Tabla!Q23:R25)+H11,MAX(Tabla!Q23:R25)) -> 0 | I19: =IF(I11>0,MAX(Tabla!S23:T25)+I11,MAX(Tabla!S23:T25)) -> 0
B20: Usd a integrar FASA | C20: =C13-C17 -> 2614631.1 | D20: =D13-D17 -> 1743087.4 | E20: =E13-E17 -> 871543.7 | F20: =F13-F17 -> 0 | G20: =G13-G17 -> -775425.2 | H20: =H13-H17 -> -1295413.5 | I20: =I13-I17 -> -1815401.9
B21: Usd salida Agro FASA | C21: =C14-C18-C11 -> 0 | D21: =D14-D18-D11 -> 0 | E21: =E14-E18-E11 -> 0 | F21: =F14-F18-F11 -> 0 | G21: =G14-G18-G11 -> -775425.2 | H21: =H14-H18-H11 -> -1295413.5 | I21: =I14-I18-I11 -> -1815401.9
B22: Usd entrada Agro FASA | C22: =C15-C19 -> 2614631.1 | D22: =D15-D19 -> 1743087.4 | E22: =E15-E19 -> 871543.7 | F22: =F15-F19 -> 0 | G22: =G15-G19 -> 0 | H22: =H15-H19 -> 0 | I22: =I15-I19 -> 0

Sheet Cartera clientes
AZ1: Estirar tabla | BD1: llevarlo siempre + Y - | BI1: PRECIOS | BP1: Dif FUTUROS | BW1: DIFERENCIAS Opciones | CD1: Delta opciones
A2: {=Colocaciones[[#All],[Record Code]]} -> Record Code | B2: {=Colocaciones[[#All],[Firm Code]]} -> Firm Code | C2: {=Colocaciones[[#All],[Office Code]]} -> Office Code | D2: {=Colocaciones[[#All],[Sales Code]]} -> Sales Code | E2: {=Colocaciones[[#All],[Account Number]]} -> Account Number | F2: {=Colocaciones[[#All],[Account Class Code]]} -> Account Class Code | G2: {=Colocaciones[[#All],[Account Subclass Code]]} -> Account Subclass Code | H2: {=Colocaciones[[#All],[Account Type Code]]} -> Account Type Code | I2: {=Colocaciones[[#All],[Cusip Code]]} -> Cusip Code | J2: {=Colocaciones[[#All],[Card Number]]} -> Card Number | K2: {=Colocaciones[[#All],[Buy Sell Code]]} -> Buy Sell Code | L2: {=Colocaciones[[#All],[Quantity]]} -> Quantity | M2: {=Colocaciones[[#All],[Security Desc Line 1]]} -> Security Desc Line 1 | N2: {=Colocaciones[[#All],[Formatted Trade Price]]} -> Formatted Trade Price | O2: {=Colocaciones[[#All],[Trade Date]]} -> Trade Date | P2: {=Colocaciones[[#All],[Open Close Code]]} -> Open Close Code | Q2: {=Colocaciones[[#All],[Contract Month]]} -> Contract Month | R2: {=Colocaciones[[#All],[Contract Day]]} -> Contract Day | S2: {=Colocaciones[[#All],[Security Type Code]]} -> Security Type Code | T2: {=Colocaciones[[#All],[Security Subtype Code]]} -> Security Subtype Code | U2: {=Colocaciones[[#All],[Option Strike Price]]} -> Option Strike Price | V2: {=Colocaciones[[#All],[Option Expire Date]]} -> Option Expire Date | W2: {=Colocaciones[[#All],[Spread Code]]} -> Spread Code | X2: {=Colocaciones[[#All],[Account Name]]} -> Account Name | Y2: {=Colocaciones[[#All],[Source Account Number]]} -> Source Account Number | Z2: {=Colocaciones[[#All],[Settlement Date]]} -> Settlement Date | AA2: {=Colocaciones[[#All],[Exchange Code]]} -> Exchange Code | AB2: {=Colocaciones[[#All],[Trade Exchange Code]]} -> Trade Exchange Code | AC2: {=Colocaciones[[#All],[Contract Code]]} -> Contract Code | AD2: {=Colocaciones[[#All],[Contract Symbol]]} -> Contract Symbol | AE2: {=Colocaciones[[#All],[Product Type Code]]} -> Product Type Code | AF2: {=Colocaciones[[#All],[Trade Price]]} -> Trade Price | AG2: {=Colocaciones[[#All],[Trade Calc Control Code]]} -> Trade Calc Control Code | AH2: {=Colocaciones[[#All],[Comment Code 1]]} -> Comment Code 1 | AI2: {=Colocaciones[[#All],[Comment Code 2]]} -> Comment Code 2 | AJ2: {=Colocaciones[[#All],[Give Up Code]]} -> Give Up Code | AK2: {=Colocaciones[[#All],[Give Up Firm Code]]} -> Give Up Firm Code | AL2: {=Colocaciones[[#All],[Buy Side Quantity]]} -> Buy Side Quantity | AM2: {=Colocaciones[[#All],[Sell Side Quantity]]} -> Sell Side Quantity | AN2: {=Colocaciones[[#All],[Account Type Currency Symbol]]} -> Account Type Currency Symbol | AO2: {=Colocaciones[[#All],[Market Value]]} -> Market Value | AP2: {=Colocaciones[[#All],[Close Price]]} -> Close Price | AQ2: {=Colocaciones[[#All],[Underlying Close Price]]} -> Underlying Close Price | AR2: {=IFERROR(Colocaciones[[#All],[Multiplication Factor]]/1000,"Multiplication Factor")} -> Multiplication Factor | AS2: {=Colocaciones[[#All],[Tracer Number]]} -> Tracer Number | AT2: {=Colocaciones[[#All],[Order Number]]} -> Order Number | AU2: {=Colocaciones[[#All],[Delta Factor]]} -> Delta Factor | AV2: {=Colocaciones[[#All],[Bloomberg Root]]} -> Bloomberg Root | AW2: {=Colocaciones[[#All],[Bloomberg Exch Code]]} -> Bloomberg Exch Code | AX2: {=Colocaciones[[#All],[Bloomberg Market Sector]]} -> Bloomberg Market Sector | AY2: {=Colocaciones[[#All],[Producto]]} -> Producto | AZ2: Coversor precio | BA2: Conversor tns | BB2: Precio | BC2: Strike | BD2: Tns | BE2: Tipo | BF2: Opcion?? | BG2: Lado | BH2: Cat opcion | BI2: -30% | BJ2: -20% | BK2: -10% | BL2: 0% | BM2: 10% | BN2: 20% | BO2: 30% | BP2: DF -30% | BQ2: DF -20% | BR2: DF -10% | BS2: DF 0% | BT2: DF 10% | BU2: DF 20% | BV2: DF 30% | BW2: -30%2 | BX2: -20%3 | BY2: -10%4 | BZ2: 0%5 | CA2: 10%6 | CB2: 20%7 | CC2: 30%8 | CD2: -30%22 | CE2: -20%33 | CF2: -10%44 | CG2: 0%55 | CH2: 10%66 | CI2: 20%77 | CJ2: 30%88 | CK2: delta teorico | CL2: Columna1
A3: P | B3: R | C3: 766 | D3: 0 | E3: 13005 | F3: C | G3: O | H3: F1 | I3: .AS-0117026E | J3: 2786 | K3: 1 | L3: 180000 | M3: CALL MAY 26 SOYBEANS 1170 | N3: .15 3/8 | O3: 20250925 | Q3: 202605 | S3: F | T3: C | U3: 1170000000 | V3: 20260424 | X3: FUTUROS Y OPCIONES.C | Z3: 20250925 | AA3: 1 | AB3: 1A | AC3: S- | AF3: .15375000 | AL3: 180000 | AM3: .0000 | AN3: USD | AO3: 1788750 | AP3: 0 | AQ3: 1116750000 | AR3: 50000 | AS3: 5I25 zLB0 | AT3: 115852786 | AU3: 0,3160 | AV3: S | AW3: CBT | AX3: Comdty | AY3: Soja | AZ3: =IF(VLOOKUP(AY3,Conversor!B:C,2,0)="HS",0.01,VLOOKUP(AY3,Conversor!B:C,2,0)) -> 0.36743 | BA3: =IF(BG3="v",-AM3/10000,AL3/10000) -> 18 | BB3: =IF(AQ3=0,AP3/1000000*AZ3,AQ3/1000000*AZ3) -> 410.32745 | BC3: =U3/1000000*AZ3 -> 429.8931 | BD3: =IF(OR(E3="FUTUR",E3="f20176"),0,VLOOKUP(AY3,Conversor!G:I,3,0)*BA3) -> 2449.44 | BE3: =IF(LEFT(M3,4)="call","Call",IF(LEFT(M3,3)="put","Put","Futuro")) -> Call | BF3: =IF(BE3="futuro","no","si") -> si | BG3: =IF(AL3=0,"V","C") -> C | BH3: =IF(BE3="futuro","",CONCATENATE(BG3,LEFT(BE3,1))) -> CC | BI3: =$BB3*(1+BI$2) -> 287.22922 | BJ3: =$BB3*(1+BJ$2) -> 328.26196 | BK3: =$BB3*(1+BK$2) -> 369.29471 | BL3: =$BB3*(1+BL$2) -> 410.32745 | BM3: =$BB3*(1+BM$2) -> 451.3602 | BN3: =$BB3*(1+BN$2) -> 492.39294 | BO3: =$BB3*(1+BO$2) -> 533.42569 | BP3: =IF($BE3="futuro",-($BL3-BI3)*$BD3,0) -> 0 | BQ3: =IF($BE3="futuro",-($BL3-BJ3)*$BD3,0) -> 0 | BR3: =IF($BE3="futuro",-($BL3-BK3)*$BD3,0) -> 0 | BS3: =IF($BE3="futuro",-($BL3-BL3)*$BD3,0) -> 0 | BT3: =IF($BE3="futuro",-($BL3-BM3)*$BD3,0) -> 0 | BU3: =IF($BE3="futuro",-($BL3-BN3)*$BD3,0) -> 0 | BV3: =IF($BE3="futuro",-($BL3-BO3)*$BD3,0) -> 0 | BW3: =IF(AND($BH3="CC",($BC3-BI3)<0),(BI3-$BC3)*$BD3, IF(AND($BH3="VC",($BC3-BI3)<0),($BC3-BI3)*-$BD3, IF(AND($BH3="CP",($BC3-BI3)>0),(BI3-$BC3)*$BD3*-1, IF(AND($BH3="VP",($BC3-BI3)>0),(BI3-$BC3)*$BD3*-1,0)))) -> 0 | BX3: =IF(AND($BH3="CC",($BC3-BJ3)<0),(BJ3-$BC3)*$BD3, IF(AND($BH3="VC",($BC3-BJ3)<0),($BC3-BJ3)*-$BD3, IF(AND($BH3="CP",($BC3-BJ3)>0),(BJ3-$BC3)*$BD3*-1, IF(AND($BH3="VP",($BC3-BJ3)>0),(BJ3-$BC3)*$BD3*-1,0)))) -> 0 | BY3: =IF(AND($BH3="CC",($BC3-BK3)<0),(BK3-$BC3)*$BD3, IF(AND($BH3="VC",($BC3-BK3)<0),($BC3-BK3)*-$BD3, IF(AND($BH3="CP",($BC3-BK3)>0),(BK3-$BC3)*$BD3*-1, IF(AND($BH3="VP",($BC3-BK3)>0),(BK3-$BC3)*$BD3*-1,0)))) -> 0 | BZ3: =IF(AND($BH3="CC",($BC3-BL3)<0),(BL3-$BC3)*$BD3, IF(AND($BH3="VC",($BC3-BL3)<0),($BC3-BL3)*-$BD3, IF(AND($BH3="CP",($BC3-BL3)>0),(BL3-$BC3)*$BD3*-1, IF(AND($BH3="VP",($BC3-BL3)>0),(BL3-$BC3)*$BD3*-1,0)))) -> 0 | CA3: =IF(AND($BH3="CC",($BC3-BM3)<0),(BM3-$BC3)*$BD3, IF(AND($BH3="VC",($BC3-BM3)<0),($BC3-BM3)*-$BD3, IF(AND($BH3="CP",($BC3-BM3)>0),(BM3-$BC3)*$BD3*-1, IF(AND($BH3="VP",($BC3-BM3)>0),(BM3-$BC3)*$BD3*-1,0)))) -> 52582.368 | CB3: =IF(AND($BH3="CC",($BC3-BN3)<0),(BN3-$BC3)*$BD3, IF(AND($BH3="VC",($BC3-BN3)<0),($BC3-BN3)*-$BD3, IF(AND($BH3="CP",($BC3-BN3)>0),(BN3-$BC3)*$BD3*-1, IF(AND($BH3="VP",($BC3-BN3)>0),(BN3-$BC3)*$BD3*-1,0)))) -> 153089.62 | CC3: =IF(AND($BH3="CC",($BC3-BO3)<0),(BO3-$BC3)*$BD3, IF(AND($BH3="VC",($BC3-BO3)<0),($BC3-BO3)*-$BD3, IF(AND($BH3="CP",($BC3-BO3)>0),(BO3-$BC3)*$BD3*-1, IF(AND($BH3="VP",($BC3-BO3)>0),(BO3-$BC3)*$BD3*-1,0)))) -> 253596.86 | CD3: =IF(AND($BH3="CC",($BC3-BI3)<0),$BD3*1, IF(AND($BH3="VC",($BC3-BI3)<0),$BD3*1, IF(AND($BH3="CP",($BC3-BI3)>0),$BD3*-1, IF(AND($BH3="VP",($BC3-BI3)>0),$BD3*-1,0)))) -> 0 | CE3: =IF(AND($BH3="CC",($BC3-BJ3)<0),$BD3*1, IF(AND($BH3="VC",($BC3-BJ3)<0),$BD3*1, IF(AND($BH3="CP",($BC3-BJ3)>0),$BD3*-1, IF(AND($BH3="VP",($BC3-BJ3)>0),$BD3*-1,0)))) -> 0 | CF3: =IF(AND($BH3="CC",($BC3-BK3)<0),$BD3*1, IF(AND($BH3="VC",($BC3-BK3)<0),$BD3*1, IF(AND($BH3="CP",($BC3-BK3)>0),$BD3*-1, IF(AND($BH3="VP",($BC3-BK3)>0),$BD3*-1,0)))) -> 0 | CG3: =IF(AND($BH3="CC",($BC3-BL3)<0),$BD3*1, IF(AND($BH3="VC",($BC3-BL3)<0),$BD3*1, IF(AND($BH3="CP",($BC3-BL3)>0),$BD3*-1, IF(AND($BH3="VP",($BC3-BL3)>0),$BD3*-1,0)))) -> 0 | CH3: =IF(AND($BH3="CC",($BC3-BM3)<0),$BD3*1, IF(AND($BH3="VC",($BC3-BM3)<0),$BD3*1, IF(AND($BH3="CP",($BC3-BM3)>0),$BD3*-1, IF(AND($BH3="VP",($BC3-BM3)>0),$BD3*-1,0)))) -> 2449.44 | CI3: =IF(AND($BH3="CC",($BC3-BN3)<0),$BD3*1, IF(AND($BH3="VC",($BC3-BN3)<0),$BD3*1, IF(AND($BH3="CP",($BC3-BN3)>0),$BD3*-1, IF(AND($BH3="VP",($BC3-BN3)>0),$BD3*-1,0)))) -> 2449.44 | CJ3: =IF(AND($BH3="CC",($BC3-BO3)<0),$BD3*1, IF(AND($BH3="VC",($BC3-BO3)<0),$BD3*1, IF(AND($BH3="CP",($BC3-BO3)>0),$BD3*-1, IF(AND($BH3="VP",($BC3-BO3)>0),$BD3*-1,0)))) -> 2449.44 | CK3: =Tabla3[[#This Row],[Tns]] -> 2449.44 | CL3: =IF(ISERROR(VLOOKUP(VALUE(E3),'Clientes CBOT'!A:A,1,0)),"VER","ok") -> ok
A4: P | B4: R | C4: 766 | D4: 0 | E4: 13006 | F4: C | G4: O | H4: F1 | I4: .AS-0115026C | J4: 9702 | K4: 2 | L4: 100000 | M4: CALL MAR 26 SOYBEANS 1150 | N4: .17 1/8 | O4: 20251205 | Q4: 202603 | S4: F | T4: C | U4: 1150000000 | V4: 20260220 | X4: FUTUROS Y OPCIONES.C | Z4: 20251205 | AA4: 1 | AB4: 1A | AC4: S- | AF4: .17125000 | AL4: 0 | AM4: 10.0000 | AN4: USD | AO4: -637500 | AP4: 0 | AQ4: 1105750000 | AR4: 50000 | AS4: 5L05 G9l0 | AT4: 116429702 | AU4: 0,2870 | AV4: S | AW4: CBT | AX4: Comdty | AY4: Soja | AZ4: =IF(VLOOKUP(AY4,Conversor!B:C,2,0)="HS",0.01,VLOOKUP(AY4,Conversor!B:C,2,0)) -> 0.36743 | BA4: =IF(BG4="v",-AM4/10000,AL4/10000) -> -10 | BB4: =IF(AQ4=0,AP4/1000000*AZ4,AQ4/1000000*AZ4) -> 406.28572 | BC4: =U4/1000000*AZ4 -> 422.5445 | BD4: =IF(OR(E4="FUTUR",E4="f20176"),0,VLOOKUP(AY4,Conversor!G:I,3,0)*BA4) -> -1360.8 | BE4: =IF(LEFT(M4,4)="call","Call",IF(LEFT(M4,3)="put","Put","Futuro")) -> Call | BF4: =IF(BE4="futuro","no","si") -> si | BG4: =IF(AL4=0,"V","C") -> V | BH4: =IF(BE4="futuro","",CONCATENATE(BG4,LEFT(BE4,1))) -> VC | BI4: =$BB4*(1+BI$2) -> 284.40001 | BJ4: =$BB4*(1+BJ$2) -> 325.02858 | BK4: =$BB4*(1+BK$2) -> 365.65715 | BL4: =$BB4*(1+BL$2) -> 406.28572 | BM4: =$BB4*(1+BM$2) -> 446.91429 | BN4: =$BB4*(1+BN$2) -> 487.54287 | BO4: =$BB4*(1+BO$2) -> 528.17144 | BP4: =IF($BE4="futuro",-($BL4-BI4)*$BD4,0) -> 0 | BQ4: =IF($BE4="futuro",-($BL4-BJ4)*$BD4,0) -> 0 | BR4: =IF($BE4="futuro",-($BL4-BK4)*$BD4,0) -> 0 | BS4: =IF($BE4="futuro",-($BL4-BL4)*$BD4,0) -> 0 | BT4: =IF($BE4="futuro",-($BL4-BM4)*$BD4,0) -> 0 | BU4: =IF($BE4="futuro",-($BL4-BN4)*$BD4,0) -> 0 | BV4: =IF($BE4="futuro",-($BL4-BO4)*$BD4,0) -> 0 | BW4: =IF(AND($BH4="CC",($BC4-BI4)<0),(BI4-$BC4)*$BD4, IF(AND($BH4="VC",($BC4-BI4)<0),($BC4-BI4)*-$BD4, IF(AND($BH4="CP",($BC4-BI4)>0),(BI4-$BC4)*$BD4*-1, IF(AND($BH4="VP",($BC4-BI4)>0),(BI4-$BC4)*$BD4*-1,0)))) -> 0 | BX4: =IF(AND($BH4="CC",($BC4-BJ4)<0),(BJ4-$BC4)*$BD4, IF(AND($BH4="VC",($BC4-BJ4)<0),($BC4-BJ4)*-$BD4, IF(AND($BH4="CP",($BC4-BJ4)>0),(BJ4-$BC4)*$BD4*-1, IF(AND($BH4="VP",($BC4-BJ4)>0),(BJ4-$BC4)*$BD4*-1,0)))) -> 0 | BY4: =IF(AND($BH4="CC",($BC4-BK4)<0),(BK4-$BC4)*$BD4, IF(AND($BH4="VC",($BC4-BK4)<0),($BC4-BK4)*-$BD4, IF(AND($BH4="CP",($BC4-BK4)>0),(BK4-$BC4)*$BD4*-1, IF(AND($BH4="VP",($BC4-BK4)>0),(BK4-$BC4)*$BD4*-1,0)))) -> 0 | BZ4: =IF(AND($BH4="CC",($BC4-BL4)<0),(BL4-$BC4)*$BD4, IF(AND($BH4="VC",($BC4-BL4)<0),($BC4-BL4)*-$BD4, IF(AND($BH4="CP",($BC4-BL4)>0),(BL4-$BC4)*$BD4*-1, IF(AND($BH4="VP",($BC4-BL4)>0),(BL4-$BC4)*$BD4*-1,0)))) -> 0 | CA4: =IF(AND($BH4="CC",($BC4-BM4)<0),(BM4-$BC4)*$BD4, IF(AND($BH4="VC",($BC4-BM4)<0),($BC4-BM4)*-$BD4, IF(AND($BH4="CP",($BC4-BM4)>0),(BM4-$BC4)*$BD4*-1, IF(AND($BH4="VP",($BC4-BM4)>0),(BM4-$BC4)*$BD4*-1,0)))) -> -33162.417 | CB4: =IF(AND($BH4="CC",($BC4-BN4)<0),(BN4-$BC4)*$BD4, IF(AND($BH4="VC",($BC4-BN4)<0),($BC4-BN4)*-$BD4, IF(AND($BH4="CP",($BC4-BN4)>0),(BN4-$BC4)*$BD4*-1, IF(AND($BH4="VP",($BC4-BN4)>0),(BN4-$BC4)*$BD4*-1,0)))) -> -88449.778 | CC4: =IF(AND($BH4="CC",($BC4-BO4)<0),(BO4-$BC4)*$BD4, IF(AND($BH4="VC",($BC4-BO4)<0),($BC4-BO4)*-$BD4, IF(AND($BH4="CP",($BC4-BO4)>0),(BO4-$BC4)*$BD4*-1, IF(AND($BH4="VP",($BC4-BO4)>0),(BO4-$BC4)*$BD4*-1,0)))) -> -143737.14 | CD4: =IF(AND($BH4="CC",($BC4-BI4)<0),$BD4*1, IF(AND($BH4="VC",($BC4-BI4)<0),$BD4*1, IF(AND($BH4="CP",($BC4-BI4)>0),$BD4*-1, IF(AND($BH4="VP",($BC4-BI4)>0),$BD4*-1,0)))) -> 0 | CE4: =IF(AND($BH4="CC",($BC4-BJ4)<0),$BD4*1, IF(AND($BH4="VC",($BC4-BJ4)<0),$BD4*1, IF(AND($BH4="CP",($BC4-BJ4)>0),$BD4*-1, IF(AND($BH4="VP",($BC4-BJ4)>0),$BD4*-1,0)))) -> 0 | CF4: =IF(AND($BH4="CC",($BC4-BK4)<0),$BD4*1, IF(AND($BH4="VC",($BC4-BK4)<0),$BD4*1, IF(AND($BH4="CP",($BC4-BK4)>0),$BD4*-1, IF(AND($BH4="VP",($BC4-BK4)>0),$BD4*-1,0)))) -> 0 | CG4: =IF(AND($BH4="CC",($BC4-BL4)<0),$BD4*1, IF(AND($BH4="VC",($BC4-BL4)<0),$BD4*1, IF(AND($BH4="CP",($BC4-BL4)>0),$BD4*-1, IF(AND($BH4="VP",($BC4-BL4)>0),$BD4*-1,0)))) -> 0 | CH4: =IF(AND($BH4="CC",($BC4-BM4)<0),$BD4*1, IF(AND($BH4="VC",($BC4-BM4)<0),$BD4*1, IF(AND($BH4="CP",($BC4-BM4)>0),$BD4*-1, IF(AND($BH4="VP",($BC4-BM4)>0),$BD4*-1,0)))) -> -1360.8 | CI4: =IF(AND($BH4="CC",($BC4-BN4)<0),$BD4*1, IF(AND($BH4="VC",($BC4-BN4)<0),$BD4*1, IF(AND($BH4="CP",($BC4-BN4)>0),$BD4*-1, IF(AND($BH4="VP",($BC4-BN4)>0),$BD4*-1,0)))) -> -1360.8 | CJ4: =IF(AND($BH4="CC",($BC4-BO4)<0),$BD4*1, IF(AND($BH4="VC",($BC4-BO4)<0),$BD4*1, IF(AND($BH4="CP",($BC4-BO4)>0),$BD4*-1, IF(AND($BH4="VP",($BC4-BO4)>0),$BD4*-1,0)))) -> -1360.8 | CK4: =Tabla3[[#This Row],[Tns]] -> -1360.8 | CL4: =IF(ISERROR(VLOOKUP(VALUE(E4),'Clientes CBOT'!A:A,1,0)),"VER","ok") -> ok
A5: P | B5: R | C5: 766 | D5: 0 | E5: 13006 | F5: C | G5: O | H5: F1 | I5: .AS-0118026E | J5: 3793 | K5: 2 | L5: 100000 | M5: CALL MAY 26 SOYBEANS 1180 | N5: .13 3/4 | O5: 20251009 | Q5: 202605 | S5: F | T5: C | U5: 1180000000 | V5: 20260424 | X5: FUTUROS Y OPCIONES.C | Z5: 20251009 | AA5: 1 | AB5: 1A | AC5: S- | AF5: .13750000 | AL5: 0 | AM5: 10.0000 | AN5: USD | AO5: -868750 | AP5: 0 | AQ5: 1116750000 | AR5: 50000 | AS5: 5J09 LRx0 | AT5: 115953793 | AU5: 0,2860 | AV5: S | AW5: CBT | AX5: Comdty | AY5: Soja | AZ5: =IF(VLOOKUP(AY5,Conversor!B:C,2,0)="HS",0.01,VLOOKUP(AY5,Conversor!B:C,2,0)) -> 0.36743 | BA5: =IF(BG5="v",-AM5/10000,AL5/10000) -> -10 | BB5: =IF(AQ5=0,AP5/1000000*AZ5,AQ5/1000000*AZ5) -> 410.32745 | BC5: =U5/1000000*AZ5 -> 433.5674 | BD5: =IF(OR(E5="FUTUR",E5="f20176"),0,VLOOKUP(AY5,Conversor!G:I,3,0)*BA5) -> -1360.8 | BE5: =IF(LEFT(M5,4)="call","Call",IF(LEFT(M5,3)="put","Put","Futuro")) -> Call | BF5: =IF(BE5="futuro","no","si") -> si | BG5: =IF(AL5=0,"V","C") -> V | BH5: =IF(BE5="futuro","",CONCATENATE(BG5,LEFT(BE5,1))) -> VC | BI5: =$BB5*(1+BI$2) -> 287.22922 | BJ5: =$BB5*(1+BJ$2) -> 328.26196 | BK5: =$BB5*(1+BK$2) -> 369.29471 | BL5: =$BB5*(1+BL$2) -> 410.32745 | BM5: =$BB5*(1+BM$2) -> 451.3602 | BN5: =$BB5*(1+BN$2) -> 492.39294 | BO5: =$BB5*(1+BO$2) -> 533.42569 | BP5: =IF($BE5="futuro",-($BL5-BI5)*$BD5,0) -> 0 | BQ5: =IF($BE5="futuro",-($BL5-BJ5)*$BD5,0) -> 0 | BR5: =IF($BE5="futuro",-($BL5-BK5)*$BD5,0) -> 0 | BS5: =IF($BE5="futuro",-($BL5-BL5)*$BD5,0) -> 0 | BT5: =IF($BE5="futuro",-($BL5-BM5)*$BD5,0) -> 0 | BU5: =IF($BE5="futuro",-($BL5-BN5)*$BD5,0) -> 0 | BV5: =IF($BE5="futuro",-($BL5-BO5)*$BD5,0) -> 0 | BW5: =IF(AND($BH5="CC",($BC5-BI5)<0),(BI5-$BC5)*$BD5, IF(AND($BH5="VC",($BC5-BI5)<0),($BC5-BI5)*-$BD5, IF(AND($BH5="CP",($BC5-BI5)>0),(BI5-$BC5)*$BD5*-1, IF(AND($BH5="VP",($BC5-BI5)>0),(BI5-$BC5)*$BD5*-1,0)))) -> 0 | BX5: =IF(AND($BH5="CC",($BC5-BJ5)<0),(BJ5-$BC5)*$BD5, IF(AND($BH5="VC",($BC5-BJ5)<0),($BC5-BJ5)*-$BD5, IF(AND($BH5="CP",($BC5-BJ5)>0),(BJ5-$BC5)*$BD5*-1, IF(AND($BH5="VP",($BC5-BJ5)>0),(BJ5-$BC5)*$BD5*-1,0)))) -> 0 | BY5: =IF(AND($BH5="CC",($BC5-BK5)<0),(BK5-$BC5)*$BD5, IF(AND($BH5="VC",($BC5-BK5)<0),($BC5-BK5)*-$BD5, IF(AND($BH5="CP",($BC5-BK5)>0),(BK5-$BC5)*$BD5*-1, IF(AND($BH5="VP",($BC5-BK5)>0),(BK5-$BC5)*$BD5*-1,0)))) -> 0 | BZ5: =IF(AND($BH5="CC",($BC5-BL5)<0),(BL5-$BC5)*$BD5, IF(AND($BH5="VC",($BC5-BL5)<0),($BC5-BL5)*-$BD5, IF(AND($BH5="CP",($BC5-BL5)>0),(BL5-$BC5)*$BD5*-1, IF(AND($BH5="VP",($BC5-BL5)>0),(BL5-$BC5)*$BD5*-1,0)))) -> 0 | CA5: =IF(AND($BH5="CC",($BC5-BM5)<0),(BM5-$BC5)*$BD5, IF(AND($BH5="VC",($BC5-BM5)<0),($BC5-BM5)*-$BD5, IF(AND($BH5="CP",($BC5-BM5)>0),(BM5-$BC5)*$BD5*-1, IF(AND($BH5="VP",($BC5-BM5)>0),(BM5-$BC5)*$BD5*-1,0)))) -> -24212.439 | CB5: =IF(AND($BH5="CC",($BC5-BN5)<0),(BN5-$BC5)*$BD5, IF(AND($BH5="VC",($BC5-BN5)<0),($BC5-BN5)*-$BD5, IF(AND($BH5="CP",($BC5-BN5)>0),(BN5-$BC5)*$BD5*-1, IF(AND($BH5="VP",($BC5-BN5)>0),(BN5-$BC5)*$BD5*-1,0)))) -> -80049.799 | CC5: =IF(AND($BH5="CC",($BC5-BO5)<0),(BO5-$BC5)*$BD5, IF(AND($BH5="VC",($BC5-BO5)<0),($BC5-BO5)*-$BD5, IF(AND($BH5="CP",($BC5-BO5)>0),(BO5-$BC5)*$BD5*-1, IF(AND($BH5="VP",($BC5-BO5)>0),(BO5-$BC5)*$BD5*-1,0)))) -> -135887.16 | CD5: =IF(AND($BH5="CC",($BC5-BI5)<0),$BD5*1, IF(AND($BH5="VC",($BC5-BI5)<0),$BD5*1, IF(AND($BH5="CP",($BC5-BI5)>0),$BD5*-1, IF(AND($BH5="VP",($BC5-BI5)>0),$BD5*-1,0)))) -> 0 | CE5: =IF(AND($BH5="CC",($BC5-BJ5)<0),$BD5*1, IF(AND($BH5="VC",($BC5-BJ5)<0),$BD5*1, IF(AND($BH5="CP",($BC5-BJ5)>0),$BD5*-1, IF(AND($BH5="VP",($BC5-BJ5)>0),$BD5*-1,0)))) -> 0 | CF5: =IF(AND($BH5="CC",($BC5-BK5)<0),$BD5*1, IF(AND($BH5="VC",($BC5-BK5)<0),$BD5*1, IF(AND($BH5="CP",($BC5-BK5)>0),$BD5*-1, IF(AND($BH5="VP",($BC5-BK5)>0),$BD5*-1,0)))) -> 0 | CG5: =IF(AND($BH5="CC",($BC5-BL5)<0),$BD5*1, IF(AND($BH5="VC",($BC5-BL5)<0),$BD5*1, IF(AND($BH5="CP",($BC5-BL5)>0),$BD5*-1, IF(AND($BH5="VP",($BC5-BL5)>0),$BD5*-1,0)))) -> 0 | CH5: =IF(AND($BH5="CC",($BC5-BM5)<0),$BD5*1, IF(AND($BH5="VC",($BC5-BM5)<0),$BD5*1, IF(AND($BH5="CP",($BC5-BM5)>0),$BD5*-1, IF(AND($BH5="VP",($BC5-BM5)>0),$BD5*-1,0)))) -> -1360.8 | CI5: =IF(AND($BH5="CC",($BC5-BN5)<0),$BD5*1, IF(AND($BH5="VC",($BC5-BN5)<0),$BD5*1, IF(AND($BH5="CP",($BC5-BN5)>0),$BD5*-1, IF(AND($BH5="VP",($BC5-BN5)>0),$BD5*-1,0)))) -> -1360.8 | CJ5: =IF(AND($BH5="CC",($BC5-BO5)<0),$BD5*1, IF(AND($BH5="VC",($BC5-BO5)<0),$BD5*1, IF(AND($BH5="CP",($BC5-BO5)>0),$BD5*-1, IF(AND($BH5="VP",($BC5-BO5)>0),$BD5*-1,0)))) -> -1360.8 | CK5: =Tabla3[[#This Row],[Tns]] -> -1360.8 | CL5: =IF(ISERROR(VLOOKUP(VALUE(E5),'Clientes CBOT'!A:A,1,0)),"VER","ok") -> ok
A6: P | B6: R | C6: 766 | D6: 0 | E6: 13006 | F6: C | G6: O | H6: F1 | I6: .AS-0118026E | J6: 7368 | K6: 2 | L6: 50000 | M6: CALL MAY 26 SOYBEANS 1180 | N6: .16 3/4 | O6: 20251023 | Q6: 202605 | S6: F | T6: C | U6: 1180000000 | V6: 20260424 | X6: FUTUROS Y OPCIONES.C | Z6: 20251023 | AA6: 1 | AB6: 1A | AC6: S- | AF6: .16750000 | AL6: 0 | AM6: 5.0000 | AN6: USD | AO6: -434375 | AP6: 0 | AQ6: 1116750000 | AR6: 50000 | AS6: 5J23 YPc0 | AT6: 116067368 | AU6: 0,2860 | AV6: S | AW6: CBT | AX6: Comdty | AY6: Soja | AZ6: =IF(VLOOKUP(AY6,Conversor!B:C,2,0)="HS",0.01,VLOOKUP(AY6,Conversor!B:C,2,0)) -> 0.36743 | BA6: =IF(BG6="v",-AM6/10000,AL6/10000) -> -5 | BB6: =IF(AQ6=0,AP6/1000000*AZ6,AQ6/1000000*AZ6) -> 410.32745 | BC6: =U6/1000000*AZ6 -> 433.5674 | BD6: =IF(OR(E6="FUTUR",E6="f20176"),0,VLOOKUP(AY6,Conversor!G:I,3,0)*BA6) -> -680.4 | BE6: =IF(LEFT(M6,4)="call","Call",IF(LEFT(M6,3)="put","Put","Futuro")) -> Call | BF6: =IF(BE6="futuro","no","si") -> si | BG6: =IF(AL6=0,"V","C") -> V | BH6: =IF(BE6="futuro","",CONCATENATE(BG6,LEFT(BE6,1))) -> VC | BI6: =$BB6*(1+BI$2) -> 287.22922 | BJ6: =$BB6*(1+BJ$2) -> 328.26196 | BK6: =$BB6*(1+BK$2) -> 369.29471 | BL6: =$BB6*(1+BL$2) -> 410.32745 | BM6: =$BB6*(1+BM$2) -> 451.3602 | BN6: =$BB6*(1+BN$2) -> 492.39294 | BO6: =$BB6*(1+BO$2) -> 533.42569 | BP6: =IF($BE6="futuro",-($BL6-BI6)*$BD6,0) -> 0 | BQ6: =IF($BE6="futuro",-($BL6-BJ6)*$BD6,0) -> 0 | BR6: =IF($BE6="futuro",-($BL6-BK6)*$BD6,0) -> 0 | BS6: =IF($BE6="futuro",-($BL6-BL6)*$BD6,0) -> 0 | BT6: =IF($BE6="futuro",-($BL6-BM6)*$BD6,0) -> 0 | BU6: =IF($BE6="futuro",-($BL6-BN6)*$BD6,0) -> 0 | BV6: =IF($BE6="futuro",-($BL6-BO6)*$BD6,0) -> 0 | BW6: =IF(AND($BH6="CC",($BC6-BI6)<0),(BI6-$BC6)*$BD6, IF(AND($BH6="VC",($BC6-BI6)<0),($BC6-BI6)*-$BD6, IF(AND($BH6="CP",($BC6-BI6)>0),(BI6-$BC6)*$BD6*-1, IF(AND($BH6="VP",($BC6-BI6)>0),(BI6-$BC6)*$BD6*-1,0)))) -> 0 | BX6: =IF(AND($BH6="CC",($BC6-BJ6)<0),(BJ6-$BC6)*$BD6, IF(AND($BH6="VC",($BC6-BJ6)<0),($BC6-BJ6)*-$BD6, IF(AND($BH6="CP",($BC6-BJ6)>0),(BJ6-$BC6)*$BD6*-1, IF(AND($BH6="VP",($BC6-BJ6)>0),(BJ6-$BC6)*$BD6*-1,0)))) -> 0 | BY6: =IF(AND($BH6="CC",($BC6-BK6)<0),(BK6-$BC6)*$BD6, IF(AND($BH6="VC",($BC6-BK6)<0),($BC6-BK6)*-$BD6, IF(AND($BH6="CP",($BC6-BK6)>0),(BK6-$BC6)*$BD6*-1, IF(AND($BH6="VP",($BC6-BK6)>0),(BK6-$BC6)*$BD6*-1,0)))) -> 0 | BZ6: =IF(AND($BH6="CC",($BC6-BL6)<0),(BL6-$BC6)*$BD6, IF(AND($BH6="VC",($BC6-BL6)<0),($BC6-BL6)*-$BD6, IF(AND($BH6="CP",($BC6-BL6)>0),(BL6-$BC6)*$BD6*-1, IF(AND($BH6="VP",($BC6-BL6)>0),(BL6-$BC6)*$BD6*-1,0)))) -> 0 | CA6: =IF(AND($BH6="CC",($BC6-BM6)<0),(BM6-$BC6)*$BD6, IF(AND($BH6="VC",($BC6-BM6)<0),($BC6-BM6)*-$BD6, IF(AND($BH6="CP",($BC6-BM6)>0),(BM6-$BC6)*$BD6*-1, IF(AND($BH6="VP",($BC6-BM6)>0),(BM6-$BC6)*$BD6*-1,0)))) -> -12106.22 | CB6: =IF(AND($BH6="CC",($BC6-BN6)<0),(BN6-$BC6)*$BD6, IF(AND($BH6="VC",($BC6-BN6)<0),($BC6-BN6)*-$BD6, IF(AND($BH6="CP",($BC6-BN6)>0),(BN6-$BC6)*$BD6*-1, IF(AND($BH6="VP",($BC6-BN6)>0),(BN6-$BC6)*$BD6*-1,0)))) -> -40024.899 | CC6: =IF(AND($BH6="CC",($BC6-BO6)<0),(BO6-$BC6)*$BD6, IF(AND($BH6="VC",($BC6-BO6)<0),($BC6-BO6)*-$BD6, IF(AND($BH6="CP",($BC6-BO6)>0),(BO6-$BC6)*$BD6*-1, IF(AND($BH6="VP",($BC6-BO6)>0),(BO6-$BC6)*$BD6*-1,0)))) -> -67943.579 | CD6: =IF(AND($BH6="CC",($BC6-BI6)<0),$BD6*1, IF(AND($BH6="VC",($BC6-BI6)<0),$BD6*1, IF(AND($BH6="CP",($BC6-BI6)>0),$BD6*-1, IF(AND($BH6="VP",($BC6-BI6)>0),$BD6*-1,0)))) -> 0 | CE6: =IF(AND($BH6="CC",($BC6-BJ6)<0),$BD6*1, IF(AND($BH6="VC",($BC6-BJ6)<0),$BD6*1, IF(AND($BH6="CP",($BC6-BJ6)>0),$BD6*-1, IF(AND($BH6="VP",($BC6-BJ6)>0),$BD6*-1,0)))) -> 0 | CF6: =IF(AND($BH6="CC",($BC6-BK6)<0),$BD6*1, IF(AND($BH6="VC",($BC6-BK6)<0),$BD6*1, IF(AND($BH6="CP",($BC6-BK6)>0),$BD6*-1, IF(AND($BH6="VP",($BC6-BK6)>0),$BD6*-1,0)))) -> 0 | CG6: =IF(AND($BH6="CC",($BC6-BL6)<0),$BD6*1, IF(AND($BH6="VC",($BC6-BL6)<0),$BD6*1, IF(AND($BH6="CP",($BC6-BL6)>0),$BD6*-1, IF(AND($BH6="VP",($BC6-BL6)>0),$BD6*-1,0)))) -> 0 | CH6: =IF(AND($BH6="CC",($BC6-BM6)<0),$BD6*1, IF(AND($BH6="VC",($BC6-BM6)<0),$BD6*1, IF(AND($BH6="CP",($BC6-BM6)>0),$BD6*-1, IF(AND($BH6="VP",($BC6-BM6)>0),$BD6*-1,0)))) -> -680.4 | CI6: =IF(AND($BH6="CC",($BC6-BN6)<0),$BD6*1, IF(AND($BH6="VC",($BC6-BN6)<0),$BD6*1, IF(AND($BH6="CP",($BC6-BN6)>0),$BD6*-1, IF(AND($BH6="VP",($BC6-BN6)>0),$BD6*-1,0)))) -> -680.4 | CJ6: =IF(AND($BH6="CC",($BC6-BO6)<0),$BD6*1, IF(AND($BH6="VC",($BC6-BO6)<0),$BD6*1, IF(AND($BH6="CP",($BC6-BO6)>0),$BD6*-1, IF(AND($BH6="VP",($BC6-BO6)>0),$BD6*-1,0)))) -> -680.4 | CK6: =Tabla3[[#This Row],[Tns]] -> -680.4 | CL6: =IF(ISERROR(VLOOKUP(VALUE(E6),'Clientes CBOT'!A:A,1,0)),"VER","ok") -> ok
A7: P | B7: R | C7: 766 | D7: 0 | E7: 13006 | F7: C | G7: O | H7: F1 | I7: .AS-0120026E | J7: 3836 | K7: 2 | L7: 100000 | M7: CALL MAY 26 SOYBEANS 1200 | N7: .11 1/8 | O7: 20251009 | Q7: 202605 | S7: F | T7: C | U7: 1200000000 | V7: 20260424 | X7: FUTUROS Y OPCIONES.C | Z7: 20251009 | AA7: 1 | AB7: 1A | AC7: S- | AF7: .11125000 | AL7: 0 | AM7: 10.0000 | AN7: USD | AO7: -668750 | AP7: 0 | AQ7: 1116750000 | AR7: 50000 | AS7: 5J09 L0h0 | AT7: 115953836 | AU7: 0,2310 | AV7: S | AW7: CBT | AX7: Comdty | AY7: Soja | AZ7: =IF(VLOOKUP(AY7,Conversor!B:C,2,0)="HS",0.01,VLOOKUP(AY7,Conversor!B:C,2,0)) -> 0.36743 | BA7: =IF(BG7="v",-AM7/10000,AL7/10000) -> -10 | BB7: =IF(AQ7=0,AP7/1000000*AZ7,AQ7/1000000*AZ7) -> 410.32745 | BC7: =U7/1000000*AZ7 -> 440.916 | BD7: =IF(OR(E7="FUTUR",E7="f20176"),0,VLOOKUP(AY7,Conversor!G:I,3,0)*BA7) -> -1360.8 | BE7: =IF(LEFT(M7,4)="call","Call",IF(LEFT(M7,3)="put","Put","Futuro")) -> Call | BF7: =IF(BE7="futuro","no","si") -> si | BG7: =IF(AL7=0,"V","C") -> V | BH7: =IF(BE7="futuro","",CONCATENATE(BG7,LEFT(BE7,1))) -> VC | BI7: =$BB7*(1+BI$2) -> 287.22922 | BJ7: =$BB7*(1+BJ$2) -> 328.26196 | BK7: =$BB7*(1+BK$2) -> 369.29471 | BL7: =$BB7*(1+BL$2) -> 410.32745 | BM7: =$BB7*(1+BM$2) -> 451.3602 | BN7: =$BB7*(1+BN$2) -> 492.39294 | BO7: =$BB7*(1+BO$2) -> 533.42569 | BP7: =IF($BE7="futuro",-($BL7-BI7)*$BD7,0) -> 0 | BQ7: =IF($BE7="futuro",-($BL7-BJ7)*$BD7,0) -> 0 | BR7: =IF($BE7="futuro",-($BL7-BK7)*$BD7,0) -> 0 | BS7: =IF($BE7="futuro",-($BL7-BL7)*$BD7,0) -> 0 | BT7: =IF($BE7="futuro",-($BL7-BM7)*$BD7,0) -> 0 | BU7: =IF($BE7="futuro",-($BL7-BN7)*$BD7,0) -> 0 | BV7: =IF($BE7="futuro",-($BL7-BO7)*$BD7,0) -> 0 | BW7: =IF(AND($BH7="CC",($BC7-BI7)<0),(BI7-$BC7)*$BD7, IF(AND($BH7="VC",($BC7-BI7)<0),($BC7-BI7)*-$BD7, IF(AND($BH7="CP",($BC7-BI7)>0),(BI7-$BC7)*$BD7*-1, IF(AND($BH7="VP",($BC7-BI7)>0),(BI7-$BC7)*$BD7*-1,0)))) -> 0 | BX7: =IF(AND($BH7="CC",($BC7-BJ7)<0),(BJ7-$BC7)*$BD7, IF(AND($BH7="VC",($BC7-BJ7)<0),($BC7-BJ7)*-$BD7, IF(AND($BH7="CP",($BC7-BJ7)>0),(BJ7-$BC7)*$BD7*-1, IF(AND($BH7="VP",($BC7-BJ7)>0),(BJ7-$BC7)*$BD7*-1,0)))) -> 0 | BY7: =IF(AND($BH7="CC",($BC7-BK7)<0),(BK7-$BC7)*$BD7, IF(AND($BH7="VC",($BC7-BK7)<0),($BC7-BK7)*-$BD7, IF(AND($BH7="CP",($BC7-BK7)>0),(BK7-$BC7)*$BD7*-1, IF(AND($BH7="VP",($BC7-BK7)>0),(BK7-$BC7)*$BD7*-1,0)))) -> 0 | BZ7: =IF(AND($BH7="CC",($BC7-BL7)<0),(BL7-$BC7)*$BD7, IF(AND($BH7="VC",($BC7-BL7)<0),($BC7-BL7)*-$BD7, IF(AND($BH7="CP",($BC7-BL7)>0),(BL7-$BC7)*$BD7*-1, IF(AND($BH7="VP",($BC7-BL7)>0),(BL7-$BC7)*$BD7*-1,0)))) -> 0 | CA7: =IF(AND($BH7="CC",($BC7-BM7)<0),(BM7-$BC7)*$BD7, IF(AND($BH7="VC",($BC7-BM7)<0),($BC7-BM7)*-$BD7, IF(AND($BH7="CP",($BC7-BM7)>0),(BM7-$BC7)*$BD7*-1, IF(AND($BH7="VP",($BC7-BM7)>0),(BM7-$BC7)*$BD7*-1,0)))) -> -14212.464 | CB7: =IF(AND($BH7="CC",($BC7-BN7)<0),(BN7-$BC7)*$BD7, IF(AND($BH7="VC",($BC7-BN7)<0),($BC7-BN7)*-$BD7, IF(AND($BH7="CP",($BC7-BN7)>0),(BN7-$BC7)*$BD7*-1, IF(AND($BH7="VP",($BC7-BN7)>0),(BN7-$BC7)*$BD7*-1,0)))) -> -70049.824 | CC7: =IF(AND($BH7="CC",($BC7-BO7)<0),(BO7-$BC7)*$BD7, IF(AND($BH7="VC",($BC7-BO7)<0),($BC7-BO7)*-$BD7, IF(AND($BH7="CP",($BC7-BO7)>0),(BO7-$BC7)*$BD7*-1, IF(AND($BH7="VP",($BC7-BO7)>0),(BO7-$BC7)*$BD7*-1,0)))) -> -125887.18 | CD7: =IF(AND($BH7="CC",($BC7-BI7)<0),$BD7*1, IF(AND($BH7="VC",($BC7-BI7)<0),$BD7*1, IF(AND($BH7="CP",($BC7-BI7)>0),$BD7*-1, IF(AND($BH7="VP",($BC7-BI7)>0),$BD7*-1,0)))) -> 0 | CE7: =IF(AND($BH7="CC",($BC7-BJ7)<0),$BD7*1, IF(AND($BH7="VC",($BC7-BJ7)<0),$BD7*1, IF(AND($BH7="CP",($BC7-BJ7)>0),$BD7*-1, IF(AND($BH7="VP",($BC7-BJ7)>0),$BD7*-1,0)))) -> 0 | CF7: =IF(AND($BH7="CC",($BC7-BK7)<0),$BD7*1, IF(AND($BH7="VC",($BC7-BK7)<0),$BD7*1, IF(AND($BH7="CP",($BC7-BK7)>0),$BD7*-1, IF(AND($BH7="VP",($BC7-BK7)>0),$BD7*-1,0)))) -> 0 | CG7: =IF(AND($BH7="CC",($BC7-BL7)<0),$BD7*1, IF(AND($BH7="VC",($BC7-BL7)<0),$BD7*1, IF(AND($BH7="CP",($BC7-BL7)>0),$BD7*-1, IF(AND($BH7="VP",($BC7-BL7)>0),$BD7*-1,0)))) -> 0 | CH7: =IF(AND($BH7="CC",($BC7-BM7)<0),$BD7*1, IF(AND($BH7="VC",($BC7-BM7)<0),$BD7*1, IF(AND($BH7="CP",($BC7-BM7)>0),$BD7*-1, IF(AND($BH7="VP",($BC7-BM7)>0),$BD7*-1,0)))) -> -1360.8 | CI7: =IF(AND($BH7="CC",($BC7-BN7)<0),$BD7*1, IF(AND($BH7="VC",($BC7-BN7)<0),$BD7*1, IF(AND($BH7="CP",($BC7-BN7)>0),$BD7*-1, IF(AND($BH7="VP",($BC7-BN7)>0),$BD7*-1,0)))) -> -1360.8 | CJ7: =IF(AND($BH7="CC",($BC7-BO7)<0),$BD7*1, IF(AND($BH7="VC",($BC7-BO7)<0),$BD7*1, IF(AND($BH7="CP",($BC7-BO7)>0),$BD7*-1, IF(AND($BH7="VP",($BC7-BO7)>0),$BD7*-1,0)))) -> -1360.8 | CK7: =Tabla3[[#This Row],[Tns]] -> -1360.8 | CL7: =IF(ISERROR(VLOOKUP(VALUE(E7),'Clientes CBOT'!A:A,1,0)),"VER","ok") -> ok
A8: P | B8: R | C8: 766 | D8: 0 | E8: 13006 | F8: C | G8: O | H8: F1 | I8: .AS-0120026E | J8: 7394 | K8: 2 | L8: 50000 | M8: CALL MAY 26 SOYBEANS 1200 | N8: .13 3/4 | O8: 20251023 | Q8: 202605 | S8: F | T8: C | U8: 1200000000 | V8: 20260424 | X8: FUTUROS Y OPCIONES.C | Z8: 20251023 | AA8: 1 | AB8: 1A | AC8: S- | AF8: .13750000 | AL8: 0 | AM8: 5.0000 | AN8: USD | AO8: -334375 | AP8: 0 | AQ8: 1116750000 | AR8: 50000 | AS8: 5J23 YVn0 | AT8: 116067394 | AU8: 0,2310 | AV8: S | AW8: CBT | AX8: Comdty | AY8: Soja | AZ8: =IF(VLOOKUP(AY8,Conversor!B:C,2,0)="HS",0.01,VLOOKUP(AY8,Conversor!B:C,2,0)) -> 0.36743 | BA8: =IF(BG8="v",-AM8/10000,AL8/10000) -> -5 | BB8: =IF(AQ8=0,AP8/1000000*AZ8,AQ8/1000000*AZ8) -> 410.32745 | BC8: =U8/1000000*AZ8 -> 440.916 | BD8: =IF(OR(E8="FUTUR",E8="f20176"),0,VLOOKUP(AY8,Conversor!G:I,3,0)*BA8) -> -680.4 | BE8: =IF(LEFT(M8,4)="call","Call",IF(LEFT(M8,3)="put","Put","Futuro")) -> Call | BF8: =IF(BE8="futuro","no","si") -> si | BG8: =IF(AL8=0,"V","C") -> V | BH8: =IF(BE8="futuro","",CONCATENATE(BG8,LEFT(BE8,1))) -> VC | BI8: =$BB8*(1+BI$2) -> 287.22922 | BJ8: =$BB8*(1+BJ$2) -> 328.26196 | BK8: =$BB8*(1+BK$2) -> 369.29471 | BL8: =$BB8*(1+BL$2) -> 410.32745 | BM8: =$BB8*(1+BM$2) -> 451.3602 | BN8: =$BB8*(1+BN$2) -> 492.39294 | BO8: =$BB8*(1+BO$2) -> 533.42569 | BP8: =IF($BE8="futuro",-($BL8-BI8)*$BD8,0) -> 0 | BQ8: =IF($BE8="futuro",-($BL8-BJ8)*$BD8,0) -> 0 | BR8: =IF($BE8="futuro",-($BL8-BK8)*$BD8,0) -> 0 | BS8: =IF($BE8="futuro",-($BL8-BL8)*$BD8,0) -> 0 | BT8: =IF($BE8="futuro",-($BL8-BM8)*$BD8,0) -> 0 | BU8: =IF($BE8="futuro",-($BL8-BN8)*$BD8,0) -> 0 | BV8: =IF($BE8="futuro",-($BL8-BO8)*$BD8,0) -> 0 | BW8: =IF(AND($BH8="CC",($BC8-BI8)<0),(BI8-$BC8)*$BD8, IF(AND($BH8="VC",($BC8-BI8)<0),($BC8-BI8)*-$BD8, IF(AND($BH8="CP",($BC8-BI8)>0),(BI8-$BC8)*$BD8*-1, IF(AND($BH8="VP",($BC8-BI8)>0),(BI8-$BC8)*$BD8*-1,0)))) -> 0 | BX8: =IF(AND($BH8="CC",($BC8-BJ8)<0),(BJ8-$BC8)*$BD8, IF(AND($BH8="VC",($BC8-BJ8)<0),($BC8-BJ8)*-$BD8, IF(AND($BH8="CP",($BC8-BJ8)>0),(BJ8-$BC8)*$BD8*-1, IF(AND($BH8="VP",($BC8-BJ8)>0),(BJ8-$BC8)*$BD8*-1,0)))) -> 0 | BY8: =IF(AND($BH8="CC",($BC8-BK8)<0),(BK8-$BC8)*$BD8, IF(AND($BH8="VC",($BC8-BK8)<0),($BC8-BK8)*-$BD8, IF(AND($BH8="CP",($BC8-BK8)>0),(BK8-$BC8)*$BD8*-1, IF(AND($BH8="VP",($BC8-BK8)>0),(BK8-$BC8)*$BD8*-1,0)))) -> 0 | BZ8: =IF(AND($BH8="CC",($BC8-BL8)<0),(BL8-$BC8)*$BD8, IF(AND($BH8="VC",($BC8-BL8)<0),($BC8-BL8)*-$BD8, IF(AND($BH8="CP",($BC8-BL8)>0),(BL8-$BC8)*$BD8*-1, IF(AND($BH8="VP",($BC8-BL8)>0),(BL8-$BC8)*$BD8*-1,0)))) -> 0 | CA8: =IF(AND($BH8="CC",($BC8-BM8)<0),(BM8-$BC8)*$BD8, IF(AND($BH8="VC",($BC8-BM8)<0),($BC8-BM8)*-$BD8, IF(AND($BH8="CP",($BC8-BM8)>0),(BM8-$BC8)*$BD8*-1, IF(AND($BH8="VP",($BC8-BM8)>0),(BM8-$BC8)*$BD8*-1,0)))) -> -7106.2321 | CB8: =IF(AND($BH8="CC",($BC8-BN8)<0),(BN8-$BC8)*$BD8, IF(AND($BH8="VC",($BC8-BN8)<0),($BC8-BN8)*-$BD8, IF(AND($BH8="CP",($BC8-BN8)>0),(BN8-$BC8)*$BD8*-1, IF(AND($BH8="VP",($BC8-BN8)>0),(BN8-$BC8)*$BD8*-1,0)))) -> -35024.912 | CC8: =IF(AND($BH8="CC",($BC8-BO8)<0),(BO8-$BC8)*$BD8, IF(AND($BH8="VC",($BC8-BO8)<0),($BC8-BO8)*-$BD8, IF(AND($BH8="CP",($BC8-BO8)>0),(BO8-$BC8)*$BD8*-1, IF(AND($BH8="VP",($BC8-BO8)>0),(BO8-$BC8)*$BD8*-1,0)))) -> -62943.592 | CD8: =IF(AND($BH8="CC",($BC8-BI8)<0),$BD8*1, IF(AND($BH8="VC",($BC8-BI8)<0),$BD8*1, IF(AND($BH8="CP",($BC8-BI8)>0),$BD8*-1, IF(AND($BH8="VP",($BC8-BI8)>0),$BD8*-1,0)))) -> 0 | CE8: =IF(AND($BH8="CC",($BC8-BJ8)<0),$BD8*1, IF(AND($BH8="VC",($BC8-BJ8)<0),$BD8*1, IF(AND($BH8="CP",($BC8-BJ8)>0),$BD8*-1, IF(AND($BH8="VP",($BC8-BJ8)>0),$BD8*-1,0)))) -> 0 | CF8: =IF(AND($BH8="CC",($BC8-BK8)<0),$BD8*1, IF(AND($BH8="VC",($BC8-BK8)<0),$BD8*1, IF(AND($BH8="CP",($BC8-BK8)>0),$BD8*-1, IF(AND($BH8="VP",($BC8-BK8)>0),$BD8*-1,0)))) -> 0 | CG8: =IF(AND($BH8="CC",($BC8-BL8)<0),$BD8*1, IF(AND($BH8="VC",($BC8-BL8)<0),$BD8*1, IF(AND($BH8="CP",($BC8-BL8)>0),$BD8*-1, IF(AND($BH8="VP",($BC8-BL8)>0),$BD8*-1,0)))) -> 0 | CH8: =IF(AND($BH8="CC",($BC8-BM8)<0),$BD8*1, IF(AND($BH8="VC",($BC8-BM8)<0),$BD8*1, IF(AND($BH8="CP",($BC8-BM8)>0),$BD8*-1, IF(AND($BH8="VP",($BC8-BM8)>0),$BD8*-1,0)))) -> -680.4 | CI8: =IF(AND($BH8="CC",($BC8-BN8)<0),$BD8*1, IF(AND($BH8="VC",($BC8-BN8)<0),$BD8*1, IF(AND($BH8="CP",($BC8-BN8)>0),$BD8*-1, IF(AND($BH8="VP",($BC8-BN8)>0),$BD8*-1,0)))) -> -680.4 | CJ8: =IF(AND($BH8="CC",($BC8-BO8)<0),$BD8*1, IF(AND($BH8="VC",($BC8-BO8)<0),$BD8*1, IF(AND($BH8="CP",($BC8-BO8)>0),$BD8*-1, IF(AND($BH8="VP",($BC8-BO8)>0),$BD8*-1,0)))) -> -680.4 | CK8: =Tabla3[[#This Row],[Tns]] -> -680.4 | CL8: =IF(ISERROR(VLOOKUP(VALUE(E8),'Clientes CBOT'!A:A,1,0)),"VER","ok") -> ok
A9: P | B9: R | C9: 766 | D9: 0 | E9: 13006 | F9: C | G9: O | H9: F1 | I9: .AS-0122026E | J9: 8416 | K9: 2 | L9: 130000 | M9: CALL MAY 26 SOYBEANS 1220 | N9: .30 1/2 | O9: 20251118 | Q9: 202605 | S9: F | T9: C | U9: 1220000000 | V9: 20260424 | X9: FUTUROS Y OPCIONES.C | Z9: 20251118 | AA9: 1 | AB9: 1A | AC9: S- | AF9: .30500000 | AL9: 0 | AM9: 13.0000 | AN9: USD | AO9: -674375 | AP9: 0 | AQ9: 1116750000 | AR9: 50000 | AS9: 5K18 WeL0 | AT9: 116298416 | AU9: 0,1860 | AV9: S | AW9: CBT | AX9: Comdty | AY9: Soja | AZ9: =IF(VLOOKUP(AY9,Conversor!B:C,2,0)="HS",0.01,VLOOKUP(AY9,Conversor!B:C,2,0)) -> 0.36743 | BA9: =IF(BG9="v",-AM9/10000,AL9/10000) -> -13 | BB9: =IF(AQ9=0,AP9/1000000*AZ9,AQ9/1000000*AZ9) -> 410.32745 | BC9: =U9/1000000*AZ9 -> 448.2646 | BD9: =IF(OR(E9="FUTUR",E9="f20176"),0,VLOOKUP(AY9,Conversor!G:I,3,0)*BA9) -> -1769.04 | BE9: =IF(LEFT(M9,4)="call","Call",IF(LEFT(M9,3)="put","Put","Futuro")) -> Call | BF9: =IF(BE9="futuro","no","si") -> si | BG9: =IF(AL9=0,"V","C") -> V | BH9: =IF(BE9="futuro","",CONCATENATE(BG9,LEFT(BE9,1))) -> VC | BI9: =$BB9*(1+BI$2) -> 287.22922 | BJ9: =$BB9*(1+BJ$2) -> 328.26196 | BK9: =$BB9*(1+BK$2) -> 369.29471 | BL9: =$BB9*(1+BL$2) -> 410.32745 | BM9: =$BB9*(1+BM$2) -> 451.3602 | BN9: =$BB9*(1+BN$2) -> 492.39294 | BO9: =$BB9*(1+BO$2) -> 533.42569 | BP9: =IF($BE9="futuro",-($BL9-BI9)*$BD9,0) -> 0 | BQ9: =IF($BE9="futuro",-($BL9-BJ9)*$BD9,0) -> 0 | BR9: =IF($BE9="futuro",-($BL9-BK9)*$BD9,0) -> 0 | BS9: =IF($BE9="futuro",-($BL9-BL9)*$BD9,0) -> 0 | BT9: =IF($BE9="futuro",-($BL9-BM9)*$BD9,0) -> 0 | BU9: =IF($BE9="futuro",-($BL9-BN9)*$BD9,0) -> 0 | BV9: =IF($BE9="futuro",-($BL9-BO9)*$BD9,0) -> 0 | BW9: =IF(AND($BH9="CC",($BC9-BI9)<0),(BI9-$BC9)*$BD9, IF(AND($BH9="VC",($BC9-BI9)<0),($BC9-BI9)*-$BD9, IF(AND($BH9="CP",($BC9-BI9)>0),(BI9-$BC9)*$BD9*-1, IF(AND($BH9="VP",($BC9-BI9)>0),(BI9-$BC9)*$BD9*-1,0)))) -> 0 | BX9: =IF(AND($BH9="CC",($BC9-BJ9)<0),(BJ9-$BC9)*$BD9, IF(AND($BH9="VC",($BC9-BJ9)<0),($BC9-BJ9)*-$BD9, IF(AND($BH9="CP",($BC9-BJ9)>0),(BJ9-$BC9)*$BD9*-1, IF(AND($BH9="VP",($BC9-BJ9)>0),(BJ9-$BC9)*$BD9*-1,0)))) -> 0 | BY9: =IF(AND($BH9="CC",($BC9-BK9)<0),(BK9-$BC9)*$BD9, IF(AND($BH9="VC",($BC9-BK9)<0),($BC9-BK9)*-$BD9, IF(AND($BH9="CP",($BC9-BK9)>0),(BK9-$BC9)*$BD9*-1, IF(AND($BH9="VP",($BC9-BK9)>0),(BK9-$BC9)*$BD9*-1,0)))) -> 0 | BZ9: =IF(AND($BH9="CC",($BC9-BL9)<0),(BL9-$BC9)*$BD9, IF(AND($BH9="VC",($BC9-BL9)<0),($BC9-BL9)*-$BD9, IF(AND($BH9="CP",($BC9-BL9)>0),(BL9-$BC9)*$BD9*-1, IF(AND($BH9="VP",($BC9-BL9)>0),(BL9-$BC9)*$BD9*-1,0)))) -> 0 | CA9: =IF(AND($BH9="CC",($BC9-BM9)<0),(BM9-$BC9)*$BD9, IF(AND($BH9="VC",($BC9-BM9)<0),($BC9-BM9)*-$BD9, IF(AND($BH9="CP",($BC9-BM9)>0),(BM9-$BC9)*$BD9*-1, IF(AND($BH9="VP",($BC9-BM9)>0),(BM9-$BC9)*$BD9*-1,0)))) -> -5476.2362 | CB9: =IF(AND($BH9="CC",($BC9-BN9)<0),(BN9-$BC9)*$BD9, IF(AND($BH9="VC",($BC9-BN9)<0),($BC9-BN9)*-$BD9, IF(AND($BH9="CP",($BC9-BN9)>0),(BN9-$BC9)*$BD9*-1, IF(AND($BH9="VP",($BC9-BN9)>0),(BN9-$BC9)*$BD9*-1,0)))) -> -78064.804 | CC9: =IF(AND($BH9="CC",($BC9-BO9)<0),(BO9-$BC9)*$BD9, IF(AND($BH9="VC",($BC9-BO9)<0),($BC9-BO9)*-$BD9, IF(AND($BH9="CP",($BC9-BO9)>0),(BO9-$BC9)*$BD9*-1, IF(AND($BH9="VP",($BC9-BO9)>0),(BO9-$BC9)*$BD9*-1,0)))) -> -150653.37 | CD9: =IF(AND($BH9="CC",($BC9-BI9)<0),$BD9*1, IF(AND($BH9="VC",($BC9-BI9)<0),$BD9*1, IF(AND($BH9="CP",($BC9-BI9)>0),$BD9*-1, IF(AND($BH9="VP",($BC9-BI9)>0),$BD9*-1,0)))) -> 0 | CE9: =IF(AND($BH9="CC",($BC9-BJ9)<0),$BD9*1, IF(AND($BH9="VC",($BC9-BJ9)<0),$BD9*1, IF(AND($BH9="CP",($BC9-BJ9)>0),$BD9*-1, IF(AND($BH9="VP",($BC9-BJ9)>0),$BD9*-1,0)))) -> 0 | CF9: =IF(AND($BH9="CC",($BC9-BK9)<0),$BD9*1, IF(AND($BH9="VC",($BC9-BK9)<0),$BD9*1, IF(AND($BH9="CP",($BC9-BK9)>0),$BD9*-1, IF(AND($BH9="VP",($BC9-BK9)>0),$BD9*-1,0)))) -> 0 | CG9: =IF(AND($BH9="CC",($BC9-BL9)<0),$BD9*1, IF(AND($BH9="VC",($BC9-BL9)<0),$BD9*1, IF(AND($BH9="CP",($BC9-BL9)>0),$BD9*-1, IF(AND($BH9="VP",($BC9-BL9)>0),$BD9*-1,0)))) -> 0 | CH9: =IF(AND($BH9="CC",($BC9-BM9)<0),$BD9*1, IF(AND($BH9="VC",($BC9-BM9)<0),$BD9*1, IF(AND($BH9="CP",($BC9-BM9)>0),$BD9*-1, IF(AND($BH9="VP",($BC9-BM9)>0),$BD9*-1,0)))) -> -1769.04 | CI9: =IF(AND($BH9="CC",($BC9-BN9)<0),$BD9*1, IF(AND($BH9="VC",($BC9-BN9)<0),$BD9*1, IF(AND($BH9="CP",($BC9-BN9)>0),$BD9*-1, IF(AND($BH9="VP",($BC9-BN9)>0),$BD9*-1,0)))) -> -1769.04 | CJ9: =IF(AND($BH9="CC",($BC9-BO9)<0),$BD9*1, IF(AND($BH9="VC",($BC9-BO9)<0),$BD9*1, IF(AND($BH9="CP",($BC9-BO9)>0),$BD9*-1, IF(AND($BH9="VP",($BC9-BO9)>0),$BD9*-1,0)))) -> -1769.04 | CK9: =Tabla3[[#This Row],[Tns]] -> -1769.04 | CL9: =IF(ISERROR(VLOOKUP(VALUE(E9),'Clientes CBOT'!A:A,1,0)),"VER","ok") -> ok
A10: P | B10: R | C10: 766 | D10: 0 | E10: 13006 | F10: C | G10: O | H10: F1 | I10: .AS-0122026E | J10: 4956 | K10: 2 | L10: 100000 | M10: CALL MAY 26 SOYBEANS 1220 | N10: .31 | O10: 20251118 | Q10: 202605 | S10: F | T10: C | U10: 1220000000 | V10: 20260424 | X10: FUTUROS Y OPCIONES.C | Z10: 20251118 | AA10: 1 | AB10: 1A | AC10: S- | AF10: .31000000 | AL10: 0 | AM10: 10.0000 | AN10: USD | AO10: -518750 | AP10: 0 | AQ10: 1116750000 | AR10: 50000 | AS10: 5K18 JH90 | AT10: 116294956 | AU10: 0,1860 | AV10: S | AW10: CBT | AX10: Comdty | AY10: Soja | AZ10: =IF(VLOOKUP(AY10,Conversor!B:C,2,0)="HS",0.01,VLOOKUP(AY10,Conversor!B:C,2,0)) -> 0.36743 | BA10: =IF(BG10="v",-AM10/10000,AL10/10000) -> -10 | BB10: =IF(AQ10=0,AP10/1000000*AZ10,AQ10/1000000*AZ10) -> 410.32745 | BC10: =U10/1000000*AZ10 -> 448.2646 | BD10: =IF(OR(E10="FUTUR",E10="f20176"),0,VLOOKUP(AY10,Conversor!G:I,3,0)*BA10) -> -1360.8 | BE10: =IF(LEFT(M10,4)="call","Call",IF(LEFT(M10,3)="put","Put","Futuro")) -> Call | BF10: =IF(BE10="futuro","no","si") -> si | BG10: =IF(AL10=0,"V","C") -> V | BH10: =IF(BE10="futuro","",CONCATENATE(BG10,LEFT(BE10,1))) -> VC | BI10: =$BB10*(1+BI$2) -> 287.22922 | BJ10: =$BB10*(1+BJ$2) -> 328.26196 | BK10: =$BB10*(1+BK$2) -> 369.29471 | BL10: =$BB10*(1+BL$2) -> 410.32745 | BM10: =$BB10*(1+BM$2) -> 451.3602 | BN10: =$BB10*(1+BN$2) -> 492.39294 | BO10: =$BB10*(1+BO$2) -> 533.42569 | BP10: =IF($BE10="futuro",-($BL10-BI10)*$BD10,0) -> 0 | BQ10: =IF($BE10="futuro",-($BL10-BJ10)*$BD10,0) -> 0 | BR10: =IF($BE10="futuro",-($BL10-BK10)*$BD10,0) -> 0 | BS10: =IF($BE10="futuro",-($BL10-BL10)*$BD10,0) -> 0 | BT10: =IF($BE10="futuro",-($BL10-BM10)*$BD10,0) -> 0 | BU10: =IF($BE10="futuro",-($BL10-BN10)*$BD10,0) -> 0 | BV10: =IF($BE10="futuro",-($BL10-BO10)*$BD10,0) -> 0 | BW10: =IF(AND($BH10="CC",($BC10-BI10)<0),(BI10-$BC10)*$BD10, IF(AND($BH10="VC",($BC10-BI10)<0),($BC10-BI10)*-$BD10, IF(AND($BH10="CP",($BC10-BI10)>0),(BI10-$BC10)*$BD10*-1, IF(AND($BH10="VP",($BC10-BI10)>0),(BI10-$BC10)*$BD10*-1,0)))) -> 0 | BX10: =IF(AND($BH10="CC",($BC10-BJ10)<0),(BJ10-$BC10)*$BD10, IF(AND($BH10="VC",($BC10-BJ10)<0),($BC10-BJ10)*-$BD10, IF(AND($BH10="CP",($BC10-BJ10)>0),(BJ10-$BC10)*$BD10*-1, IF(AND($BH10="VP",($BC10-BJ10)>0),(BJ10-$BC10)*$BD10*-1,0)))) -> 0 | BY10: =IF(AND($BH10="CC",($BC10-BK10)<0),(BK10-$BC10)*$BD10, IF(AND($BH10="VC",($BC10-BK10)<0),($BC10-BK10)*-$BD10, IF(AND($BH10="CP",($BC10-BK10)>0),(BK10-$BC10)*$BD10*-1, IF(AND($BH10="VP",($BC10-BK10)>0),(BK10-$BC10)*$BD10*-1,0)))) -> 0 | BZ10: =IF(AND($BH10="CC",($BC10-BL10)<0),(BL10-$BC10)*$BD10, IF(AND($BH10="VC",($BC10-BL10)<0),($BC10-BL10)*-$BD10, IF(AND($BH10="CP",($BC10-BL10)>0),(BL10-$BC10)*$BD10*-1, IF(AND($BH10="VP",($BC10-BL10)>0),(BL10-$BC10)*$BD10*-1,0)))) -> 0 | CA10: =IF(AND($BH10="CC",($BC10-BM10)<0),(BM10-$BC10)*$BD10, IF(AND($BH10="VC",($BC10-BM10)<0),($BC10-BM10)*-$BD10, IF(AND($BH10="CP",($BC10-BM10)>0),(BM10-$BC10)*$BD10*-1, IF(AND($BH10="VP",($BC10-BM10)>0),(BM10-$BC10)*$BD10*-1,0)))) -> -4212.4894 | CB10: =IF(AND($BH10="CC",($BC10-BN10)<0),(BN10-$BC10)*$BD10, IF(AND($BH10="VC",($BC10-BN10)<0),($BC10-BN10)*-$BD10, IF(AND($BH10="CP",($BC10-BN10)>0),(BN10-$BC10)*$BD10*-1, IF(AND($BH10="VP",($BC10-BN10)>0),(BN10-$BC10)*$BD10*-1,0)))) -> -60049.849 | CC10: =IF(AND($BH10="CC",($BC10-BO10)<0),(BO10-$BC10)*$BD10, IF(AND($BH10="VC",($BC10-BO10)<0),($BC10-BO10)*-$BD10, IF(AND($BH10="CP",($BC10-BO10)>0),(BO10-$BC10)*$BD10*-1, IF(AND($BH10="VP",($BC10-BO10)>0),(BO10-$BC10)*$BD10*-1,0)))) -> -115887.21 | CD10: =IF(AND($BH10="CC",($BC10-BI10)<0),$BD10*1, IF(AND($BH10="VC",($BC10-BI10)<0),$BD10*1, IF(AND($BH10="CP",($BC10-BI10)>0),$BD10*-1, IF(AND($BH10="VP",($BC10-BI10)>0),$BD10*-1,0)))) -> 0 | CE10: =IF(AND($BH10="CC",($BC10-BJ10)<0),$BD10*1, IF(AND($BH10="VC",($BC10-BJ10)<0),$BD10*1, IF(AND($BH10="CP",($BC10-BJ10)>0),$BD10*-1, IF(AND($BH10="VP",($BC10-BJ10)>0),$BD10*-1,0)))) -> 0 | CF10: =IF(AND($BH10="CC",($BC10-BK10)<0),$BD10*1, IF(AND($BH10="VC",($BC10-BK10)<0),$BD10*1, IF(AND($BH10="CP",($BC10-BK10)>0),$BD10*-1, IF(AND($BH10="VP",($BC10-BK10)>0),$BD10*-1,0)))) -> 0 | CG10: =IF(AND($BH10="CC",($BC10-BL10)<0),$BD10*1, IF(AND($BH10="VC",($BC10-BL10)<0),$BD10*1, IF(AND($BH10="CP",($BC10-BL10)>0),$BD10*-1, IF(AND($BH10="VP",($BC10-BL10)>0),$BD10*-1,0)))) -> 0 | CH10: =IF(AND($BH10="CC",($BC10-BM10)<0),$BD10*1, IF(AND($BH10="VC",($BC10-BM10)<0),$BD10*1, IF(AND($BH10="CP",($BC10-BM10)>0),$BD10*-1, IF(AND($BH10="VP",($BC10-BM10)>0),$BD10*-1,0)))) -> -1360.8 | CI10: =IF(AND($BH10="CC",($BC10-BN10)<0),$BD10*1, IF(AND($BH10="VC",($BC10-BN10)<0),$BD10*1, IF(AND($BH10="CP",($BC10-BN10)>0),$BD10*-1, IF(AND($BH10="VP",($BC10-BN10)>0),$BD10*-1,0)))) -> -1360.8 | CJ10: =IF(AND($BH10="CC",($BC10-BO10)<0),$BD10*1, IF(AND($BH10="VC",($BC10-BO10)<0),$BD10*1, IF(AND($BH10="CP",($BC10-BO10)>0),$BD10*-1, IF(AND($BH10="VP",($BC10-BO10)>0),$BD10*-1,0)))) -> -1360.8 | CK10: =Tabla3[[#This Row],[Tns]] -> -1360.8 | CL10: =IF(ISERROR(VLOOKUP(VALUE(E10),'Clientes CBOT'!A:A,1,0)),"VER","ok") -> ok
A11: P | B11: R | C11: 766 | D11: 0 | E11: 13007 | F11: C | G11: O | H11: F1 | I11: .AS-0115026C | J11: 9710 | K11: 2 | L11: 100000 | M11: CALL MAR 26 SOYBEANS 1150 | N11: .17 1/8 | O11: 20251205 | Q11: 202603 | S11: F | T11: C | U11: 1150000000 | V11: 20260220 | X11: FUTUROS Y OPCIONES.C | Z11: 20251205 | AA11: 1 | AB11: 1A | AC11: S- | AF11: .17125000 | AL11: 0 | AM11: 10.0000 | AN11: USD | AO11: -637500 | AP11: 0 | AQ11: 1105750000 | AR11: 50000 | AS11: 5L05 G9k0 | AT11: 116429710 | AU11: 0,2870 | AV11: S | AW11: CBT | AX11: Comdty | AY11: Soja | AZ11: =IF(VLOOKUP(AY11,Conversor!B:C,2,0)="HS",0.01,VLOOKUP(AY11,Conversor!B:C,2,0)) -> 0.36743 | BA11: =IF(BG11="v",-AM11/10000,AL11/10000) -> -10 | BB11: =IF(AQ11=0,AP11/1000000*AZ11,AQ11/1000000*AZ11) -> 406.28572 | BC11: =U11/1000000*AZ11 -> 422.5445 | BD11: =IF(OR(E11="FUTUR",E11="f20176"),0,VLOOKUP(AY11,Conversor!G:I,3,0)*BA11) -> -1360.8 | BE11: =IF(LEFT(M11,4)="call","Call",IF(LEFT(M11,3)="put","Put","Futuro")) -> Call | BF11: =IF(BE11="futuro","no","si") -> si | BG11: =IF(AL11=0,"V","C") -> V | BH11: =IF(BE11="futuro","",CONCATENATE(BG11,LEFT(BE11,1))) -> VC | BI11: =$BB11*(1+BI$2) -> 284.40001 | BJ11: =$BB11*(1+BJ$2) -> 325.02858 | BK11: =$BB11*(1+BK$2) -> 365.65715 | BL11: =$BB11*(1+BL$2) -> 406.28572 | BM11: =$BB11*(1+BM$2) -> 446.91429 | BN11: =$BB11*(1+BN$2) -> 487.54287 | BO11: =$BB11*(1+BO$2) -> 528.17144 | BP11: =IF($BE11="futuro",-($BL11-BI11)*$BD11,0) -> 0 | BQ11: =IF($BE11="futuro",-($BL11-BJ11)*$BD11,0) -> 0 | BR11: =IF($BE11="futuro",-($BL11-BK11)*$BD11,0) -> 0 | BS11: =IF($BE11="futuro",-($BL11-BL11)*$BD11,0) -> 0 | BT11: =IF($BE11="futuro",-($BL11-BM11)*$BD11,0) -> 0 | BU11: =IF($BE11="futuro",-($BL11-BN11)*$BD11,0) -> 0 | BV11: =IF($BE11="futuro",-($BL11-BO11)*$BD11,0) -> 0 | BW11: =IF(AND($BH11="CC",($BC11-BI11)<0),(BI11-$BC11)*$BD11, IF(AND($BH11="VC",($BC11-BI11)<0),($BC11-BI11)*-$BD11, IF(AND($BH11="CP",($BC11-BI11)>0),(BI11-$BC11)*$BD11*-1, IF(AND($BH11="VP",($BC11-BI11)>0),(BI11-$BC11)*$BD11*-1,0)))) -> 0 | BX11: =IF(AND($BH11="CC",($BC11-BJ11)<0),(BJ11-$BC11)*$BD11, IF(AND($BH11="VC",($BC11-BJ11)<0),($BC11-BJ11)*-$BD11, IF(AND($BH11="CP",($BC11-BJ11)>0),(BJ11-$BC11)*$BD11*-1, IF(AND($BH11="VP",($BC11-BJ11)>0),(BJ11-$BC11)*$BD11*-1,0)))) -> 0 | BY11: =IF(AND($BH11="CC",($BC11-BK11)<0),(BK11-$BC11)*$BD11, IF(AND($BH11="VC",($BC11-BK11)<0),($BC11-BK11)*-$BD11, IF(AND($BH11="CP",($BC11-BK11)>0),(BK11-$BC11)*$BD11*-1, IF(AND($BH11="VP",($BC11-BK11)>0),(BK11-$BC11)*$BD11*-1,0)))) -> 0 | BZ11: =IF(AND($BH11="CC",($BC11-BL11)<0),(BL11-$BC11)*$BD11, IF(AND($BH11="VC",($BC11-BL11)<0),($BC11-BL11)*-$BD11, IF(AND($BH11="CP",($BC11-BL11)>0),(BL11-$BC11)*$BD11*-1, IF(AND($BH11="VP",($BC11-BL11)>0),(BL11-$BC11)*$BD11*-1,0)))) -> 0 | CA11: =IF(AND($BH11="CC",($BC11-BM11)<0),(BM11-$BC11)*$BD11, IF(AND($BH11="VC",($BC11-BM11)<0),($BC11-BM11)*-$BD11, IF(AND($BH11="CP",($BC11-BM11)>0),(BM11-$BC11)*$BD11*-1, IF(AND($BH11="VP",($BC11-BM11)>0),(BM11-$BC11)*$BD11*-1,0)))) -> -33162.417 | CB11: =IF(AND($BH11="CC",($BC11-BN11)<0),(BN11-$BC11)*$BD11, IF(AND($BH11="VC",($BC11-BN11)<0),($BC11-BN11)*-$BD11, IF(AND($BH11="CP",($BC11-BN11)>0),(BN11-$BC11)*$BD11*-1, IF(AND($BH11="VP",($BC11-BN11)>0),(BN11-$BC11)*$BD11*-1,0)))) -> -88449.778 | CC11: =IF(AND($BH11="CC",($BC11-BO11)<0),(BO11-$BC11)*$BD11, IF(AND($BH11="VC",($BC11-BO11)<0),($BC11-BO11)*-$BD11, IF(AND($BH11="CP",($BC11-BO11)>0),(BO11-$BC11)*$BD11*-1, IF(AND($BH11="VP",($BC11-BO11)>0),(BO11-$BC11)*$BD11*-1,0)))) -> -143737.14 | CD11: =IF(AND($BH11="CC",($BC11-BI11)<0),$BD11*1, IF(AND($BH11="VC",($BC11-BI11)<0),$BD11*1, IF(AND($BH11="CP",($BC11-BI11)>0),$BD11*-1, IF(AND($BH11="VP",($BC11-BI11)>0),$BD11*-1,0)))) -> 0 | CE11: =IF(AND($BH11="CC",($BC11-BJ11)<0),$BD11*1, IF(AND($BH11="VC",($BC11-BJ11)<0),$BD11*1, IF(AND($BH11="CP",($BC11-BJ11)>0),$BD11*-1, IF(AND($BH11="VP",($BC11-BJ11)>0),$BD11*-1,0)))) -> 0 | CF11: =IF(AND($BH11="CC",($BC11-BK11)<0),$BD11*1, IF(AND($BH11="VC",($BC11-BK11)<0),$BD11*1, IF(AND($BH11="CP",($BC11-BK11)>0),$BD11*-1, IF(AND($BH11="VP",($BC11-BK11)>0),$BD11*-1,0)))) -> 0 | CG11: =IF(AND($BH11="CC",($BC11-BL11)<0),$BD11*1, IF(AND($BH11="VC",($BC11-BL11)<0),$BD11*1, IF(AND($BH11="CP",($BC11-BL11)>0),$BD11*-1, IF(AND($BH11="VP",($BC11-BL11)>0),$BD11*-1,0)))) -> 0 | CH11: =IF(AND($BH11="CC",($BC11-BM11)<0),$BD11*1, IF(AND($BH11="VC",($BC11-BM11)<0),$BD11*1, IF(AND($BH11="CP",($BC11-BM11)>0),$BD11*-1, IF(AND($BH11="VP",($BC11-BM11)>0),$BD11*-1,0)))) -> -1360.8 | CI11: =IF(AND($BH11="CC",($BC11-BN11)<0),$BD11*1, IF(AND($BH11="VC",($BC11-BN11)<0),$BD11*1, IF(AND($BH11="CP",($BC11-BN11)>0),$BD11*-1, IF(AND($BH11="VP",($BC11-BN11)>0),$BD11*-1,0)))) -> -1360.8 | CJ11: =IF(AND($BH11="CC",($BC11-BO11)<0),$BD11*1, IF(AND($BH11="VC",($BC11-BO11)<0),$BD11*1, IF(AND($BH11="CP",($BC11-BO11)>0),$BD11*-1, IF(AND($BH11="VP",($BC11-BO11)>0),$BD11*-1,0)))) -> -1360.8 | CK11: =Tabla3[[#This Row],[Tns]] -> -1360.8 | CL11: =IF(ISERROR(VLOOKUP(VALUE(E11),'Clientes CBOT'!A:A,1,0)),"VER","ok") -> ok
A12: P | B12: R | C12: 766 | D12: 0 | E12: 13007 | F12: C | G12: O | H12: F1 | I12: .AS-0118026E | J12: 3802 | K12: 2 | L12: 100000 | M12: CALL MAY 26 SOYBEANS 1180 | N12: .13 1/2 | O12: 20251009 | Q12: 202605 | S12: F | T12: C | U12: 1180000000 | V12: 20260424 | X12: FUTUROS Y OPCIONES.C | Z12: 20251009 | AA12: 1 | AB12: 1A | AC12: S- | AF12: .13500000 | AL12: 0 | AM12: 10.0000 | AN12: USD | AO12: -868750 | AP12: 0 | AQ12: 1116750000 | AR12: 50000 | AS12: 5J09 MKX0 | AT12: 115953802 | AU12: 0,2860 | AV12: S | AW12: CBT | AX12: Comdty | AY12: Soja | AZ12: =IF(VLOOKUP(AY12,Conversor!B:C,2,0)="HS",0.01,VLOOKUP(AY12,Conversor!B:C,2,0)) -> 0.36743 | BA12: =IF(BG12="v",-AM12/10000,AL12/10000) -> -10 | BB12: =IF(AQ12=0,AP12/1000000*AZ12,AQ12/1000000*AZ12) -> 410.32745 | BC12: =U12/1000000*AZ12 -> 433.5674 | BD12: =IF(OR(E12="FUTUR",E12="f20176"),0,VLOOKUP(AY12,Conversor!G:I,3,0)*BA12) -> -1360.8 | BE12: =IF(LEFT(M12,4)="call","Call",IF(LEFT(M12,3)="put","Put","Futuro")) -> Call | BF12: =IF(BE12="futuro","no","si") -> si | BG12: =IF(AL12=0,"V","C") -> V | BH12: =IF(BE12="futuro","",CONCATENATE(BG12,LEFT(BE12,1))) -> VC | BI12: =$BB12*(1+BI$2) -> 287.22922 | BJ12: =$BB12*(1+BJ$2) -> 328.26196 | BK12: =$BB12*(1+BK$2) -> 369.29471 | BL12: =$BB12*(1+BL$2) -> 410.32745 | BM12: =$BB12*(1+BM$2) -> 451.3602 | BN12: =$BB12*(1+BN$2) -> 492.39294 | BO12: =$BB12*(1+BO$2) -> 533.42569 | BP12: =IF($BE12="futuro",-($BL12-BI12)*$BD12,0) -> 0 | BQ12: =IF($BE12="futuro",-($BL12-BJ12)*$BD12,0) -> 0 | BR12: =IF($BE12="futuro",-($BL12-BK12)*$BD12,0) -> 0 | BS12: =IF($BE12="futuro",-($BL12-BL12)*$BD12,0) -> 0 | BT12: =IF($BE12="futuro",-($BL12-BM12)*$BD12,0) -> 0 | BU12: =IF($BE12="futuro",-($BL12-BN12)*$BD12,0) -> 0 | BV12: =IF($BE12="futuro",-($BL12-BO12)*$BD12,0) -> 0 | BW12: =IF(AND($BH12="CC",($BC12-BI12)<0),(BI12-$BC12)*$BD12, IF(AND($BH12="VC",($BC12-BI12)<0),($BC12-BI12)*-$BD12, IF(AND($BH12="CP",($BC12-BI12)>0),(BI12-$BC12)*$BD12*-1, IF(AND($BH12="VP",($BC12-BI12)>0),(BI12-$BC12)*$BD12*-1,0)))) -> 0 | BX12: =IF(AND($BH12="CC",($BC12-BJ12)<0),(BJ12-$BC12)*$BD12, IF(AND($BH12="VC",($BC12-BJ12)<0),($BC12-BJ12)*-$BD12, IF(AND($BH12="CP",($BC12-BJ12)>0),(BJ12-$BC12)*$BD12*-1, IF(AND($BH12="VP",($BC12-BJ12)>0),(BJ12-$BC12)*$BD12*-1,0)))) -> 0 | BY12: =IF(AND($BH12="CC",($BC12-BK12)<0),(BK12-$BC12)*$BD12, IF(AND($BH12="VC",($BC12-BK12)<0),($BC12-BK12)*-$BD12, IF(AND($BH12="CP",($BC12-BK12)>0),(BK12-$BC12)*$BD12*-1, IF(AND($BH12="VP",($BC12-BK12)>0),(BK12-$BC12)*$BD12*-1,0)))) -> 0 | BZ12: =IF(AND($BH12="CC",($BC12-BL12)<0),(BL12-$BC12)*$BD12, IF(AND($BH12="VC",($BC12-BL12)<0),($BC12-BL12)*-$BD12, IF(AND($BH12="CP",($BC12-BL12)>0),(BL12-$BC12)*$BD12*-1, IF(AND($BH12="VP",($BC12-BL12)>0),(BL12-$BC12)*$BD12*-1,0)))) -> 0 | CA12: =IF(AND($BH12="CC",($BC12-BM12)<0),(BM12-$BC12)*$BD12, IF(AND($BH12="VC",($BC12-BM12)<0),($BC12-BM12)*-$BD12, IF(AND($BH12="CP",($BC12-BM12)>0),(BM12-$BC12)*$BD12*-1, IF(AND($BH12="VP",($BC12-BM12)>0),(BM12-$BC12)*$BD12*-1,0)))) -> -24212.439 | CB12: =IF(AND($BH12="CC",($BC12-BN12)<0),(BN12-$BC12)*$BD12, IF(AND($BH12="VC",($BC12-BN12)<0),($BC12-BN12)*-$BD12, IF(AND($BH12="CP",($BC12-BN12)>0),(BN12-$BC12)*$BD12*-1, IF(AND($BH12="VP",($BC12-BN12)>0),(BN12-$BC12)*$BD12*-1,0)))) -> -80049.799 | CC12: =IF(AND($BH12="CC",($BC12-BO12)<0),(BO12-$BC12)*$BD12, IF(AND($BH12="VC",($BC12-BO12)<0),($BC12-BO12)*-$BD12, IF(AND($BH12="CP",($BC12-BO12)>0),(BO12-$BC12)*$BD12*-1, IF(AND($BH12="VP",($BC12-BO12)>0),(BO12-$BC12)*$BD12*-1,0)))) -> -135887.16 | CD12: =IF(AND($BH12="CC",($BC12-BI12)<0),$BD12*1, IF(AND($BH12="VC",($BC12-BI12)<0),$BD12*1, IF(AND($BH12="CP",($BC12-BI12)>0),$BD12*-1, IF(AND($BH12="VP",($BC12-BI12)>0),$BD12*-1,0)))) -> 0 | CE12: =IF(AND($BH12="CC",($BC12-BJ12)<0),$BD12*1, IF(AND($BH12="VC",($BC12-BJ12)<0),$BD12*1, IF(AND($BH12="CP",($BC12-BJ12)>0),$BD12*-1, IF(AND($BH12="VP",($BC12-BJ12)>0),$BD12*-1,0)))) -> 0 | CF12: =IF(AND($BH12="CC",($BC12-BK12)<0),$BD12*1, IF(AND($BH12="VC",($BC12-BK12)<0),$BD12*1, IF(AND($BH12="CP",($BC12-BK12)>0),$BD12*-1, IF(AND($BH12="VP",($BC12-BK12)>0),$BD12*-1,0)))) -> 0 | CG12: =IF(AND($BH12="CC",($BC12-BL12)<0),$BD12*1, IF(AND($BH12="VC",($BC12-BL12)<0),$BD12*1, IF(AND($BH12="CP",($BC12-BL12)>0),$BD12*-1, IF(AND($BH12="VP",($BC12-BL12)>0),$BD12*-1,0)))) -> 0 | CH12: =IF(AND($BH12="CC",($BC12-BM12)<0),$BD12*1, IF(AND($BH12="VC",($BC12-BM12)<0),$BD12*1, IF(AND($BH12="CP",($BC12-BM12)>0),$BD12*-1, IF(AND($BH12="VP",($BC12-BM12)>0),$BD12*-1,0)))) -> -1360.8 | CI12: =IF(AND($BH12="CC",($BC12-BN12)<0),$BD12*1, IF(AND($BH12="VC",($BC12-BN12)<0),$BD12*1, IF(AND($BH12="CP",($BC12-BN12)>0),$BD12*-1, IF(AND($BH12="VP",($BC12-BN12)>0),$BD12*-1,0)))) -> -1360.8 | CJ12: =IF(AND($BH12="CC",($BC12-BO12)<0),$BD12*1, IF(AND($BH12="VC",($BC12-BO12)<0),$BD12*1, IF(AND($BH12="CP",($BC12-BO12)>0),$BD12*-1, IF(AND($BH12="VP",($BC12-BO12)>0),$BD12*-1,0)))) -> -1360.8 | CK12: =Tabla3[[#This Row],[Tns]] -> -1360.8 | CL12: =IF(ISERROR(VLOOKUP(VALUE(E12),'Clientes CBOT'!A:A,1,0)),"VER","ok") -> ok
A13: P | B13: R | C13: 766 | D13: 0 | E13: 13007 | F13: C | G13: O | H13: F1 | I13: .AS-0118026E | J13: 7379 | K13: 2 | L13: 50000 | M13: CALL MAY 26 SOYBEANS 1180 | N13: .16 3/4 | O13: 20251023 | Q13: 202605 | S13: F | T13: C | U13: 1180000000 | V13: 20260424 | X13: FUTUROS Y OPCIONES.C | Z13: 20251023 | AA13: 1 | AB13: 1A | AC13: S- | AF13: .16750000 | AL13: 0 | AM13: 5.0000 | AN13: USD | AO13: -434375 | AP13: 0 | AQ13: 1116750000 | AR13: 50000 | AS13: 5J23 YP20 | AT13: 116067379 | AU13: 0,2860 | AV13: S | AW13: CBT | AX13: Comdty | AY13: Soja | AZ13: =IF(VLOOKUP(AY13,Conversor!B:C,2,0)="HS",0.01,VLOOKUP(AY13,Conversor!B:C,2,0)) -> 0.36743 | BA13: =IF(BG13="v",-AM13/10000,AL13/10000) -> -5 | BB13: =IF(AQ13=0,AP13/1000000*AZ13,AQ13/1000000*AZ13) -> 410.32745 | BC13: =U13/1000000*AZ13 -> 433.5674 | BD13: =IF(OR(E13="FUTUR",E13="f20176"),0,VLOOKUP(AY13,Conversor!G:I,3,0)*BA13) -> -680.4 | BE13: =IF(LEFT(M13,4)="call","Call",IF(LEFT(M13,3)="put","Put","Futuro")) -> Call | BF13: =IF(BE13="futuro","no","si") -> si | BG13: =IF(AL13=0,"V","C") -> V | BH13: =IF(BE13="futuro","",CONCATENATE(BG13,LEFT(BE13,1))) -> VC | BI13: =$BB13*(1+BI$2) -> 287.22922 | BJ13: =$BB13*(1+BJ$2) -> 328.26196 | BK13: =$BB13*(1+BK$2) -> 369.29471 | BL13: =$BB13*(1+BL$2) -> 410.32745 | BM13: =$BB13*(1+BM$2) -> 451.3602 | BN13: =$BB13*(1+BN$2) -> 492.39294 | BO13: =$BB13*(1+BO$2) -> 533.42569 | BP13: =IF($BE13="futuro",-($BL13-BI13)*$BD13,0) -> 0 | BQ13: =IF($BE13="futuro",-($BL13-BJ13)*$BD13,0) -> 0 | BR13: =IF($BE13="futuro",-($BL13-BK13)*$BD13,0) -> 0 | BS13: =IF($BE13="futuro",-($BL13-BL13)*$BD13,0) -> 0 | BT13: =IF($BE13="futuro",-($BL13-BM13)*$BD13,0) -> 0 | BU13: =IF($BE13="futuro",-($BL13-BN13)*$BD13,0) -> 0 | BV13: =IF($BE13="futuro",-($BL13-BO13)*$BD13,0) -> 0 | BW13: =IF(AND($BH13="CC",($BC13-BI13)<0),(BI13-$BC13)*$BD13, IF(AND($BH13="VC",($BC13-BI13)<0),($BC13-BI13)*-$BD13, IF(AND($BH13="CP",($BC13-BI13)>0),(BI13-$BC13)*$BD13*-1, IF(AND($BH13="VP",($BC13-BI13)>0),(BI13-$BC13)*$BD13*-1,0)))) -> 0 | BX13: =IF(AND($BH13="CC",($BC13-BJ13)<0),(BJ13-$BC13)*$BD13, IF(AND($BH13="VC",($BC13-BJ13)<0),($BC13-BJ13)*-$BD13, IF(AND($BH13="CP",($BC13-BJ13)>0),(BJ13-$BC13)*$BD13*-1, IF(AND($BH13="VP",($BC13-BJ13)>0),(BJ13-$BC13)*$BD13*-1,0)))) -> 0 | BY13: =IF(AND($BH13="CC",($BC13-BK13)<0),(BK13-$BC13)*$BD13, IF(AND($BH13="VC",($BC13-BK13)<0),($BC13-BK13)*-$BD13, IF(AND($BH13="CP",($BC13-BK13)>0),(BK13-$BC13)*$BD13*-1, IF(AND($BH13="VP",($BC13-BK13)>0),(BK13-$BC13)*$BD13*-1,0)))) -> 0 | BZ13: =IF(AND($BH13="CC",($BC13-BL13)<0),(BL13-$BC13)*$BD13, IF(AND($BH13="VC",($BC13-BL13)<0),($BC13-BL13)*-$BD13, IF(AND($BH13="CP",($BC13-BL13)>0),(BL13-$BC13)*$BD13*-1, IF(AND($BH13="VP",($BC13-BL13)>0),(BL13-$BC13)*$BD13*-1,0)))) -> 0 | CA13: =IF(AND($BH13="CC",($BC13-BM13)<0),(BM13-$BC13)*$BD13, IF(AND($BH13="VC",($BC13-BM13)<0),($BC13-BM13)*-$BD13, IF(AND($BH13="CP",($BC13-BM13)>0),(BM13-$BC13)*$BD13*-1, IF(AND($BH13="VP",($BC13-BM13)>0),(BM13-$BC13)*$BD13*-1,0)))) -> -12106.22 | CB13: =IF(AND($BH13="CC",($BC13-BN13)<0),(BN13-$BC13)*$BD13, IF(AND($BH13="VC",($BC13-BN13)<0),($BC13-BN13)*-$BD13, IF(AND($BH13="CP",($BC13-BN13)>0),(BN13-$BC13)*$BD13*-1, IF(AND($BH13="VP",($BC13-BN13)>0),(BN13-$BC13)*$BD13*-1,0)))) -> -40024.899 | CC13: =IF(AND($BH13="CC",($BC13-BO13)<0),(BO13-$BC13)*$BD13, IF(AND($BH13="VC",($BC13-BO13)<0),($BC13-BO13)*-$BD13, IF(AND($BH13="CP",($BC13-BO13)>0),(BO13-$BC13)*$BD13*-1, IF(AND($BH13="VP",($BC13-BO13)>0),(BO13-$BC13)*$BD13*-1,0)))) -> -67943.579 | CD13: =IF(AND($BH13="CC",($BC13-BI13)<0),$BD13*1, IF(AND($BH13="VC",($BC13-BI13)<0),$BD13*1, IF(AND($BH13="CP",($BC13-BI13)>0),$BD13*-1, IF(AND($BH13="VP",($BC13-BI13)>0),$BD13*-1,0)))) -> 0 | CE13: =IF(AND($BH13="CC",($BC13-BJ13)<0),$BD13*1, IF(AND($BH13="VC",($BC13-BJ13)<0),$BD13*1, IF(AND($BH13="CP",($BC13-BJ13)>0),$BD13*-1, IF(AND($BH13="VP",($BC13-BJ13)>0),$BD13*-1,0)))) -> 0 | CF13: =IF(AND($BH13="CC",($BC13-BK13)<0),$BD13*1, IF(AND($BH13="VC",($BC13-BK13)<0),$BD13*1, IF(AND($BH13="CP",($BC13-BK13)>0),$BD13*-1, IF(AND($BH13="VP",($BC13-BK13)>0),$BD13*-1,0)))) -> 0 | CG13: =IF(AND($BH13="CC",($BC13-BL13)<0),$BD13*1, IF(AND($BH13="VC",($BC13-BL13)<0),$BD13*1, IF(AND($BH13="CP",($BC13-BL13)>0),$BD13*-1, IF(AND($BH13="VP",($BC13-BL13)>0),$BD13*-1,0)))) -> 0 | CH13: =IF(AND($BH13="CC",($BC13-BM13)<0),$BD13*1, IF(AND($BH13="VC",($BC13-BM13)<0),$BD13*1, IF(AND($BH13="CP",($BC13-BM13)>0),$BD13*-1, IF(AND($BH13="VP",($BC13-BM13)>0),$BD13*-1,0)))) -> -680.4 | CI13: =IF(AND($BH13="CC",($BC13-BN13)<0),$BD13*1, IF(AND($BH13="VC",($BC13-BN13)<0),$BD13*1, IF(AND($BH13="CP",($BC13-BN13)>0),$BD13*-1, IF(AND($BH13="VP",($BC13-BN13)>0),$BD13*-1,0)))) -> -680.4 | CJ13: =IF(AND($BH13="CC",($BC13-BO13)<0),$BD13*1, IF(AND($BH13="VC",($BC13-BO13)<0),$BD13*1, IF(AND($BH13="CP",($BC13-BO13)>0),$BD13*-1, IF(AND($BH13="VP",($BC13-BO13)>0),$BD13*-1,0)))) -> -680.4 | CK13: =Tabla3[[#This Row],[Tns]] -> -680.4 | CL13: =IF(ISERROR(VLOOKUP(VALUE(E13),'Clientes CBOT'!A:A,1,0)),"VER","ok") -> ok
A14: P | B14: R | C14: 766 | D14: 0 | E14: 13007 | F14: C | G14: O | H14: F1 | I14: .AS-0120026E | J14: 3846 | K14: 2 | L14: 100000 | M14: CALL MAY 26 SOYBEANS 1200 | N14: .11 1/8 | O14: 20251009 | Q14: 202605 | S14: F | T14: C | U14: 1200000000 | V14: 20260424 | X14: FUTUROS Y OPCIONES.C | Z14: 20251009 | AA14: 1 | AB14: 1A | AC14: S- | AF14: .11125000 | AL14: 0 | AM14: 10.0000 | AN14: USD | AO14: -668750 | AP14: 0 | AQ14: 1116750000 | AR14: 50000 | AS14: 5J09 L0k0 | AT14: 115953846 | AU14: 0,2310 | AV14: S | AW14: CBT | AX14: Comdty | AY14: Soja | AZ14: =IF(VLOOKUP(AY14,Conversor!B:C,2,0)="HS",0.01,VLOOKUP(AY14,Conversor!B:C,2,0)) -> 0.36743 | BA14: =IF(BG14="v",-AM14/10000,AL14/10000) -> -10 | BB14: =IF(AQ14=0,AP14/1000000*AZ14,AQ14/1000000*AZ14) -> 410.32745 | BC14: =U14/1000000*AZ14 -> 440.916 | BD14: =IF(OR(E14="FUTUR",E14="f20176"),0,VLOOKUP(AY14,Conversor!G:I,3,0)*BA14) -> -1360.8 | BE14: =IF(LEFT(M14,4)="call","Call",IF(LEFT(M14,3)="put","Put","Futuro")) -> Call | BF14: =IF(BE14="futuro","no","si") -> si | BG14: =IF(AL14=0,"V","C") -> V | BH14: =IF(BE14="futuro","",CONCATENATE(BG14,LEFT(BE14,1))) -> VC | BI14: =$BB14*(1+BI$2) -> 287.22922 | BJ14: =$BB14*(1+BJ$2) -> 328.26196 | BK14: =$BB14*(1+BK$2) -> 369.29471 | BL14: =$BB14*(1+BL$2) -> 410.32745 | BM14: =$BB14*(1+BM$2) -> 451.3602 | BN14: =$BB14*(1+BN$2) -> 492.39294 | BO14: =$BB14*(1+BO$2) -> 533.42569 | BP14: =IF($BE14="futuro",-($BL14-BI14)*$BD14,0) -> 0 | BQ14: =IF($BE14="futuro",-($BL14-BJ14)*$BD14,0) -> 0 | BR14: =IF($BE14="futuro",-($BL14-BK14)*$BD14,0) -> 0 | BS14: =IF($BE14="futuro",-($BL14-BL14)*$BD14,0) -> 0 | BT14: =IF($BE14="futuro",-($BL14-BM14)*$BD14,0) -> 0 | BU14: =IF($BE14="futuro",-($BL14-BN14)*$BD14,0) -> 0 | BV14: =IF($BE14="futuro",-($BL14-BO14)*$BD14,0) -> 0 | BW14: =IF(AND($BH14="CC",($BC14-BI14)<0),(BI14-$BC14)*$BD14, IF(AND($BH14="VC",($BC14-BI14)<0),($BC14-BI14)*-$BD14, IF(AND($BH14="CP",($BC14-BI14)>0),(BI14-$BC14)*$BD14*-1, IF(AND($BH14="VP",($BC14-BI14)>0),(BI14-$BC14)*$BD14*-1,0)))) -> 0 | BX14: =IF(AND($BH14="CC",($BC14-BJ14)<0),(BJ14-$BC14)*$BD14, IF(AND($BH14="VC",($BC14-BJ14)<0),($BC14-BJ14)*-$BD14, IF(AND($BH14="CP",($BC14-BJ14)>0),(BJ14-$BC14)*$BD14*-1, IF(AND($BH14="VP",($BC14-BJ14)>0),(BJ14-$BC14)*$BD14*-1,0)))) -> 0 | BY14: =IF(AND($BH14="CC",($BC14-BK14)<0),(BK14-$BC14)*$BD14, IF(AND($BH14="VC",($BC14-BK14)<0),($BC14-BK14)*-$BD14, IF(AND($BH14="CP",($BC14-BK14)>0),(BK14-$BC14)*$BD14*-1, IF(AND($BH14="VP",($BC14-BK14)>0),(BK14-$BC14)*$BD14*-1,0)))) -> 0 | BZ14: =IF(AND($BH14="CC",($BC14-BL14)<0),(BL14-$BC14)*$BD14, IF(AND($BH14="VC",($BC14-BL14)<0),($BC14-BL14)*-$BD14, IF(AND($BH14="CP",($BC14-BL14)>0),(BL14-$BC14)*$BD14*-1, IF(AND($BH14="VP",($BC14-BL14)>0),(BL14-$BC14)*$BD14*-1,0)))) -> 0 | CA14: =IF(AND($BH14="CC",($BC14-BM14)<0),(BM14-$BC14)*$BD14, IF(AND($BH14="VC",($BC14-BM14)<0),($BC14-BM14)*-$BD14, IF(AND($BH14="CP",($BC14-BM14)>0),(BM14-$BC14)*$BD14*-1, IF(AND($BH14="VP",($BC14-BM14)>0),(BM14-$BC14)*$BD14*-1,0)))) -> -14212.464 | CB14: =IF(AND($BH14="CC",($BC14-BN14)<0),(BN14-$BC14)*$BD14, IF(AND($BH14="VC",($BC14-BN14)<0),($BC14-BN14)*-$BD14, IF(AND($BH14="CP",($BC14-BN14)>0),(BN14-$BC14)*$BD14*-1, IF(AND($BH14="VP",($BC14-BN14)>0),(BN14-$BC14)*$BD14*-1,0)))) -> -70049.824 | CC14: =IF(AND($BH14="CC",($BC14-BO14)<0),(BO14-$BC14)*$BD14, IF(AND($BH14="VC",($BC14-BO14)<0),($BC14-BO14)*-$BD14, IF(AND($BH14="CP",($BC14-BO14)>0),(BO14-$BC14)*$BD14*-1, IF(AND($BH14="VP",($BC14-BO14)>0),(BO14-$BC14)*$BD14*-1,0)))) -> -125887.18 | CD14: =IF(AND($BH14="CC",($BC14-BI14)<0),$BD14*1, IF(AND($BH14="VC",($BC14-BI14)<0),$BD14*1, IF(AND($BH14="CP",($BC14-BI14)>0),$BD14*-1, IF(AND($BH14="VP",($BC14-BI14)>0),$BD14*-1,0)))) -> 0 | CE14: =IF(AND($BH14="CC",($BC14-BJ14)<0),$BD14*1, IF(AND($BH14="VC",($BC14-BJ14)<0),$BD14*1, IF(AND($BH14="CP",($BC14-BJ14)>0),$BD14*-1, IF(AND($BH14="VP",($BC14-BJ14)>0),$BD14*-1,0)))) -> 0 | CF14: =IF(AND($BH14="CC",($BC14-BK14)<0),$BD14*1, IF(AND($BH14="VC",($BC14-BK14)<0),$BD14*1, IF(AND($BH14="CP",($BC14-BK14)>0),$BD14*-1, IF(AND($BH14="VP",($BC14-BK14)>0),$BD14*-1,0)))) -> 0 | CG14: =IF(AND($BH14="CC",($BC14-BL14)<0),$BD14*1, IF(AND($BH14="VC",($BC14-BL14)<0),$BD14*1, IF(AND($BH14="CP",($BC14-BL14)>0),$BD14*-1, IF(AND($BH14="VP",($BC14-BL14)>0),$BD14*-1,0)))) -> 0 | CH14: =IF(AND($BH14="CC",($BC14-BM14)<0),$BD14*1, IF(AND($BH14="VC",($BC14-BM14)<0),$BD14*1, IF(AND($BH14="CP",($BC14-BM14)>0),$BD14*-1, IF(AND($BH14="VP",($BC14-BM14)>0),$BD14*-1,0)))) -> -1360.8 | CI14: =IF(AND($BH14="CC",($BC14-BN14)<0),$BD14*1, IF(AND($BH14="VC",($BC14-BN14)<0),$BD14*1, IF(AND($BH14="CP",($BC14-BN14)>0),$BD14*-1, IF(AND($BH14="VP",($BC14-BN14)>0),$BD14*-1,0)))) -> -1360.8 | CJ14: =IF(AND($BH14="CC",($BC14-BO14)<0),$BD14*1, IF(AND($BH14="VC",($BC14-BO14)<0),$BD14*1, IF(AND($BH14="CP",($BC14-BO14)>0),$BD14*-1, IF(AND($BH14="VP",($BC14-BO14)>0),$BD14*-1,0)))) -> -1360.8 | CK14: =Tabla3[[#This Row],[Tns]] -> -1360.8 | CL14: =IF(ISERROR(VLOOKUP(VALUE(E14),'Clientes CBOT'!A:A,1,0)),"VER","ok") -> ok
... A24: P | B24: R | C24: 766 | D24: 0 | E24: 13010 | F24: C | G24: O | H24: F1 | I24: .AS-0120026C | J24: 1715 | K24: 1 | L24: 40000 | M24: CALL MAR 26 SOYBEANS 1200 | N24: .13 1/2 | O24: 20251104 | Q24: 202603 | S24: F | T24: C | U24: 1200000000 | V24: 20260220 | X24: FUTUROS Y OPCIONES.C | Z24: 20251104 | AA24: 1 | AB24: 1A | AC24: S- | AF24: .13500000 | AL24: 40000 | AM24: .0000 | AN24: USD | AO24: 100000 | AP24: 0 | AQ24: 1105750000 | AR24: 50000 | AS24: 5K04 EJP0 | AT24: 116171715 | AU24: 0,1320 | AV24: S | AW24: CBT | AX24: Comdty | AY24: Soja | AZ24: =IF(VLOOKUP(AY24,Conversor!B:C,2,0)="HS",0.01,VLOOKUP(AY24,Conversor!B:C,2,0)) -> 0.36743 | BA24: =IF(BG24="v",-AM24/10000,AL24/10000) -> 4 | BB24: =IF(AQ24=0,AP24/1000000*AZ24,AQ24/1000000*AZ24) -> 406.28572 | BC24: =U24/1000000*AZ24 -> 440.916 | BD24: =IF(OR(E24="FUTUR",E24="f20176"),0,VLOOKUP(AY24,Conversor!G:I,3,0)*BA24) -> 544.32 | BE24: =IF(LEFT(M24,4)="call","Call",IF(LEFT(M24,3)="put","Put","Futuro")) -> Call | BF24: =IF(BE24="futuro","no","si") -> si | BG24: =IF(AL24=0,"V","C") -> C | BH24: =IF(BE24="futuro","",CONCATENATE(BG24,LEFT(BE24,1))) -> CC | BI24: =$BB24*(1+BI$2) -> 284.40001 | BJ24: =$BB24*(1+BJ$2) -> 325.02858 | BK24: =$BB24*(1+BK$2) -> 365.65715 | BL24: =$BB24*(1+BL$2) -> 406.28572 | BM24: =$BB24*(1+BM$2) -> 446.91429 | BN24: =$BB24*(1+BN$2) -> 487.54287 | BO24: =$BB24*(1+BO$2) -> 528.17144 | BP24: =IF($BE24="futuro",-($BL24-BI24)*$BD24,0) -> 0 | BQ24: =IF($BE24="futuro",-($BL24-BJ24)*$BD24,0) -> 0 | BR24: =IF($BE24="futuro",-($BL24-BK24)*$BD24,0) -> 0 | BS24: =IF($BE24="futuro",-($BL24-BL24)*$BD24,0) -> 0 | BT24: =IF($BE24="futuro",-($BL24-BM24)*$BD24,0) -> 0 | BU24: =IF($BE24="futuro",-($BL24-BN24)*$BD24,0) -> 0 | BV24: =IF($BE24="futuro",-($BL24-BO24)*$BD24,0) -> 0 | BW24: =IF(AND($BH24="CC",($BC24-BI24)<0),(BI24-$BC24)*$BD24, IF(AND($BH24="VC",($BC24-BI24)<0),($BC24-BI24)*-$BD24, IF(AND($BH24="CP",($BC24-BI24)>0),(BI24-$BC24)*$BD24*-1, IF(AND($BH24="VP",($BC24-BI24)>0),(BI24-$BC24)*$BD24*-1,0)))) -> 0 | BX24: =IF(AND($BH24="CC",($BC24-BJ24)<0),(BJ24-$BC24)*$BD24, IF(AND($BH24="VC",($BC24-BJ24)<0),($BC24-BJ24)*-$BD24, IF(AND($BH24="CP",($BC24-BJ24)>0),(BJ24-$BC24)*$BD24*-1, IF(AND($BH24="VP",($BC24-BJ24)>0),(BJ24-$BC24)*$BD24*-1,0)))) -> 0 | BY24: =IF(AND($BH24="CC",($BC24-BK24)<0),(BK24-$BC24)*$BD24, IF(AND($BH24="VC",($BC24-BK24)<0),($BC24-BK24)*-$BD24, IF(AND($BH24="CP",($BC24-BK24)>0),(BK24-$BC24)*$BD24*-1, IF(AND($BH24="VP",($BC24-BK24)>0),(BK24-$BC24)*$BD24*-1,0)))) -> 0 | BZ24: =IF(AND($BH24="CC",($BC24-BL24)<0),(BL24-$BC24)*$BD24, IF(AND($BH24="VC",($BC24-BL24)<0),($BC24-BL24)*-$BD24, IF(AND($BH24="CP",($BC24-BL24)>0),(BL24-$BC24)*$BD24*-1, IF(AND($BH24="VP",($BC24-BL24)>0),(BL24-$BC24)*$BD24*-1,0)))) -> 0 | CA24: =IF(AND($BH24="CC",($BC24-BM24)<0),(BM24-$BC24)*$BD24, IF(AND($BH24="VC",($BC24-BM24)<0),($BC24-BM24)*-$BD24, IF(AND($BH24="CP",($BC24-BM24)>0),(BM24-$BC24)*$BD24*-1, IF(AND($BH24="VP",($BC24-BM24)>0),(BM24-$BC24)*$BD24*-1,0)))) -> 3264.9918 | CB24: =IF(AND($BH24="CC",($BC24-BN24)<0),(BN24-$BC24)*$BD24, IF(AND($BH24="VC",($BC24-BN24)<0),($BC24-BN24)*-$BD24, IF(AND($BH24="CP",($BC24-BN24)>0),(BN24-$BC24)*$BD24*-1, IF(AND($BH24="VP",($BC24-BN24)>0),(BN24-$BC24)*$BD24*-1,0)))) -> 25379.936 | CC24: =IF(AND($BH24="CC",($BC24-BO24)<0),(BO24-$BC24)*$BD24, IF(AND($BH24="VC",($BC24-BO24)<0),($BC24-BO24)*-$BD24, IF(AND($BH24="CP",($BC24-BO24)>0),(BO24-$BC24)*$BD24*-1, IF(AND($BH24="VP",($BC24-BO24)>0),(BO24-$BC24)*$BD24*-1,0)))) -> 47494.881 | CD24: =IF(AND($BH24="CC",($BC24-BI24)<0),$BD24*1, IF(AND($BH24="VC",($BC24-BI24)<0),$BD24*1, IF(AND($BH24="CP",($BC24-BI24)>0),$BD24*-1, IF(AND($BH24="VP",($BC24-BI24)>0),$BD24*-1,0)))) -> 0 | CE24: =IF(AND($BH24="CC",($BC24-BJ24)<0),$BD24*1, IF(AND($BH24="VC",($BC24-BJ24)<0),$BD24*1, IF(AND($BH24="CP",($BC24-BJ24)>0),$BD24*-1, IF(AND($BH24="VP",($BC24-BJ24)>0),$BD24*-1,0)))) -> 0 | CF24: =IF(AND($BH24="CC",($BC24-BK24)<0),$BD24*1, IF(AND($BH24="VC",($BC24-BK24)<0),$BD24*1, IF(AND($BH24="CP",($BC24-BK24)>0),$BD24*-1, IF(AND($BH24="VP",($BC24-BK24)>0),$BD24*-1,0)))) -> 0 | CG24: =IF(AND($BH24="CC",($BC24-BL24)<0),$BD24*1, IF(AND($BH24="VC",($BC24-BL24)<0),$BD24*1, IF(AND($BH24="CP",($BC24-BL24)>0),$BD24*-1, IF(AND($BH24="VP",($BC24-BL24)>0),$BD24*-1,0)))) -> 0 | CH24: =IF(AND($BH24="CC",($BC24-BM24)<0),$BD24*1, IF(AND($BH24="VC",($BC24-BM24)<0),$BD24*1, IF(AND($BH24="CP",($BC24-BM24)>0),$BD24*-1, IF(AND($BH24="VP",($BC24-BM24)>0),$BD24*-1,0)))) -> 544.32 | CI24: =IF(AND($BH24="CC",($BC24-BN24)<0),$BD24*1, IF(AND($BH24="VC",($BC24-BN24)<0),$BD24*1, IF(AND($BH24="CP",($BC24-BN24)>0),$BD24*-1, IF(AND($BH24="VP",($BC24-BN24)>0),$BD24*-1,0)))) -> 544.32 | CJ24: =IF(AND($BH24="CC",($BC24-BO24)<0),$BD24*1, IF(AND($BH24="VC",($BC24-BO24)<0),$BD24*1, IF(AND($BH24="CP",($BC24-BO24)>0),$BD24*-1, IF(AND($BH24="VP",($BC24-BO24)>0),$BD24*-1,0)))) -> 544.32 | CK24: =Tabla3[[#This Row],[Tns]] -> 544.32 | CL24: =IF(ISERROR(VLOOKUP(VALUE(E24),'Clientes CBOT'!A:A,1,0)),"VER","ok") -> ok
A25: P | B25: R | C25: 766 | D25: 0 | E25: 20176 | F25: C | H25: F1 | I25: .AC-0000026C | J25: 1477 | K25: 1 | L25: 920000 | M25: MAR 26 CORN | N25: 4.45 1/2 | O25: 20251030 | Q25: 202603 | S25: F | U25: 0 | V25: 0 | X25: FYO ACOPIO SA | Z25: 20251030 | AA25: 1 | AB25: 1A | AC25: C- | AF25: 4.45500000 | AL25: 920000 | AM25: .0000 | AN25: USD | AO25: -805000 | AP25: 443750000 | AQ25: 0 | AR25: 50000 | AS25: 5J30 PNI0 | AT25: 116141477 | AU25: 0,0000 | AV25: C | AW25: CBT | AX25: Comdty | AY25: Maíz | AZ25: =IF(VLOOKUP(AY25,Conversor!B:C,2,0)="HS",0.01,VLOOKUP(AY25,Conversor!B:C,2,0)) -> 0.3937 | BA25: =IF(BG25="v",-AM25/10000,AL25/10000) -> 92 | BB25: =IF(AQ25=0,AP25/1000000*AZ25,AQ25/1000000*AZ25) -> 174.70437 | BC25: =U25/1000000*AZ25 -> 0 | BD25: =IF(OR(E25="FUTUR",E25="f20176"),0,VLOOKUP(AY25,Conversor!G:I,3,0)*BA25) -> 11684.46 | BE25: =IF(LEFT(M25,4)="call","Call",IF(LEFT(M25,3)="put","Put","Futuro")) -> Futuro | BF25: =IF(BE25="futuro","no","si") -> no | BG25: =IF(AL25=0,"V","C") -> C | BH25: =IF(BE25="futuro","",CONCATENATE(BG25,LEFT(BE25,1))) | BI25: =$BB25*(1+BI$2) -> 122.29306 | BJ25: =$BB25*(1+BJ$2) -> 139.7635 | BK25: =$BB25*(1+BK$2) -> 157.23394 | BL25: =$BB25*(1+BL$2) -> 174.70437 | BM25: =$BB25*(1+BM$2) -> 192.17481 | BN25: =$BB25*(1+BN$2) -> 209.64525 | BO25: =$BB25*(1+BO$2) -> 227.11569 | BP25: =IF($BE25="futuro",-($BL25-BI25)*$BD25,0) -> -612397.88 | BQ25: =IF($BE25="futuro",-($BL25-BJ25)*$BD25,0) -> -408265.26 | BR25: =IF($BE25="futuro",-($BL25-BK25)*$BD25,0) -> -204132.63 | BS25: =IF($BE25="futuro",-($BL25-BL25)*$BD25,0) -> 0 | BT25: =IF($BE25="futuro",-($BL25-BM25)*$BD25,0) -> 204132.63 | BU25: =IF($BE25="futuro",-($BL25-BN25)*$BD25,0) -> 408265.26 | BV25: =IF($BE25="futuro",-($BL25-BO25)*$BD25,0) -> 612397.88 | BW25: =IF(AND($BH25="CC",($BC25-BI25)<0),(BI25-$BC25)*$BD25, IF(AND($BH25="VC",($BC25-BI25)<0),($BC25-BI25)*-$BD25, IF(AND($BH25="CP",($BC25-BI25)>0),(BI25-$BC25)*$BD25*-1, IF(AND($BH25="VP",($BC25-BI25)>0),(BI25-$BC25)*$BD25*-1,0)))) -> 0 | BX25: =IF(AND($BH25="CC",($BC25-BJ25)<0),(BJ25-$BC25)*$BD25, IF(AND($BH25="VC",($BC25-BJ25)<0),($BC25-BJ25)*-$BD25, IF(AND($BH25="CP",($BC25-BJ25)>0),(BJ25-$BC25)*$BD25*-1, IF(AND($BH25="VP",($BC25-BJ25)>0),(BJ25-$BC25)*$BD25*-1,0)))) -> 0 | BY25: =IF(AND($BH25="CC",($BC25-BK25)<0),(BK25-$BC25)*$BD25, IF(AND($BH25="VC",($BC25-BK25)<0),($BC25-BK25)*-$BD25, IF(AND($BH25="CP",($BC25-BK25)>0),(BK25-$BC25)*$BD25*-1, IF(AND($BH25="VP",($BC25-BK25)>0),(BK25-$BC25)*$BD25*-1,0)))) -> 0 | BZ25: =IF(AND($BH25="CC",($BC25-BL25)<0),(BL25-$BC25)*$BD25, IF(AND($BH25="VC",($BC25-BL25)<0),($BC25-BL25)*-$BD25, IF(AND($BH25="CP",($BC25-BL25)>0),(BL25-$BC25)*$BD25*-1, IF(AND($BH25="VP",($BC25-BL25)>0),(BL25-$BC25)*$BD25*-1,0)))) -> 0 | CA25: =IF(AND($BH25="CC",($BC25-BM25)<0),(BM25-$BC25)*$BD25, IF(AND($BH25="VC",($BC25-BM25)<0),($BC25-BM25)*-$BD25, IF(AND($BH25="CP",($BC25-BM25)>0),(BM25-$BC25)*$BD25*-1, IF(AND($BH25="VP",($BC25-BM25)>0),(BM25-$BC25)*$BD25*-1,0)))) -> 0 | CB25: =IF(AND($BH25="CC",($BC25-BN25)<0),(BN25-$BC25)*$BD25, IF(AND($BH25="VC",($BC25-BN25)<0),($BC25-BN25)*-$BD25, IF(AND($BH25="CP",($BC25-BN25)>0),(BN25-$BC25)*$BD25*-1, IF(AND($BH25="VP",($BC25-BN25)>0),(BN25-$BC25)*$BD25*-1,0)))) -> 0 | CC25: =IF(AND($BH25="CC",($BC25-BO25)<0),(BO25-$BC25)*$BD25, IF(AND($BH25="VC",($BC25-BO25)<0),($BC25-BO25)*-$BD25, IF(AND($BH25="CP",($BC25-BO25)>0),(BO25-$BC25)*$BD25*-1, IF(AND($BH25="VP",($BC25-BO25)>0),(BO25-$BC25)*$BD25*-1,0)))) -> 0 | CD25: =IF(AND($BH25="CC",($BC25-BI25)<0),$BD25*1, IF(AND($BH25="VC",($BC25-BI25)<0),$BD25*1, IF(AND($BH25="CP",($BC25-BI25)>0),$BD25*-1, IF(AND($BH25="VP",($BC25-BI25)>0),$BD25*-1,0)))) -> 0 | CE25: =IF(AND($BH25="CC",($BC25-BJ25)<0),$BD25*1, IF(AND($BH25="VC",($BC25-BJ25)<0),$BD25*1, IF(AND($BH25="CP",($BC25-BJ25)>0),$BD25*-1, IF(AND($BH25="VP",($BC25-BJ25)>0),$BD25*-1,0)))) -> 0 | CF25: =IF(AND($BH25="CC",($BC25-BK25)<0),$BD25*1, IF(AND($BH25="VC",($BC25-BK25)<0),$BD25*1, IF(AND($BH25="CP",($BC25-BK25)>0),$BD25*-1, IF(AND($BH25="VP",($BC25-BK25)>0),$BD25*-1,0)))) -> 0 | CG25: =IF(AND($BH25="CC",($BC25-BL25)<0),$BD25*1, IF(AND($BH25="VC",($BC25-BL25)<0),$BD25*1, IF(AND($BH25="CP",($BC25-BL25)>0),$BD25*-1, IF(AND($BH25="VP",($BC25-BL25)>0),$BD25*-1,0)))) -> 0 | CH25: =IF(AND($BH25="CC",($BC25-BM25)<0),$BD25*1, IF(AND($BH25="VC",($BC25-BM25)<0),$BD25*1, IF(AND($BH25="CP",($BC25-BM25)>0),$BD25*-1, IF(AND($BH25="VP",($BC25-BM25)>0),$BD25*-1,0)))) -> 0 | CI25: =IF(AND($BH25="CC",($BC25-BN25)<0),$BD25*1, IF(AND($BH25="VC",($BC25-BN25)<0),$BD25*1, IF(AND($BH25="CP",($BC25-BN25)>0),$BD25*-1, IF(AND($BH25="VP",($BC25-BN25)>0),$BD25*-1,0)))) -> 0 | CJ25: =IF(AND($BH25="CC",($BC25-BO25)<0),$BD25*1, IF(AND($BH25="VC",($BC25-BO25)<0),$BD25*1, IF(AND($BH25="CP",($BC25-BO25)>0),$BD25*-1, IF(AND($BH25="VP",($BC25-BO25)>0),$BD25*-1,0)))) -> 0 | CK25: =Tabla3[[#This Row],[Tns]] -> 11684.46 | CL25: =IF(ISERROR(VLOOKUP(VALUE(E25),'Clientes CBOT'!A:A,1,0)),"VER","ok") -> ok
A26: P | B26: R | C26: 766 | D26: 0 | E26: 20176 | F26: C | H26: F1 | I26: .AC-0000026C | J26: 3966 | K26: 1 | L26: 950000 | M26: MAR 26 CORN | N26: 4.49 3/4 | O26: 20251117 | Q26: 202603 | S26: F | U26: 0 | V26: 0 | X26: FYO ACOPIO SA | Z26: 20251117 | AA26: 1 | AB26: 1A | AC26: C- | AF26: 4.49750000 | AL26: 950000 | AM26: .0000 | AN26: USD | AO26: -2850000 | AP26: 443750000 | AQ26: 0 | AR26: 50000 | AS26: 5K17 GcE0 | AT26: 116283966 | AU26: 0,0000 | AV26: C | AW26: CBT | AX26: Comdty | AY26: Maíz | AZ26: =IF(VLOOKUP(AY26,Conversor!B:C,2,0)="HS",0.01,VLOOKUP(AY26,Conversor!B:C,2,0)) -> 0.3937 | BA26: =IF(BG26="v",-AM26/10000,AL26/10000) -> 95 | BB26: =IF(AQ26=0,AP26/1000000*AZ26,AQ26/1000000*AZ26) -> 174.70437 | BC26: =U26/1000000*AZ26 -> 0 | BD26: =IF(OR(E26="FUTUR",E26="f20176"),0,VLOOKUP(AY26,Conversor!G:I,3,0)*BA26) -> 12065.475 | BE26: =IF(LEFT(M26,4)="call","Call",IF(LEFT(M26,3)="put","Put","Futuro")) -> Futuro | BF26: =IF(BE26="futuro","no","si") -> no | BG26: =IF(AL26=0,"V","C") -> C | BH26: =IF(BE26="futuro","",CONCATENATE(BG26,LEFT(BE26,1))) | BI26: =$BB26*(1+BI$2) -> 122.29306 | BJ26: =$BB26*(1+BJ$2) -> 139.7635 | BK26: =$BB26*(1+BK$2) -> 157.23394 | BL26: =$BB26*(1+BL$2) -> 174.70437 | BM26: =$BB26*(1+BM$2) -> 192.17481 | BN26: =$BB26*(1+BN$2) -> 209.64525 | BO26: =$BB26*(1+BO$2) -> 227.11569 | BP26: =IF($BE26="futuro",-($BL26-BI26)*$BD26,0) -> -632367.38 | BQ26: =IF($BE26="futuro",-($BL26-BJ26)*$BD26,0) -> -421578.25 | BR26: =IF($BE26="futuro",-($BL26-BK26)*$BD26,0) -> -210789.13 | BS26: =IF($BE26="futuro",-($BL26-BL26)*$BD26,0) -> 0 | BT26: =IF($BE26="futuro",-($BL26-BM26)*$BD26,0) -> 210789.13 | BU26: =IF($BE26="futuro",-($BL26-BN26)*$BD26,0) -> 421578.25 | BV26: =IF($BE26="futuro",-($BL26-BO26)*$BD26,0) -> 632367.38 | BW26: =IF(AND($BH26="CC",($BC26-BI26)<0),(BI26-$BC26)*$BD26, IF(AND($BH26="VC",($BC26-BI26)<0),($BC26-BI26)*-$BD26, IF(AND($BH26="CP",($BC26-BI26)>0),(BI26-$BC26)*$BD26*-1, IF(AND($BH26="VP",($BC26-BI26)>0),(BI26-$BC26)*$BD26*-1,0)))) -> 0 | BX26: =IF(AND($BH26="CC",($BC26-BJ26)<0),(BJ26-$BC26)*$BD26, IF(AND($BH26="VC",($BC26-BJ26)<0),($BC26-BJ26)*-$BD26, IF(AND($BH26="CP",($BC26-BJ26)>0),(BJ26-$BC26)*$BD26*-1, IF(AND($BH26="VP",($BC26-BJ26)>0),(BJ26-$BC26)*$BD26*-1,0)))) -> 0 | BY26: =IF(AND($BH26="CC",($BC26-BK26)<0),(BK26-$BC26)*$BD26, IF(AND($BH26="VC",($BC26-BK26)<0),($BC26-BK26)*-$BD26, IF(AND($BH26="CP",($BC26-BK26)>0),(BK26-$BC26)*$BD26*-1, IF(AND($BH26="VP",($BC26-BK26)>0),(BK26-$BC26)*$BD26*-1,0)))) -> 0 | BZ26: =IF(AND($BH26="CC",($BC26-BL26)<0),(BL26-$BC26)*$BD26, IF(AND($BH26="VC",($BC26-BL26)<0),($BC26-BL26)*-$BD26, IF(AND($BH26="CP",($BC26-BL26)>0),(BL26-$BC26)*$BD26*-1, IF(AND($BH26="VP",($BC26-BL26)>0),(BL26-$BC26)*$BD26*-1,0)))) -> 0 | CA26: =IF(AND($BH26="CC",($BC26-BM26)<0),(BM26-$BC26)*$BD26, IF(AND($BH26="VC",($BC26-BM26)<0),($BC26-BM26)*-$BD26, IF(AND($BH26="CP",($BC26-BM26)>0),(BM26-$BC26)*$BD26*-1, IF(AND($BH26="VP",($BC26-BM26)>0),(BM26-$BC26)*$BD26*-1,0)))) -> 0 | CB26: =IF(AND($BH26="CC",($BC26-BN26)<0),(BN26-$BC26)*$BD26, IF(AND($BH26="VC",($BC26-BN26)<0),($BC26-BN26)*-$BD26, IF(AND($BH26="CP",($BC26-BN26)>0),(BN26-$BC26)*$BD26*-1, IF(AND($BH26="VP",($BC26-BN26)>0),(BN26-$BC26)*$BD26*-1,0)))) -> 0 | CC26: =IF(AND($BH26="CC",($BC26-BO26)<0),(BO26-$BC26)*$BD26, IF(AND($BH26="VC",($BC26-BO26)<0),($BC26-BO26)*-$BD26, IF(AND($BH26="CP",($BC26-BO26)>0),(BO26-$BC26)*$BD26*-1, IF(AND($BH26="VP",($BC26-BO26)>0),(BO26-$BC26)*$BD26*-1,0)))) -> 0 | CD26: =IF(AND($BH26="CC",($BC26-BI26)<0),$BD26*1, IF(AND($BH26="VC",($BC26-BI26)<0),$BD26*1, IF(AND($BH26="CP",($BC26-BI26)>0),$BD26*-1, IF(AND($BH26="VP",($BC26-BI26)>0),$BD26*-1,0)))) -> 0 | CE26: =IF(AND($BH26="CC",($BC26-BJ26)<0),$BD26*1, IF(AND($BH26="VC",($BC26-BJ26)<0),$BD26*1, IF(AND($BH26="CP",($BC26-BJ26)>0),$BD26*-1, IF(AND($BH26="VP",($BC26-BJ26)>0),$BD26*-1,0)))) -> 0 | CF26: =IF(AND($BH26="CC",($BC26-BK26)<0),$BD26*1, IF(AND($BH26="VC",($BC26-BK26)<0),$BD26*1, IF(AND($BH26="CP",($BC26-BK26)>0),$BD26*-1, IF(AND($BH26="VP",($BC26-BK26)>0),$BD26*-1,0)))) -> 0 | CG26: =IF(AND($BH26="CC",($BC26-BL26)<0),$BD26*1, IF(AND($BH26="VC",($BC26-BL26)<0),$BD26*1, IF(AND($BH26="CP",($BC26-BL26)>0),$BD26*-1, IF(AND($BH26="VP",($BC26-BL26)>0),$BD26*-1,0)))) -> 0 | CH26: =IF(AND($BH26="CC",($BC26-BM26)<0),$BD26*1, IF(AND($BH26="VC",($BC26-BM26)<0),$BD26*1, IF(AND($BH26="CP",($BC26-BM26)>0),$BD26*-1, IF(AND($BH26="VP",($BC26-BM26)>0),$BD26*-1,0)))) -> 0 | CI26: =IF(AND($BH26="CC",($BC26-BN26)<0),$BD26*1, IF(AND($BH26="VC",($BC26-BN26)<0),$BD26*1, IF(AND($BH26="CP",($BC26-BN26)>0),$BD26*-1, IF(AND($BH26="VP",($BC26-BN26)>0),$BD26*-1,0)))) -> 0 | CJ26: =IF(AND($BH26="CC",($BC26-BO26)<0),$BD26*1, IF(AND($BH26="VC",($BC26-BO26)<0),$BD26*1, IF(AND($BH26="CP",($BC26-BO26)>0),$BD26*-1, IF(AND($BH26="VP",($BC26-BO26)>0),$BD26*-1,0)))) -> 0 | CK26: =Tabla3[[#This Row],[Tns]] -> 12065.475 | CL26: =IF(ISERROR(VLOOKUP(VALUE(E26),'Clientes CBOT'!A:A,1,0)),"VER","ok") -> ok
A27: P | B27: R | C27: 766 | D27: 0 | E27: 20176 | F27: C | H27: F1 | I27: .AC-0000026E | J27: 5040 | K27: 1 | L27: 230000 | M27: MAY 26 CORN | N27: 4.48 1/2 | O27: 20250911 | Q27: 202605 | S27: F | U27: 0 | V27: 0 | X27: FYO ACOPIO SA | Z27: 20250911 | AA27: 1 | AB27: 1A | AC27: C- | AF27: 4.48500000 | AL27: 230000 | AM27: .0000 | AN27: USD | AO27: 316250 | AP27: 451250000 | AQ27: 0 | AR27: 50000 | AS27: 5I11 EMM0 | AT27: 115755040 | AU27: 0,0000 | AV27: C | AW27: CBT | AX27: Comdty | AY27: Maíz | AZ27: =IF(VLOOKUP(AY27,Conversor!B:C,2,0)="HS",0.01,VLOOKUP(AY27,Conversor!B:C,2,0)) -> 0.3937 | BA27: =IF(BG27="v",-AM27/10000,AL27/10000) -> 23 | BB27: =IF(AQ27=0,AP27/1000000*AZ27,AQ27/1000000*AZ27) -> 177.65713 | BC27: =U27/1000000*AZ27 -> 0 | BD27: =IF(OR(E27="FUTUR",E27="f20176"),0,VLOOKUP(AY27,Conversor!G:I,3,0)*BA27) -> 2921.115 | BE27: =IF(LEFT(M27,4)="call","Call",IF(LEFT(M27,3)="put","Put","Futuro")) -> Futuro | BF27: =IF(BE27="futuro","no","si") -> no | BG27: =IF(AL27=0,"V","C") -> C | BH27: =IF(BE27="futuro","",CONCATENATE(BG27,LEFT(BE27,1))) | BI27: =$BB27*(1+BI$2) -> 124.35999 | BJ27: =$BB27*(1+BJ$2) -> 142.1257 | BK27: =$BB27*(1+BK$2) -> 159.89141 | BL27: =$BB27*(1+BL$2) -> 177.65713 | BM27: =$BB27*(1+BM$2) -> 195.42284 | BN27: =$BB27*(1+BN$2) -> 213.18855 | BO27: =$BB27*(1+BO$2) -> 230.95426 | BP27: =IF($BE27="futuro",-($BL27-BI27)*$BD27,0) -> -155687.07 | BQ27: =IF($BE27="futuro",-($BL27-BJ27)*$BD27,0) -> -103791.38 | BR27: =IF($BE27="futuro",-($BL27-BK27)*$BD27,0) -> -51895.689 | BS27: =IF($BE27="futuro",-($BL27-BL27)*$BD27,0) -> 0 | BT27: =IF($BE27="futuro",-($BL27-BM27)*$BD27,0) -> 51895.689 | BU27: =IF($BE27="futuro",-($BL27-BN27)*$BD27,0) -> 103791.38 | BV27: =IF($BE27="futuro",-($BL27-BO27)*$BD27,0) -> 155687.07 | BW27: =IF(AND($BH27="CC",($BC27-BI27)<0),(BI27-$BC27)*$BD27, IF(AND($BH27="VC",($BC27-BI27)<0),($BC27-BI27)*-$BD27, IF(AND($BH27="CP",($BC27-BI27)>0),(BI27-$BC27)*$BD27*-1, IF(AND($BH27="VP",($BC27-BI27)>0),(BI27-$BC27)*$BD27*-1,0)))) -> 0 | BX27: =IF(AND($BH27="CC",($BC27-BJ27)<0),(BJ27-$BC27)*$BD27, IF(AND($BH27="VC",($BC27-BJ27)<0),($BC27-BJ27)*-$BD27, IF(AND($BH27="CP",($BC27-BJ27)>0),(BJ27-$BC27)*$BD27*-1, IF(AND($BH27="VP",($BC27-BJ27)>0),(BJ27-$BC27)*$BD27*-1,0)))) -> 0 | BY27: =IF(AND($BH27="CC",($BC27-BK27)<0),(BK27-$BC27)*$BD27, IF(AND($BH27="VC",($BC27-BK27)<0),($BC27-BK27)*-$BD27, IF(AND($BH27="CP",($BC27-BK27)>0),(BK27-$BC27)*$BD27*-1, IF(AND($BH27="VP",($BC27-BK27)>0),(BK27-$BC27)*$BD27*-1,0)))) -> 0 | BZ27: =IF(AND($BH27="CC",($BC27-BL27)<0),(BL27-$BC27)*$BD27, IF(AND($BH27="VC",($BC27-BL27)<0),($BC27-BL27)*-$BD27, IF(AND($BH27="CP",($BC27-BL27)>0),(BL27-$BC27)*$BD27*-1, IF(AND($BH27="VP",($BC27-BL27)>0),(BL27-$BC27)*$BD27*-1,0)))) -> 0 | CA27: =IF(AND($BH27="CC",($BC27-BM27)<0),(BM27-$BC27)*$BD27, IF(AND($BH27="VC",($BC27-BM27)<0),($BC27-BM27)*-$BD27, IF(AND($BH27="CP",($BC27-BM27)>0),(BM27-$BC27)*$BD27*-1, IF(AND($BH27="VP",($BC27-BM27)>0),(BM27-$BC27)*$BD27*-1,0)))) -> 0 | CB27: =IF(AND($BH27="CC",($BC27-BN27)<0),(BN27-$BC27)*$BD27, IF(AND($BH27="VC",($BC27-BN27)<0),($BC27-BN27)*-$BD27, IF(AND($BH27="CP",($BC27-BN27)>0),(BN27-$BC27)*$BD27*-1, IF(AND($BH27="VP",($BC27-BN27)>0),(BN27-$BC27)*$BD27*-1,0)))) -> 0 | CC27: =IF(AND($BH27="CC",($BC27-BO27)<0),(BO27-$BC27)*$BD27, IF(AND($BH27="VC",($BC27-BO27)<0),($BC27-BO27)*-$BD27, IF(AND($BH27="CP",($BC27-BO27)>0),(BO27-$BC27)*$BD27*-1, IF(AND($BH27="VP",($BC27-BO27)>0),(BO27-$BC27)*$BD27*-1,0)))) -> 0 | CD27: =IF(AND($BH27="CC",($BC27-BI27)<0),$BD27*1, IF(AND($BH27="VC",($BC27-BI27)<0),$BD27*1, IF(AND($BH27="CP",($BC27-BI27)>0),$BD27*-1, IF(AND($BH27="VP",($BC27-BI27)>0),$BD27*-1,0)))) -> 0 | CE27: =IF(AND($BH27="CC",($BC27-BJ27)<0),$BD27*1, IF(AND($BH27="VC",($BC27-BJ27)<0),$BD27*1, IF(AND($BH27="CP",($BC27-BJ27)>0),$BD27*-1, IF(AND($BH27="VP",($BC27-BJ27)>0),$BD27*-1,0)))) -> 0 | CF27: =IF(AND($BH27="CC",($BC27-BK27)<0),$BD27*1, IF(AND($BH27="VC",($BC27-BK27)<0),$BD27*1, IF(AND($BH27="CP",($BC27-BK27)>0),$BD27*-1, IF(AND($BH27="VP",($BC27-BK27)>0),$BD27*-1,0)))) -> 0 | CG27: =IF(AND($BH27="CC",($BC27-BL27)<0),$BD27*1, IF(AND($BH27="VC",($BC27-BL27)<0),$BD27*1, IF(AND($BH27="CP",($BC27-BL27)>0),$BD27*-1, IF(AND($BH27="VP",($BC27-BL27)>0),$BD27*-1,0)))) -> 0 | CH27: =IF(AND($BH27="CC",($BC27-BM27)<0),$BD27*1, IF(AND($BH27="VC",($BC27-BM27)<0),$BD27*1, IF(AND($BH27="CP",($BC27-BM27)>0),$BD27*-1, IF(AND($BH27="VP",($BC27-BM27)>0),$BD27*-1,0)))) -> 0 | CI27: =IF(AND($BH27="CC",($BC27-BN27)<0),$BD27*1, IF(AND($BH27="VC",($BC27-BN27)<0),$BD27*1, IF(AND($BH27="CP",($BC27-BN27)>0),$BD27*-1, IF(AND($BH27="VP",($BC27-BN27)>0),$BD27*-1,0)))) -> 0 | CJ27: =IF(AND($BH27="CC",($BC27-BO27)<0),$BD27*1, IF(AND($BH27="VC",($BC27-BO27)<0),$BD27*1, IF(AND($BH27="CP",($BC27-BO27)>0),$BD27*-1, IF(AND($BH27="VP",($BC27-BO27)>0),$BD27*-1,0)))) -> 0 | CK27: =Tabla3[[#This Row],[Tns]] -> 2921.115 | CL27: =IF(ISERROR(VLOOKUP(VALUE(E27),'Clientes CBOT'!A:A,1,0)),"VER","ok") -> ok
A28: P | B28: R | C28: 766 | D28: 0 | E28: 20176 | F28: C | H28: F1 | I28: .AC-0000026G | J28: 4946 | K28: 1 | L28: 230000 | M28: JUL 26 CORN | N28: 4.57 | O28: 20251119 | Q28: 202607 | S28: F | U28: 0 | V28: 0 | X28: FYO ACOPIO SA | Z28: 20251119 | AA28: 1 | AB28: 1A | AC28: C- | AF28: 4.57000000 | AL28: 230000 | AM28: .0000 | AN28: USD | AO28: 0 | AP28: 457000000 | AQ28: 0 | AR28: 50000 | AS28: 5K19 AP00 | AT28: 116304946 | AU28: 0,0000 | AV28: C | AW28: CBT | AX28: Comdty | AY28: Maíz | AZ28: =IF(VLOOKUP(AY28,Conversor!B:C,2,0)="HS",0.01,VLOOKUP(AY28,Conversor!B:C,2,0)) -> 0.3937 | BA28: =IF(BG28="v",-AM28/10000,AL28/10000) -> 23 | BB28: =IF(AQ28=0,AP28/1000000*AZ28,AQ28/1000000*AZ28) -> 179.9209 | BC28: =U28/1000000*AZ28 -> 0 | BD28: =IF(OR(E28="FUTUR",E28="f20176"),0,VLOOKUP(AY28,Conversor!G:I,3,0)*BA28) -> 2921.115 | BE28: =IF(LEFT(M28,4)="call","Call",IF(LEFT(M28,3)="put","Put","Futuro")) -> Futuro | BF28: =IF(BE28="futuro","no","si") -> no | BG28: =IF(AL28=0,"V","C") -> C | BH28: =IF(BE28="futuro","",CONCATENATE(BG28,LEFT(BE28,1))) | BI28: =$BB28*(1+BI$2) -> 125.94463 | BJ28: =$BB28*(1+BJ$2) -> 143.93672 | BK28: =$BB28*(1+BK$2) -> 161.92881 | BL28: =$BB28*(1+BL$2) -> 179.9209 | BM28: =$BB28*(1+BM$2) -> 197.91299 | BN28: =$BB28*(1+BN$2) -> 215.90508 | BO28: =$BB28*(1+BO$2) -> 233.89717 | BP28: =IF($BE28="futuro",-($BL28-BI28)*$BD28,0) -> -157670.89 | BQ28: =IF($BE28="futuro",-($BL28-BJ28)*$BD28,0) -> -105113.93 | BR28: =IF($BE28="futuro",-($BL28-BK28)*$BD28,0) -> -52556.964 | BS28: =IF($BE28="futuro",-($BL28-BL28)*$BD28,0) -> 0 | BT28: =IF($BE28="futuro",-($BL28-BM28)*$BD28,0) -> 52556.964 | BU28: =IF($BE28="futuro",-($BL28-BN28)*$BD28,0) -> 105113.93 | BV28: =IF($BE28="futuro",-($BL28-BO28)*$BD28,0) -> 157670.89 | BW28: =IF(AND($BH28="CC",($BC28-BI28)<0),(BI28-$BC28)*$BD28, IF(AND($BH28="VC",($BC28-BI28)<0),($BC28-BI28)*-$BD28, IF(AND($BH28="CP",($BC28-BI28)>0),(BI28-$BC28)*$BD28*-1, IF(AND($BH28="VP",($BC28-BI28)>0),(BI28-$BC28)*$BD28*-1,0)))) -> 0 | BX28: =IF(AND($BH28="CC",($BC28-BJ28)<0),(BJ28-$BC28)*$BD28, IF(AND($BH28="VC",($BC28-BJ28)<0),($BC28-BJ28)*-$BD28, IF(AND($BH28="CP",($BC28-BJ28)>0),(BJ28-$BC28)*$BD28*-1, IF(AND($BH28="VP",($BC28-BJ28)>0),(BJ28-$BC28)*$BD28*-1,0)))) -> 0 | BY28: =IF(AND($BH28="CC",($BC28-BK28)<0),(BK28-$BC28)*$BD28, IF(AND($BH28="VC",($BC28-BK28)<0),($BC28-BK28)*-$BD28, IF(AND($BH28="CP",($BC28-BK28)>0),(BK28-$BC28)*$BD28*-1, IF(AND($BH28="VP",($BC28-BK28)>0),(BK28-$BC28)*$BD28*-1,0)))) -> 0 | BZ28: =IF(AND($BH28="CC",($BC28-BL28)<0),(BL28-$BC28)*$BD28, IF(AND($BH28="VC",($BC28-BL28)<0),($BC28-BL28)*-$BD28, IF(AND($BH28="CP",($BC28-BL28)>0),(BL28-$BC28)*$BD28*-1, IF(AND($BH28="VP",($BC28-BL28)>0),(BL28-$BC28)*$BD28*-1,0)))) -> 0 | CA28: =IF(AND($BH28="CC",($BC28-BM28)<0),(BM28-$BC28)*$BD28, IF(AND($BH28="VC",($BC28-BM28)<0),($BC28-BM28)*-$BD28, IF(AND($BH28="CP",($BC28-BM28)>0),(BM28-$BC28)*$BD28*-1, IF(AND($BH28="VP",($BC28-BM28)>0),(BM28-$BC28)*$BD28*-1,0)))) -> 0 | CB28: =IF(AND($BH28="CC",($BC28-BN28)<0),(BN28-$BC28)*$BD28, IF(AND($BH28="VC",($BC28-BN28)<0),($BC28-BN28)*-$BD28, IF(AND($BH28="CP",($BC28-BN28)>0),(BN28-$BC28)*$BD28*-1, IF(AND($BH28="VP",($BC28-BN28)>0),(BN28-$BC28)*$BD28*-1,0)))) -> 0 | CC28: =IF(AND($BH28="CC",($BC28-BO28)<0),(BO28-$BC28)*$BD28, IF(AND($BH28="VC",($BC28-BO28)<0),($BC28-BO28)*-$BD28, IF(AND($BH28="CP",($BC28-BO28)>0),(BO28-$BC28)*$BD28*-1, IF(AND($BH28="VP",($BC28-BO28)>0),(BO28-$BC28)*$BD28*-1,0)))) -> 0 | CD28: =IF(AND($BH28="CC",($BC28-BI28)<0),$BD28*1, IF(AND($BH28="VC",($BC28-BI28)<0),$BD28*1, IF(AND($BH28="CP",($BC28-BI28)>0),$BD28*-1, IF(AND($BH28="VP",($BC28-BI28)>0),$BD28*-1,0)))) -> 0 | CE28: =IF(AND($BH28="CC",($BC28-BJ28)<0),$BD28*1, IF(AND($BH28="VC",($BC28-BJ28)<0),$BD28*1, IF(AND($BH28="CP",($BC28-BJ28)>0),$BD28*-1, IF(AND($BH28="VP",($BC28-BJ28)>0),$BD28*-1,0)))) -> 0 | CF28: =IF(AND($BH28="CC",($BC28-BK28)<0),$BD28*1, IF(AND($BH28="VC",($BC28-BK28)<0),$BD28*1, IF(AND($BH28="CP",($BC28-BK28)>0),$BD28*-1, IF(AND($BH28="VP",($BC28-BK28)>0),$BD28*-1,0)))) -> 0 | CG28: =IF(AND($BH28="CC",($BC28-BL28)<0),$BD28*1, IF(AND($BH28="VC",($BC28-BL28)<0),$BD28*1, IF(AND($BH28="CP",($BC28-BL28)>0),$BD28*-1, IF(AND($BH28="VP",($BC28-BL28)>0),$BD28*-1,0)))) -> 0 | CH28: =IF(AND($BH28="CC",($BC28-BM28)<0),$BD28*1, IF(AND($BH28="VC",($BC28-BM28)<0),$BD28*1, IF(AND($BH28="CP",($BC28-BM28)>0),$BD28*-1, IF(AND($BH28="VP",($BC28-BM28)>0),$BD28*-1,0)))) -> 0 | CI28: =IF(AND($BH28="CC",($BC28-BN28)<0),$BD28*1, IF(AND($BH28="VC",($BC28-BN28)<0),$BD28*1, IF(AND($BH28="CP",($BC28-BN28)>0),$BD28*-1, IF(AND($BH28="VP",($BC28-BN28)>0),$BD28*-1,0)))) -> 0 | CJ28: =IF(AND($BH28="CC",($BC28-BO28)<0),$BD28*1, IF(AND($BH28="VC",($BC28-BO28)<0),$BD28*1, IF(AND($BH28="CP",($BC28-BO28)>0),$BD28*-1, IF(AND($BH28="VP",($BC28-BO28)>0),$BD28*-1,0)))) -> 0 | CK28: =Tabla3[[#This Row],[Tns]] -> 2921.115 | CL28: =IF(ISERROR(VLOOKUP(VALUE(E28),'Clientes CBOT'!A:A,1,0)),"VER","ok") -> ok
A29: P | B29: R | C29: 766 | D29: 0 | E29: 20176 | F29: C | H29: F1 | I29: .AS-0000026A | J29: 1276 | K29: 2 | L29: 370000 | M29: JAN 26 SOYBEANS | N29: 11.08 | O29: 20251030 | Q29: 202601 | S29: F | U29: 0 | V29: 0 | X29: FYO ACOPIO SA | Z29: 20251030 | AA29: 1 | AB29: 1A | AC29: S- | AF29: 11.08000000 | AL29: 0 | AM29: 37.0000 | AN29: USD | AO29: 2636250 | AP29: 1093750000 | AQ29: 0 | AR29: 50000 | AS29: 5J30 Pva0 | AT29: 116141276 | AU29: 0,0000 | AV29: S | AW29: CBT | AX29: Comdty | AY29: Soja | AZ29: =IF(VLOOKUP(AY29,Conversor!B:C,2,0)="HS",0.01,VLOOKUP(AY29,Conversor!B:C,2,0)) -> 0.36743 | BA29: =IF(BG29="v",-AM29/10000,AL29/10000) -> -37 | BB29: =IF(AQ29=0,AP29/1000000*AZ29,AQ29/1000000*AZ29) -> 401.87656 | BC29: =U29/1000000*AZ29 -> 0 | BD29: =IF(OR(E29="FUTUR",E29="f20176"),0,VLOOKUP(AY29,Conversor!G:I,3,0)*BA29) -> -5034.96 | BE29: =IF(LEFT(M29,4)="call","Call",IF(LEFT(M29,3)="put","Put","Futuro")) -> Futuro | BF29: =IF(BE29="futuro","no","si") -> no | BG29: =IF(AL29=0,"V","C") -> V | BH29: =IF(BE29="futuro","",CONCATENATE(BG29,LEFT(BE29,1))) | BI29: =$BB29*(1+BI$2) -> 281.31359 | BJ29: =$BB29*(1+BJ$2) -> 321.50125 | BK29: =$BB29*(1+BK$2) -> 361.68891 | BL29: =$BB29*(1+BL$2) -> 401.87656 | BM29: =$BB29*(1+BM$2) -> 442.06422 | BN29: =$BB29*(1+BN$2) -> 482.25187 | BO29: =$BB29*(1+BO$2) -> 522.43953 | BP29: =IF($BE29="futuro",-($BL29-BI29)*$BD29,0) -> 607029.73 | BQ29: =IF($BE29="futuro",-($BL29-BJ29)*$BD29,0) -> 404686.48 | BR29: =IF($BE29="futuro",-($BL29-BK29)*$BD29,0) -> 202343.24 | BS29: =IF($BE29="futuro",-($BL29-BL29)*$BD29,0) -> 0 | BT29: =IF($BE29="futuro",-($BL29-BM29)*$BD29,0) -> -202343.24 | BU29: =IF($BE29="futuro",-($BL29-BN29)*$BD29,0) -> -404686.48 | BV29: =IF($BE29="futuro",-($BL29-BO29)*$BD29,0) -> -607029.73 | BW29: =IF(AND($BH29="CC",($BC29-BI29)<0),(BI29-$BC29)*$BD29, IF(AND($BH29="VC",($BC29-BI29)<0),($BC29-BI29)*-$BD29, IF(AND($BH29="CP",($BC29-BI29)>0),(BI29-$BC29)*$BD29*-1, IF(AND($BH29="VP",($BC29-BI29)>0),(BI29-$BC29)*$BD29*-1,0)))) -> 0 | BX29: =IF(AND($BH29="CC",($BC29-BJ29)<0),(BJ29-$BC29)*$BD29, IF(AND($BH29="VC",($BC29-BJ29)<0),($BC29-BJ29)*-$BD29, IF(AND($BH29="CP",($BC29-BJ29)>0),(BJ29-$BC29)*$BD29*-1, IF(AND($BH29="VP",($BC29-BJ29)>0),(BJ29-$BC29)*$BD29*-1,0)))) -> 0 | BY29: =IF(AND($BH29="CC",($BC29-BK29)<0),(BK29-$BC29)*$BD29, IF(AND($BH29="VC",($BC29-BK29)<0),($BC29-BK29)*-$BD29, IF(AND($BH29="CP",($BC29-BK29)>0),(BK29-$BC29)*$BD29*-1, IF(AND($BH29="VP",($BC29-BK29)>0),(BK29-$BC29)*$BD29*-1,0)))) -> 0 | BZ29: =IF(AND($BH29="CC",($BC29-BL29)<0),(BL29-$BC29)*$BD29, IF(AND($BH29="VC",($BC29-BL29)<0),($BC29-BL29)*-$BD29, IF(AND($BH29="CP",($BC29-BL29)>0),(BL29-$BC29)*$BD29*-1, IF(AND($BH29="VP",($BC29-BL29)>0),(BL29-$BC29)*$BD29*-1,0)))) -> 0 | CA29: =IF(AND($BH29="CC",($BC29-BM29)<0),(BM29-$BC29)*$BD29, IF(AND($BH29="VC",($BC29-BM29)<0),($BC29-BM29)*-$BD29, IF(AND($BH29="CP",($BC29-BM29)>0),(BM29-$BC29)*$BD29*-1, IF(AND($BH29="VP",($BC29-BM29)>0),(BM29-$BC29)*$BD29*-1,0)))) -> 0 | CB29: =IF(AND($BH29="CC",($BC29-BN29)<0),(BN29-$BC29)*$BD29, IF(AND($BH29="VC",($BC29-BN29)<0),($BC29-BN29)*-$BD29, IF(AND($BH29="CP",($BC29-BN29)>0),(BN29-$BC29)*$BD29*-1, IF(AND($BH29="VP",($BC29-BN29)>0),(BN29-$BC29)*$BD29*-1,0)))) -> 0 | CC29: =IF(AND($BH29="CC",($BC29-BO29)<0),(BO29-$BC29)*$BD29, IF(AND($BH29="VC",($BC29-BO29)<0),($BC29-BO29)*-$BD29, IF(AND($BH29="CP",($BC29-BO29)>0),(BO29-$BC29)*$BD29*-1, IF(AND($BH29="VP",($BC29-BO29)>0),(BO29-$BC29)*$BD29*-1,0)))) -> 0 | CD29: =IF(AND($BH29="CC",($BC29-BI29)<0),$BD29*1, IF(AND($BH29="VC",($BC29-BI29)<0),$BD29*1, IF(AND($BH29="CP",($BC29-BI29)>0),$BD29*-1, IF(AND($BH29="VP",($BC29-BI29)>0),$BD29*-1,0)))) -> 0 | CE29: =IF(AND($BH29="CC",($BC29-BJ29)<0),$BD29*1, IF(AND($BH29="VC",($BC29-BJ29)<0),$BD29*1, IF(AND($BH29="CP",($BC29-BJ29)>0),$BD29*-1, IF(AND($BH29="VP",($BC29-BJ29)>0),$BD29*-1,0)))) -> 0 | CF29: =IF(AND($BH29="CC",($BC29-BK29)<0),$BD29*1, IF(AND($BH29="VC",($BC29-BK29)<0),$BD29*1, IF(AND($BH29="CP",($BC29-BK29)>0),$BD29*-1, IF(AND($BH29="VP",($BC29-BK29)>0),$BD29*-1,0)))) -> 0 | CG29: =IF(AND($BH29="CC",($BC29-BL29)<0),$BD29*1, IF(AND($BH29="VC",($BC29-BL29)<0),$BD29*1, IF(AND($BH29="CP",($BC29-BL29)>0),$BD29*-1, IF(AND($BH29="VP",($BC29-BL29)>0),$BD29*-1,0)))) -> 0 | CH29: =IF(AND($BH29="CC",($BC29-BM29)<0),$BD29*1, IF(AND($BH29="VC",($BC29-BM29)<0),$BD29*1, IF(AND($BH29="CP",($BC29-BM29)>0),$BD29*-1, IF(AND($BH29="VP",($BC29-BM29)>0),$BD29*-1,0)))) -> 0 | CI29: =IF(AND($BH29="CC",($BC29-BN29)<0),$BD29*1, IF(AND($BH29="VC",($BC29-BN29)<0),$BD29*1, IF(AND($BH29="CP",($BC29-BN29)>0),$BD29*-1, IF(AND($BH29="VP",($BC29-BN29)>0),$BD29*-1,0)))) -> 0 | CJ29: =IF(AND($BH29="CC",($BC29-BO29)<0),$BD29*1, IF(AND($BH29="VC",($BC29-BO29)<0),$BD29*1, IF(AND($BH29="CP",($BC29-BO29)>0),$BD29*-1, IF(AND($BH29="VP",($BC29-BO29)>0),$BD29*-1,0)))) -> 0 | CK29: =Tabla3[[#This Row],[Tns]] -> -5034.96 | CL29: =IF(ISERROR(VLOOKUP(VALUE(E29),'Clientes CBOT'!A:A,1,0)),"VER","ok") -> ok
A30: P | B30: R | C30: 766 | D30: 0 | E30: 20176 | F30: C | H30: F1 | I30: .AS-0000026A | J30: 3899 | K30: 2 | L30: 370000 | M30: JAN 26 SOYBEANS | N30: 11.55 | O30: 20251117 | Q30: 202601 | S30: F | U30: 0 | V30: 0 | X30: FYO ACOPIO SA | Z30: 20251117 | AA30: 1 | AB30: 1A | AC30: S- | AF30: 11.55000000 | AL30: 0 | AM30: 37.0000 | AN30: USD | AO30: 11331250 | AP30: 1093750000 | AQ30: 0 | AR30: 50000 | AS30: 5K17 FNb0 | AT30: 116283899 | AU30: 0,0000 | AV30: S | AW30: CBT | AX30: Comdty | AY30: Soja | AZ30: =IF(VLOOKUP(AY30,Conversor!B:C,2,0)="HS",0.01,VLOOKUP(AY30,Conversor!B:C,2,0)) -> 0.36743 | BA30: =IF(BG30="v",-AM30/10000,AL30/10000) -> -37 | BB30: =IF(AQ30=0,AP30/1000000*AZ30,AQ30/1000000*AZ30) -> 401.87656 | BC30: =U30/1000000*AZ30 -> 0 | BD30: =IF(OR(E30="FUTUR",E30="f20176"),0,VLOOKUP(AY30,Conversor!G:I,3,0)*BA30) -> -5034.96 | BE30: =IF(LEFT(M30,4)="call","Call",IF(LEFT(M30,3)="put","Put","Futuro")) -> Futuro | BF30: =IF(BE30="futuro","no","si") -> no | BG30: =IF(AL30=0,"V","C") -> V | BH30: =IF(BE30="futuro","",CONCATENATE(BG30,LEFT(BE30,1))) | BI30: =$BB30*(1+BI$2) -> 281.31359 | BJ30: =$BB30*(1+BJ$2) -> 321.50125 | BK30: =$BB30*(1+BK$2) -> 361.68891 | BL30: =$BB30*(1+BL$2) -> 401.87656 | BM30: =$BB30*(1+BM$2) -> 442.06422 | BN30: =$BB30*(1+BN$2) -> 482.25187 | BO30: =$BB30*(1+BO$2) -> 522.43953 | BP30: =IF($BE30="futuro",-($BL30-BI30)*$BD30,0) -> 607029.73 | BQ30: =IF($BE30="futuro",-($BL30-BJ30)*$BD30,0) -> 404686.48 | BR30: =IF($BE30="futuro",-($BL30-BK30)*$BD30,0) -> 202343.24 | BS30: =IF($BE30="futuro",-($BL30-BL30)*$BD30,0) -> 0 | BT30: =IF($BE30="futuro",-($BL30-BM30)*$BD30,0) -> -202343.24 | BU30: =IF($BE30="futuro",-($BL30-BN30)*$BD30,0) -> -404686.48 | BV30: =IF($BE30="futuro",-($BL30-BO30)*$BD30,0) -> -607029.73 | BW30: =IF(AND($BH30="CC",($BC30-BI30)<0),(BI30-$BC30)*$BD30, IF(AND($BH30="VC",($BC30-BI30)<0),($BC30-BI30)*-$BD30, IF(AND($BH30="CP",($BC30-BI30)>0),(BI30-$BC30)*$BD30*-1, IF(AND($BH30="VP",($BC30-BI30)>0),(BI30-$BC30)*$BD30*-1,0)))) -> 0 | BX30: =IF(AND($BH30="CC",($BC30-BJ30)<0),(BJ30-$BC30)*$BD30, IF(AND($BH30="VC",($BC30-BJ30)<0),($BC30-BJ30)*-$BD30, IF(AND($BH30="CP",($BC30-BJ30)>0),(BJ30-$BC30)*$BD30*-1, IF(AND($BH30="VP",($BC30-BJ30)>0),(BJ30-$BC30)*$BD30*-1,0)))) -> 0 | BY30: =IF(AND($BH30="CC",($BC30-BK30)<0),(BK30-$BC30)*$BD30, IF(AND($BH30="VC",($BC30-BK30)<0),($BC30-BK30)*-$BD30, IF(AND($BH30="CP",($BC30-BK30)>0),(BK30-$BC30)*$BD30*-1, IF(AND($BH30="VP",($BC30-BK30)>0),(BK30-$BC30)*$BD30*-1,0)))) -> 0 | BZ30: =IF(AND($BH30="CC",($BC30-BL30)<0),(BL30-$BC30)*$BD30, IF(AND($BH30="VC",($BC30-BL30)<0),($BC30-BL30)*-$BD30, IF(AND($BH30="CP",($BC30-BL30)>0),(BL30-$BC30)*$BD30*-1, IF(AND($BH30="VP",($BC30-BL30)>0),(BL30-$BC30)*$BD30*-1,0)))) -> 0 | CA30: =IF(AND($BH30="CC",($BC30-BM30)<0),(BM30-$BC30)*$BD30, IF(AND($BH30="VC",($BC30-BM30)<0),($BC30-BM30)*-$BD30, IF(AND($BH30="CP",($BC30-BM30)>0),(BM30-$BC30)*$BD30*-1, IF(AND($BH30="VP",($BC30-BM30)>0),(BM30-$BC30)*$BD30*-1,0)))) -> 0 | CB30: =IF(AND($BH30="CC",($BC30-BN30)<0),(BN30-$BC30)*$BD30, IF(AND($BH30="VC",($BC30-BN30)<0),($BC30-BN30)*-$BD30, IF(AND($BH30="CP",($BC30-BN30)>0),(BN30-$BC30)*$BD30*-1, IF(AND($BH30="VP",($BC30-BN30)>0),(BN30-$BC30)*$BD30*-1,0)))) -> 0 | CC30: =IF(AND($BH30="CC",($BC30-BO30)<0),(BO30-$BC30)*$BD30, IF(AND($BH30="VC",($BC30-BO30)<0),($BC30-BO30)*-$BD30, IF(AND($BH30="CP",($BC30-BO30)>0),(BO30-$BC30)*$BD30*-1, IF(AND($BH30="VP",($BC30-BO30)>0),(BO30-$BC30)*$BD30*-1,0)))) -> 0 | CD30: =IF(AND($BH30="CC",($BC30-BI30)<0),$BD30*1, IF(AND($BH30="VC",($BC30-BI30)<0),$BD30*1, IF(AND($BH30="CP",($BC30-BI30)>0),$BD30*-1, IF(AND($BH30="VP",($BC30-BI30)>0),$BD30*-1,0)))) -> 0 | CE30: =IF(AND($BH30="CC",($BC30-BJ30)<0),$BD30*1, IF(AND($BH30="VC",($BC30-BJ30)<0),$BD30*1, IF(AND($BH30="CP",($BC30-BJ30)>0),$BD30*-1, IF(AND($BH30="VP",($BC30-BJ30)>0),$BD30*-1,0)))) -> 0 | CF30: =IF(AND($BH30="CC",($BC30-BK30)<0),$BD30*1, IF(AND($BH30="VC",($BC30-BK30)<0),$BD30*1, IF(AND($BH30="CP",($BC30-BK30)>0),$BD30*-1, IF(AND($BH30="VP",($BC30-BK30)>0),$BD30*-1,0)))) -> 0 | CG30: =IF(AND($BH30="CC",($BC30-BL30)<0),$BD30*1, IF(AND($BH30="VC",($BC30-BL30)<0),$BD30*1, IF(AND($BH30="CP",($BC30-BL30)>0),$BD30*-1, IF(AND($BH30="VP",($BC30-BL30)>0),$BD30*-1,0)))) -> 0 | CH30: =IF(AND($BH30="CC",($BC30-BM30)<0),$BD30*1, IF(AND($BH30="VC",($BC30-BM30)<0),$BD30*1, IF(AND($BH30="CP",($BC30-BM30)>0),$BD30*-1, IF(AND($BH30="VP",($BC30-BM30)>0),$BD30*-1,0)))) -> 0 | CI30: =IF(AND($BH30="CC",($BC30-BN30)<0),$BD30*1, IF(AND($BH30="VC",($BC30-BN30)<0),$BD30*1, IF(AND($BH30="CP",($BC30-BN30)>0),$BD30*-1, IF(AND($BH30="VP",($BC30-BN30)>0),$BD30*-1,0)))) -> 0 | CJ30: =IF(AND($BH30="CC",($BC30-BO30)<0),$BD30*1, IF(AND($BH30="VC",($BC30-BO30)<0),$BD30*1, IF(AND($BH30="CP",($BC30-BO30)>0),$BD30*-1, IF(AND($BH30="VP",($BC30-BO30)>0),$BD30*-1,0)))) -> 0 | CK30: =Tabla3[[#This Row],[Tns]] -> -5034.96 | CL30: =IF(ISERROR(VLOOKUP(VALUE(E30),'Clientes CBOT'!A:A,1,0)),"VER","ok") -> ok
A31: P | B31: R | C31: 766 | D31: 0 | E31: 20176 | F31: C | H31: F1 | I31: .AS-0000026E | J31: 7780 | K31: 2 | L31: 200000 | M31: MAY 26 SOYBEANS | N31: 10.85 3/4 | O31: 20251023 | Q31: 202605 | S31: F | U31: 0 | V31: 0 | X31: FYO ACOPIO SA | Z31: 20251023 | AA31: 1 | AB31: 1A | AC31: S- | AF31: 10.85750000 | AL31: 0 | AM31: 20.0000 | AN31: USD | AO31: -3100000 | AP31: 1116750000 | AQ31: 0 | AR31: 50000 | AS31: 5J23 ZMz0 | AT31: 116067780 | AU31: 0,0000 | AV31: S | AW31: CBT | AX31: Comdty | AY31: Soja | AZ31: =IF(VLOOKUP(AY31,Conversor!B:C,2,0)="HS",0.01,VLOOKUP(AY31,Conversor!B:C,2,0)) -> 0.36743 | BA31: =IF(BG31="v",-AM31/10000,AL31/10000) -> -20 | BB31: =IF(AQ31=0,AP31/1000000*AZ31,AQ31/1000000*AZ31) -> 410.32745 | BC31: =U31/1000000*AZ31 -> 0 | BD31: =IF(OR(E31="FUTUR",E31="f20176"),0,VLOOKUP(AY31,Conversor!G:I,3,0)*BA31) -> -2721.6 | BE31: =IF(LEFT(M31,4)="call","Call",IF(LEFT(M31,3)="put","Put","Futuro")) -> Futuro | BF31: =IF(BE31="futuro","no","si") -> no | BG31: =IF(AL31=0,"V","C") -> V | BH31: =IF(BE31="futuro","",CONCATENATE(BG31,LEFT(BE31,1))) | BI31: =$BB31*(1+BI$2) -> 287.22922 | BJ31: =$BB31*(1+BJ$2) -> 328.26196 | BK31: =$BB31*(1+BK$2) -> 369.29471 | BL31: =$BB31*(1+BL$2) -> 410.32745 | BM31: =$BB31*(1+BM$2) -> 451.3602 | BN31: =$BB31*(1+BN$2) -> 492.39294 | BO31: =$BB31*(1+BO$2) -> 533.42569 | BP31: =IF($BE31="futuro",-($BL31-BI31)*$BD31,0) -> 335024.16 | BQ31: =IF($BE31="futuro",-($BL31-BJ31)*$BD31,0) -> 223349.44 | BR31: =IF($BE31="futuro",-($BL31-BK31)*$BD31,0) -> 111674.72 | BS31: =IF($BE31="futuro",-($BL31-BL31)*$BD31,0) -> 0 | BT31: =IF($BE31="futuro",-($BL31-BM31)*$BD31,0) -> -111674.72 | BU31: =IF($BE31="futuro",-($BL31-BN31)*$BD31,0) -> -223349.44 | BV31: =IF($BE31="futuro",-($BL31-BO31)*$BD31,0) -> -335024.16 | BW31: =IF(AND($BH31="CC",($BC31-BI31)<0),(BI31-$BC31)*$BD31, IF(AND($BH31="VC",($BC31-BI31)<0),($BC31-BI31)*-$BD31, IF(AND($BH31="CP",($BC31-BI31)>0),(BI31-$BC31)*$BD31*-1, IF(AND($BH31="VP",($BC31-BI31)>0),(BI31-$BC31)*$BD31*-1,0)))) -> 0 | BX31: =IF(AND($BH31="CC",($BC31-BJ31)<0),(BJ31-$BC31)*$BD31, IF(AND($BH31="VC",($BC31-BJ31)<0),($BC31-BJ31)*-$BD31, IF(AND($BH31="CP",($BC31-BJ31)>0),(BJ31-$BC31)*$BD31*-1, IF(AND($BH31="VP",($BC31-BJ31)>0),(BJ31-$BC31)*$BD31*-1,0)))) -> 0 | BY31: =IF(AND($BH31="CC",($BC31-BK31)<0),(BK31-$BC31)*$BD31, IF(AND($BH31="VC",($BC31-BK31)<0),($BC31-BK31)*-$BD31, IF(AND($BH31="CP",($BC31-BK31)>0),(BK31-$BC31)*$BD31*-1, IF(AND($BH31="VP",($BC31-BK31)>0),(BK31-$BC31)*$BD31*-1,0)))) -> 0 | BZ31: =IF(AND($BH31="CC",($BC31-BL31)<0),(BL31-$BC31)*$BD31, IF(AND($BH31="VC",($BC31-BL31)<0),($BC31-BL31)*-$BD31, IF(AND($BH31="CP",($BC31-BL31)>0),(BL31-$BC31)*$BD31*-1, IF(AND($BH31="VP",($BC31-BL31)>0),(BL31-$BC31)*$BD31*-1,0)))) -> 0 | CA31: =IF(AND($BH31="CC",($BC31-BM31)<0),(BM31-$BC31)*$BD31, IF(AND($BH31="VC",($BC31-BM31)<0),($BC31-BM31)*-$BD31, IF(AND($BH31="CP",($BC31-BM31)>0),(BM31-$BC31)*$BD31*-1, IF(AND($BH31="VP",($BC31-BM31)>0),(BM31-$BC31)*$BD31*-1,0)))) -> 0 | CB31: =IF(AND($BH31="CC",($BC31-BN31)<0),(BN31-$BC31)*$BD31, IF(AND($BH31="VC",($BC31-BN31)<0),($BC31-BN31)*-$BD31, IF(AND($BH31="CP",($BC31-BN31)>0),(BN31-$BC31)*$BD31*-1, IF(AND($BH31="VP",($BC31-BN31)>0),(BN31-$BC31)*$BD31*-1,0)))) -> 0 | CC31: =IF(AND($BH31="CC",($BC31-BO31)<0),(BO31-$BC31)*$BD31, IF(AND($BH31="VC",($BC31-BO31)<0),($BC31-BO31)*-$BD31, IF(AND($BH31="CP",($BC31-BO31)>0),(BO31-$BC31)*$BD31*-1, IF(AND($BH31="VP",($BC31-BO31)>0),(BO31-$BC31)*$BD31*-1,0)))) -> 0 | CD31: =IF(AND($BH31="CC",($BC31-BI31)<0),$BD31*1, IF(AND($BH31="VC",($BC31-BI31)<0),$BD31*1, IF(AND($BH31="CP",($BC31-BI31)>0),$BD31*-1, IF(AND($BH31="VP",($BC31-BI31)>0),$BD31*-1,0)))) -> 0 | CE31: =IF(AND($BH31="CC",($BC31-BJ31)<0),$BD31*1, IF(AND($BH31="VC",($BC31-BJ31)<0),$BD31*1, IF(AND($BH31="CP",($BC31-BJ31)>0),$BD31*-1, IF(AND($BH31="VP",($BC31-BJ31)>0),$BD31*-1,0)))) -> 0 | CF31: =IF(AND($BH31="CC",($BC31-BK31)<0),$BD31*1, IF(AND($BH31="VC",($BC31-BK31)<0),$BD31*1, IF(AND($BH31="CP",($BC31-BK31)>0),$BD31*-1, IF(AND($BH31="VP",($BC31-BK31)>0),$BD31*-1,0)))) -> 0 | CG31: =IF(AND($BH31="CC",($BC31-BL31)<0),$BD31*1, IF(AND($BH31="VC",($BC31-BL31)<0),$BD31*1, IF(AND($BH31="CP",($BC31-BL31)>0),$BD31*-1, IF(AND($BH31="VP",($BC31-BL31)>0),$BD31*-1,0)))) -> 0 | CH31: =IF(AND($BH31="CC",($BC31-BM31)<0),$BD31*1, IF(AND($BH31="VC",($BC31-BM31)<0),$BD31*1, IF(AND($BH31="CP",($BC31-BM31)>0),$BD31*-1, IF(AND($BH31="VP",($BC31-BM31)>0),$BD31*-1,0)))) -> 0 | CI31: =IF(AND($BH31="CC",($BC31-BN31)<0),$BD31*1, IF(AND($BH31="VC",($BC31-BN31)<0),$BD31*1, IF(AND($BH31="CP",($BC31-BN31)>0),$BD31*-1, IF(AND($BH31="VP",($BC31-BN31)>0),$BD31*-1,0)))) -> 0 | CJ31: =IF(AND($BH31="CC",($BC31-BO31)<0),$BD31*1, IF(AND($BH31="VC",($BC31-BO31)<0),$BD31*1, IF(AND($BH31="CP",($BC31-BO31)>0),$BD31*-1, IF(AND($BH31="VP",($BC31-BO31)>0),$BD31*-1,0)))) -> 0 | CK31: =Tabla3[[#This Row],[Tns]] -> -2721.6 | CL31: =IF(ISERROR(VLOOKUP(VALUE(E31),'Clientes CBOT'!A:A,1,0)),"VER","ok") -> ok
A32: P | B32: R | C32: 766 | D32: 0 | E32: 20176 | F32: C | H32: F1 | I32: .AS-0000026E | J32: 8107 | K32: 2 | L32: 450000 | M32: MAY 26 SOYBEANS | N32: 10.87 | O32: 20251023 | Q32: 202605 | S32: F | U32: 0 | V32: 0 | X32: FYO ACOPIO SA | Z32: 20251023 | AA32: 1 | AB32: 1A | AC32: S- | AF32: 10.87000000 | AL32: 0 | AM32: 45.0000 | AN32: USD | AO32: -6693750 | AP32: 1116750000 | AQ32: 0 | AR32: 50000 | AS32: 5J23 0qs0 | AT32: 116068107 | AU32: 0,0000 | AV32: S | AW32: CBT | AX32: Comdty | AY32: Soja | AZ32: =IF(VLOOKUP(AY32,Conversor!B:C,2,0)="HS",0.01,VLOOKUP(AY32,Conversor!B:C,2,0)) -> 0.36743 | BA32: =IF(BG32="v",-AM32/10000,AL32/10000) -> -45 | BB32: =IF(AQ32=0,AP32/1000000*AZ32,AQ32/1000000*AZ32) -> 410.32745 | BC32: =U32/1000000*AZ32 -> 0 | BD32: =IF(OR(E32="FUTUR",E32="f20176"),0,VLOOKUP(AY32,Conversor!G:I,3,0)*BA32) -> -6123.6 | BE32: =IF(LEFT(M32,4)="call","Call",IF(LEFT(M32,3)="put","Put","Futuro")) -> Futuro | BF32: =IF(BE32="futuro","no","si") -> no | BG32: =IF(AL32=0,"V","C") -> V | BH32: =IF(BE32="futuro","",CONCATENATE(BG32,LEFT(BE32,1))) | BI32: =$BB32*(1+BI$2) -> 287.22922 | BJ32: =$BB32*(1+BJ$2) -> 328.26196 | BK32: =$BB32*(1+BK$2) -> 369.29471 | BL32: =$BB32*(1+BL$2) -> 410.32745 | BM32: =$BB32*(1+BM$2) -> 451.3602 | BN32: =$BB32*(1+BN$2) -> 492.39294 | BO32: =$BB32*(1+BO$2) -> 533.42569 | BP32: =IF($BE32="futuro",-($BL32-BI32)*$BD32,0) -> 753804.36 | BQ32: =IF($BE32="futuro",-($BL32-BJ32)*$BD32,0) -> 502536.24 | BR32: =IF($BE32="futuro",-($BL32-BK32)*$BD32,0) -> 251268.12 | BS32: =IF($BE32="futuro",-($BL32-BL32)*$BD32,0) -> 0 | BT32: =IF($BE32="futuro",-($BL32-BM32)*$BD32,0) -> -251268.12 | BU32: =IF($BE32="futuro",-($BL32-BN32)*$BD32,0) -> -502536.24 | BV32: =IF($BE32="futuro",-($BL32-BO32)*$BD32,0) -> -753804.36 | BW32: =IF(AND($BH32="CC",($BC32-BI32)<0),(BI32-$BC32)*$BD32, IF(AND($BH32="VC",($BC32-BI32)<0),($BC32-BI32)*-$BD32, IF(AND($BH32="CP",($BC32-BI32)>0),(BI32-$BC32)*$BD32*-1, IF(AND($BH32="VP",($BC32-BI32)>0),(BI32-$BC32)*$BD32*-1,0)))) -> 0 | BX32: =IF(AND($BH32="CC",($BC32-BJ32)<0),(BJ32-$BC32)*$BD32, IF(AND($BH32="VC",($BC32-BJ32)<0),($BC32-BJ32)*-$BD32, IF(AND($BH32="CP",($BC32-BJ32)>0),(BJ32-$BC32)*$BD32*-1, IF(AND($BH32="VP",($BC32-BJ32)>0),(BJ32-$BC32)*$BD32*-1,0)))) -> 0 | BY32: =IF(AND($BH32="CC",($BC32-BK32)<0),(BK32-$BC32)*$BD32, IF(AND($BH32="VC",($BC32-BK32)<0),($BC32-BK32)*-$BD32, IF(AND($BH32="CP",($BC32-BK32)>0),(BK32-$BC32)*$BD32*-1, IF(AND($BH32="VP",($BC32-BK32)>0),(BK32-$BC32)*$BD32*-1,0)))) -> 0 | BZ32: =IF(AND($BH32="CC",($BC32-BL32)<0),(BL32-$BC32)*$BD32, IF(AND($BH32="VC",($BC32-BL32)<0),($BC32-BL32)*-$BD32, IF(AND($BH32="CP",($BC32-BL32)>0),(BL32-$BC32)*$BD32*-1, IF(AND($BH32="VP",($BC32-BL32)>0),(BL32-$BC32)*$BD32*-1,0)))) -> 0 | CA32: =IF(AND($BH32="CC",($BC32-BM32)<0),(BM32-$BC32)*$BD32, IF(AND($BH32="VC",($BC32-BM32)<0),($BC32-BM32)*-$BD32, IF(AND($BH32="CP",($BC32-BM32)>0),(BM32-$BC32)*$BD32*-1, IF(AND($BH32="VP",($BC32-BM32)>0),(BM32-$BC32)*$BD32*-1,0)))) -> 0 | CB32: =IF(AND($BH32="CC",($BC32-BN32)<0),(BN32-$BC32)*$BD32, IF(AND($BH32="VC",($BC32-BN32)<0),($BC32-BN32)*-$BD32, IF(AND($BH32="CP",($BC32-BN32)>0),(BN32-$BC32)*$BD32*-1, IF(AND($BH32="VP",($BC32-BN32)>0),(BN32-$BC32)*$BD32*-1,0)))) -> 0 | CC32: =IF(AND($BH32="CC",($BC32-BO32)<0),(BO32-$BC32)*$BD32, IF(AND($BH32="VC",($BC32-BO32)<0),($BC32-BO32)*-$BD32, IF(AND($BH32="CP",($BC32-BO32)>0),(BO32-$BC32)*$BD32*-1, IF(AND($BH32="VP",($BC32-BO32)>0),(BO32-$BC32)*$BD32*-1,0)))) -> 0 | CD32: =IF(AND($BH32="CC",($BC32-BI32)<0),$BD32*1, IF(AND($BH32="VC",($BC32-BI32)<0),$BD32*1, IF(AND($BH32="CP",($BC32-BI32)>0),$BD32*-1, IF(AND($BH32="VP",($BC32-BI32)>0),$BD32*-1,0)))) -> 0 | CE32: =IF(AND($BH32="CC",($BC32-BJ32)<0),$BD32*1, IF(AND($BH32="VC",($BC32-BJ32)<0),$BD32*1, IF(AND($BH32="CP",($BC32-BJ32)>0),$BD32*-1, IF(AND($BH32="VP",($BC32-BJ32)>0),$BD32*-1,0)))) -> 0 | CF32: =IF(AND($BH32="CC",($BC32-BK32)<0),$BD32*1, IF(AND($BH32="VC",($BC32-BK32)<0),$BD32*1, IF(AND($BH32="CP",($BC32-BK32)>0),$BD32*-1, IF(AND($BH32="VP",($BC32-BK32)>0),$BD32*-1,0)))) -> 0 | CG32: =IF(AND($BH32="CC",($BC32-BL32)<0),$BD32*1, IF(AND($BH32="VC",($BC32-BL32)<0),$BD32*1, IF(AND($BH32="CP",($BC32-BL32)>0),$BD32*-1, IF(AND($BH32="VP",($BC32-BL32)>0),$BD32*-1,0)))) -> 0 | CH32: =IF(AND($BH32="CC",($BC32-BM32)<0),$BD32*1, IF(AND($BH32="VC",($BC32-BM32)<0),$BD32*1, IF(AND($BH32="CP",($BC32-BM32)>0),$BD32*-1, IF(AND($BH32="VP",($BC32-BM32)>0),$BD32*-1,0)))) -> 0 | CI32: =IF(AND($BH32="CC",($BC32-BN32)<0),$BD32*1, IF(AND($BH32="VC",($BC32-BN32)<0),$BD32*1, IF(AND($BH32="CP",($BC32-BN32)>0),$BD32*-1, IF(AND($BH32="VP",($BC32-BN32)>0),$BD32*-1,0)))) -> 0 | CJ32: =IF(AND($BH32="CC",($BC32-BO32)<0),$BD32*1, IF(AND($BH32="VC",($BC32-BO32)<0),$BD32*1, IF(AND($BH32="CP",($BC32-BO32)>0),$BD32*-1, IF(AND($BH32="VP",($BC32-BO32)>0),$BD32*-1,0)))) -> 0 | CK32: =Tabla3[[#This Row],[Tns]] -> -6123.6 | CL32: =IF(ISERROR(VLOOKUP(VALUE(E32),'Clientes CBOT'!A:A,1,0)),"VER","ok") -> ok
A33: P | B33: R | C33: 766 | D33: 0 | E33: 20176 | F33: C | H33: F1 | I33: .AS-0000026E | J33: 7453 | K33: 2 | L33: 120000 | M33: MAY 26 SOYBEANS | N33: 10.86 1/2 | O33: 20251024 | Q33: 202605 | S33: F | U33: 0 | V33: 0 | X33: FYO ACOPIO SA | Z33: 20251024 | AA33: 1 | AB33: 1A | AC33: S- | AF33: 10.86500000 | AL33: 0 | AM33: 12.0000 | AN33: USD | AO33: -1815000 | AP33: 1116750000 | AQ33: 0 | AR33: 50000 | AS33: 5J24 JnG0 | AT33: 116077453 | AU33: 0,0000 | AV33: S | AW33: CBT | AX33: Comdty | AY33: Soja | AZ33: =IF(VLOOKUP(AY33,Conversor!B:C,2,0)="HS",0.01,VLOOKUP(AY33,Conversor!B:C,2,0)) -> 0.36743 | BA33: =IF(BG33="v",-AM33/10000,AL33/10000) -> -12 | BB33: =IF(AQ33=0,AP33/1000000*AZ33,AQ33/1000000*AZ33) -> 410.32745 | BC33: =U33/1000000*AZ33 -> 0 | BD33: =IF(OR(E33="FUTUR",E33="f20176"),0,VLOOKUP(AY33,Conversor!G:I,3,0)*BA33) -> -1632.96 | BE33: =IF(LEFT(M33,4)="call","Call",IF(LEFT(M33,3)="put","Put","Futuro")) -> Futuro | BF33: =IF(BE33="futuro","no","si") -> no | BG33: =IF(AL33=0,"V","C") -> V | BH33: =IF(BE33="futuro","",CONCATENATE(BG33,LEFT(BE33,1))) | BI33: =$BB33*(1+BI$2) -> 287.22922 | BJ33: =$BB33*(1+BJ$2) -> 328.26196 | BK33: =$BB33*(1+BK$2) -> 369.29471 | BL33: =$BB33*(1+BL$2) -> 410.32745 | BM33: =$BB33*(1+BM$2) -> 451.3602 | BN33: =$BB33*(1+BN$2) -> 492.39294 | BO33: =$BB33*(1+BO$2) -> 533.42569 | BP33: =IF($BE33="futuro",-($BL33-BI33)*$BD33,0) -> 201014.5 | BQ33: =IF($BE33="futuro",-($BL33-BJ33)*$BD33,0) -> 134009.66 | BR33: =IF($BE33="futuro",-($BL33-BK33)*$BD33,0) -> 67004.832 | BS33: =IF($BE33="futuro",-($BL33-BL33)*$BD33,0) -> 0 | BT33: =IF($BE33="futuro",-($BL33-BM33)*$BD33,0) -> -67004.832 | BU33: =IF($BE33="futuro",-($BL33-BN33)*$BD33,0) -> -134009.66 | BV33: =IF($BE33="futuro",-($BL33-BO33)*$BD33,0) -> -201014.5 | BW33: =IF(AND($BH33="CC",($BC33-BI33)<0),(BI33-$BC33)*$BD33, IF(AND($BH33="VC",($BC33-BI33)<0),($BC33-BI33)*-$BD33, IF(AND($BH33="CP",($BC33-BI33)>0),(BI33-$BC33)*$BD33*-1, IF(AND($BH33="VP",($BC33-BI33)>0),(BI33-$BC33)*$BD33*-1,0)))) -> 0 | BX33: =IF(AND($BH33="CC",($BC33-BJ33)<0),(BJ33-$BC33)*$BD33, IF(AND($BH33="VC",($BC33-BJ33)<0),($BC33-BJ33)*-$BD33, IF(AND($BH33="CP",($BC33-BJ33)>0),(BJ33-$BC33)*$BD33*-1, IF(AND($BH33="VP",($BC33-BJ33)>0),(BJ33-$BC33)*$BD33*-1,0)))) -> 0 | BY33: =IF(AND($BH33="CC",($BC33-BK33)<0),(BK33-$BC33)*$BD33, IF(AND($BH33="VC",($BC33-BK33)<0),($BC33-BK33)*-$BD33, IF(AND($BH33="CP",($BC33-BK33)>0),(BK33-$BC33)*$BD33*-1, IF(AND($BH33="VP",($BC33-BK33)>0),(BK33-$BC33)*$BD33*-1,0)))) -> 0 | BZ33: =IF(AND($BH33="CC",($BC33-BL33)<0),(BL33-$BC33)*$BD33, IF(AND($BH33="VC",($BC33-BL33)<0),($BC33-BL33)*-$BD33, IF(AND($BH33="CP",($BC33-BL33)>0),(BL33-$BC33)*$BD33*-1, IF(AND($BH33="VP",($BC33-BL33)>0),(BL33-$BC33)*$BD33*-1,0)))) -> 0 | CA33: =IF(AND($BH33="CC",($BC33-BM33)<0),(BM33-$BC33)*$BD33, IF(AND($BH33="VC",($BC33-BM33)<0),($BC33-BM33)*-$BD33, IF(AND($BH33="CP",($BC33-BM33)>0),(BM33-$BC33)*$BD33*-1, IF(AND($BH33="VP",($BC33-BM33)>0),(BM33-$BC33)*$BD33*-1,0)))) -> 0 | CB33: =IF(AND($BH33="CC",($BC33-BN33)<0),(BN33-$BC33)*$BD33, IF(AND($BH33="VC",($BC33-BN33)<0),($BC33-BN33)*-$BD33, IF(AND($BH33="CP",($BC33-BN33)>0),(BN33-$BC33)*$BD33*-1, IF(AND($BH33="VP",($BC33-BN33)>0),(BN33-$BC33)*$BD33*-1,0)))) -> 0 | CC33: =IF(AND($BH33="CC",($BC33-BO33)<0),(BO33-$BC33)*$BD33, IF(AND($BH33="VC",($BC33-BO33)<0),($BC33-BO33)*-$BD33, IF(AND($BH33="CP",($BC33-BO33)>0),(BO33-$BC33)*$BD33*-1, IF(AND($BH33="VP",($BC33-BO33)>0),(BO33-$BC33)*$BD33*-1,0)))) -> 0 | CD33: =IF(AND($BH33="CC",($BC33-BI33)<0),$BD33*1, IF(AND($BH33="VC",($BC33-BI33)<0),$BD33*1, IF(AND($BH33="CP",($BC33-BI33)>0),$BD33*-1, IF(AND($BH33="VP",($BC33-BI33)>0),$BD33*-1,0)))) -> 0 | CE33: =IF(AND($BH33="CC",($BC33-BJ33)<0),$BD33*1, IF(AND($BH33="VC",($BC33-BJ33)<0),$BD33*1, IF(AND($BH33="CP",($BC33-BJ33)>0),$BD33*-1, IF(AND($BH33="VP",($BC33-BJ33)>0),$BD33*-1,0)))) -> 0 | CF33: =IF(AND($BH33="CC",($BC33-BK33)<0),$BD33*1, IF(AND($BH33="VC",($BC33-BK33)<0),$BD33*1, IF(AND($BH33="CP",($BC33-BK33)>0),$BD33*-1, IF(AND($BH33="VP",($BC33-BK33)>0),$BD33*-1,0)))) -> 0 | CG33: =IF(AND($BH33="CC",($BC33-BL33)<0),$BD33*1, IF(AND($BH33="VC",($BC33-BL33)<0),$BD33*1, IF(AND($BH33="CP",($BC33-BL33)>0),$BD33*-1, IF(AND($BH33="VP",($BC33-BL33)>0),$BD33*-1,0)))) -> 0 | CH33: =IF(AND($BH33="CC",($BC33-BM33)<0),$BD33*1, IF(AND($BH33="VC",($BC33-BM33)<0),$BD33*1, IF(AND($BH33="CP",($BC33-BM33)>0),$BD33*-1, IF(AND($BH33="VP",($BC33-BM33)>0),$BD33*-1,0)))) -> 0 | CI33: =IF(AND($BH33="CC",($BC33-BN33)<0),$BD33*1, IF(AND($BH33="VC",($BC33-BN33)<0),$BD33*1, IF(AND($BH33="CP",($BC33-BN33)>0),$BD33*-1, IF(AND($BH33="VP",($BC33-BN33)>0),$BD33*-1,0)))) -> 0 | CJ33: =IF(AND($BH33="CC",($BC33-BO33)<0),$BD33*1, IF(AND($BH33="VC",($BC33-BO33)<0),$BD33*1, IF(AND($BH33="CP",($BC33-BO33)>0),$BD33*-1, IF(AND($BH33="VP",($BC33-BO33)>0),$BD33*-1,0)))) -> 0 | CK33: =Tabla3[[#This Row],[Tns]] -> -1632.96 | CL33: =IF(ISERROR(VLOOKUP(VALUE(E33),'Clientes CBOT'!A:A,1,0)),"VER","ok") -> ok
A34: P | B34: R | C34: 766 | D34: 0 | E34: 20176 | F34: C | H34: F1 | I34: .AS-0000026E | J34: 5595 | K34: 2 | L34: 40000 | M34: MAY 26 SOYBEANS | N34: 10.87 | O34: 20251024 | Q34: 202605 | S34: F | U34: 0 | V34: 0 | X34: FYO ACOPIO SA | Z34: 20251024 | AA34: 1 | AB34: 1A | AC34: S- | AF34: 10.87000000 | AL34: 0 | AM34: 4.0000 | AN34: USD | AO34: -595000 | AP34: 1116750000 | AQ34: 0 | AR34: 50000 | AS34: 5J24 Es50 | AT34: 116075595 | AU34: 0,0000 | AV34: S | AW34: CBT | AX34: Comdty | AY34: Soja | AZ34: =IF(VLOOKUP(AY34,Conversor!B:C,2,0)="HS",0.01,VLOOKUP(AY34,Conversor!B:C,2,0)) -> 0.36743 | BA34: =IF(BG34="v",-AM34/10000,AL34/10000) -> -4 | BB34: =IF(AQ34=0,AP34/1000000*AZ34,AQ34/1000000*AZ34) -> 410.32745 | BC34: =U34/1000000*AZ34 -> 0 | BD34: =IF(OR(E34="FUTUR",E34="f20176"),0,VLOOKUP(AY34,Conversor!G:I,3,0)*BA34) -> -544.32 | BE34: =IF(LEFT(M34,4)="call","Call",IF(LEFT(M34,3)="put","Put","Futuro")) -> Futuro | BF34: =IF(BE34="futuro","no","si") -> no | BG34: =IF(AL34=0,"V","C") -> V | BH34: =IF(BE34="futuro","",CONCATENATE(BG34,LEFT(BE34,1))) | BI34: =$BB34*(1+BI$2) -> 287.22922 | BJ34: =$BB34*(1+BJ$2) -> 328.26196 | BK34: =$BB34*(1+BK$2) -> 369.29471 | BL34: =$BB34*(1+BL$2) -> 410.32745 | BM34: =$BB34*(1+BM$2) -> 451.3602 | BN34: =$BB34*(1+BN$2) -> 492.39294 | BO34: =$BB34*(1+BO$2) -> 533.42569 | BP34: =IF($BE34="futuro",-($BL34-BI34)*$BD34,0) -> 67004.832 | BQ34: =IF($BE34="futuro",-($BL34-BJ34)*$BD34,0) -> 44669.888 | BR34: =IF($BE34="futuro",-($BL34-BK34)*$BD34,0) -> 22334.944 | BS34: =IF($BE34="futuro",-($BL34-BL34)*$BD34,0) -> 0 | BT34: =IF($BE34="futuro",-($BL34-BM34)*$BD34,0) -> -22334.944 | BU34: =IF($BE34="futuro",-($BL34-BN34)*$BD34,0) -> -44669.888 | BV34: =IF($BE34="futuro",-($BL34-BO34)*$BD34,0) -> -67004.832 | BW34: =IF(AND($BH34="CC",($BC34-BI34)<0),(BI34-$BC34)*$BD34, IF(AND($BH34="VC",($BC34-BI34)<0),($BC34-BI34)*-$BD34, IF(AND($BH34="CP",($BC34-BI34)>0),(BI34-$BC34)*$BD34*-1, IF(AND($BH34="VP",($BC34-BI34)>0),(BI34-$BC34)*$BD34*-1,0)))) -> 0 | BX34: =IF(AND($BH34="CC",($BC34-BJ34)<0),(BJ34-$BC34)*$BD34, IF(AND($BH34="VC",($BC34-BJ34)<0),($BC34-BJ34)*-$BD34, IF(AND($BH34="CP",($BC34-BJ34)>0),(BJ34-$BC34)*$BD34*-1, IF(AND($BH34="VP",($BC34-BJ34)>0),(BJ34-$BC34)*$BD34*-1,0)))) -> 0 | BY34: =IF(AND($BH34="CC",($BC34-BK34)<0),(BK34-$BC34)*$BD34, IF(AND($BH34="VC",($BC34-BK34)<0),($BC34-BK34)*-$BD34, IF(AND($BH34="CP",($BC34-BK34)>0),(BK34-$BC34)*$BD34*-1, IF(AND($BH34="VP",($BC34-BK34)>0),(BK34-$BC34)*$BD34*-1,0)))) -> 0 | BZ34: =IF(AND($BH34="CC",($BC34-BL34)<0),(BL34-$BC34)*$BD34, IF(AND($BH34="VC",($BC34-BL34)<0),($BC34-BL34)*-$BD34, IF(AND($BH34="CP",($BC34-BL34)>0),(BL34-$BC34)*$BD34*-1, IF(AND($BH34="VP",($BC34-BL34)>0),(BL34-$BC34)*$BD34*-1,0)))) -> 0 | CA34: =IF(AND($BH34="CC",($BC34-BM34)<0),(BM34-$BC34)*$BD34, IF(AND($BH34="VC",($BC34-BM34)<0),($BC34-BM34)*-$BD34, IF(AND($BH34="CP",($BC34-BM34)>0),(BM34-$BC34)*$BD34*-1, IF(AND($BH34="VP",($BC34-BM34)>0),(BM34-$BC34)*$BD34*-1,0)))) -> 0 | CB34: =IF(AND($BH34="CC",($BC34-BN34)<0),(BN34-$BC34)*$BD34, IF(AND($BH34="VC",($BC34-BN34)<0),($BC34-BN34)*-$BD34, IF(AND($BH34="CP",($BC34-BN34)>0),(BN34-$BC34)*$BD34*-1, IF(AND($BH34="VP",($BC34-BN34)>0),(BN34-$BC34)*$BD34*-1,0)))) -> 0 | CC34: =IF(AND($BH34="CC",($BC34-BO34)<0),(BO34-$BC34)*$BD34, IF(AND($BH34="VC",($BC34-BO34)<0),($BC34-BO34)*-$BD34, IF(AND($BH34="CP",($BC34-BO34)>0),(BO34-$BC34)*$BD34*-1, IF(AND($BH34="VP",($BC34-BO34)>0),(BO34-$BC34)*$BD34*-1,0)))) -> 0 | CD34: =IF(AND($BH34="CC",($BC34-BI34)<0),$BD34*1, IF(AND($BH34="VC",($BC34-BI34)<0),$BD34*1, IF(AND($BH34="CP",($BC34-BI34)>0),$BD34*-1, IF(AND($BH34="VP",($BC34-BI34)>0),$BD34*-1,0)))) -> 0 | CE34: =IF(AND($BH34="CC",($BC34-BJ34)<0),$BD34*1, IF(AND($BH34="VC",($BC34-BJ34)<0),$BD34*1, IF(AND($BH34="CP",($BC34-BJ34)>0),$BD34*-1, IF(AND($BH34="VP",($BC34-BJ34)>0),$BD34*-1,0)))) -> 0 | CF34: =IF(AND($BH34="CC",($BC34-BK34)<0),$BD34*1, IF(AND($BH34="VC",($BC34-BK34)<0),$BD34*1, IF(AND($BH34="CP",($BC34-BK34)>0),$BD34*-1, IF(AND($BH34="VP",($BC34-BK34)>0),$BD34*-1,0)))) -> 0 | CG34: =IF(AND($BH34="CC",($BC34-BL34)<0),$BD34*1, IF(AND($BH34="VC",($BC34-BL34)<0),$BD34*1, IF(AND($BH34="CP",($BC34-BL34)>0),$BD34*-1, IF(AND($BH34="VP",($BC34-BL34)>0),$BD34*-1,0)))) -> 0 | CH34: =IF(AND($BH34="CC",($BC34-BM34)<0),$BD34*1, IF(AND($BH34="VC",($BC34-BM34)<0),$BD34*1, IF(AND($BH34="CP",($BC34-BM34)>0),$BD34*-1, IF(AND($BH34="VP",($BC34-BM34)>0),$BD34*-1,0)))) -> 0 | CI34: =IF(AND($BH34="CC",($BC34-BN34)<0),$BD34*1, IF(AND($BH34="VC",($BC34-BN34)<0),$BD34*1, IF(AND($BH34="CP",($BC34-BN34)>0),$BD34*-1, IF(AND($BH34="VP",($BC34-BN34)>0),$BD34*-1,0)))) -> 0 | CJ34: =IF(AND($BH34="CC",($BC34-BO34)<0),$BD34*1, IF(AND($BH34="VC",($BC34-BO34)<0),$BD34*1, IF(AND($BH34="CP",($BC34-BO34)>0),$BD34*-1, IF(AND($BH34="VP",($BC34-BO34)>0),$BD34*-1,0)))) -> 0 | CK34: =Tabla3[[#This Row],[Tns]] -> -544.32 | CL34: =IF(ISERROR(VLOOKUP(VALUE(E34),'Clientes CBOT'!A:A,1,0)),"VER","ok") -> ok
A35: P | B35: R | C35: 766 | D35: 0 | E35: 20176 | F35: C | H35: F1 | I35: .AS-0000026E | J35: 6142 | K35: 2 | L35: 180000 | M35: MAY 26 SOYBEANS | N35: 11.09 | O35: 20251027 | Q35: 202605 | S35: F | U35: 0 | V35: 0 | X35: FYO ACOPIO SA | Z35: 20251027 | AA35: 1 | AB35: 1A | AC35: S- | AF35: 11.09000000 | AL35: 0 | AM35: 18.0000 | AN35: USD | AO35: -697500 | AP35: 1116750000 | AQ35: 0 | AR35: 50000 | AS35: 5J27 Q8g0 | AT35: 116096142 | AU35: 0,0000 | AV35: S | AW35: CBT | AX35: Comdty | AY35: Soja | AZ35: =IF(VLOOKUP(AY35,Conversor!B:C,2,0)="HS",0.01,VLOOKUP(AY35,Conversor!B:C,2,0)) -> 0.36743 | BA35: =IF(BG35="v",-AM35/10000,AL35/10000) -> -18 | BB35: =IF(AQ35=0,AP35/1000000*AZ35,AQ35/1000000*AZ35) -> 410.32745 | BC35: =U35/1000000*AZ35 -> 0 | BD35: =IF(OR(E35="FUTUR",E35="f20176"),0,VLOOKUP(AY35,Conversor!G:I,3,0)*BA35) -> -2449.44 | BE35: =IF(LEFT(M35,4)="call","Call",IF(LEFT(M35,3)="put","Put","Futuro")) -> Futuro | BF35: =IF(BE35="futuro","no","si") -> no | BG35: =IF(AL35=0,"V","C") -> V | BH35: =IF(BE35="futuro","",CONCATENATE(BG35,LEFT(BE35,1))) | BI35: =$BB35*(1+BI$2) -> 287.22922 | BJ35: =$BB35*(1+BJ$2) -> 328.26196 | BK35: =$BB35*(1+BK$2) -> 369.29471 | BL35: =$BB35*(1+BL$2) -> 410.32745 | BM35: =$BB35*(1+BM$2) -> 451.3602 | BN35: =$BB35*(1+BN$2) -> 492.39294 | BO35: =$BB35*(1+BO$2) -> 533.42569 | BP35: =IF($BE35="futuro",-($BL35-BI35)*$BD35,0) -> 301521.74 | BQ35: =IF($BE35="futuro",-($BL35-BJ35)*$BD35,0) -> 201014.5 | BR35: =IF($BE35="futuro",-($BL35-BK35)*$BD35,0) -> 100507.25 | BS35: =IF($BE35="futuro",-($BL35-BL35)*$BD35,0) -> 0 | BT35: =IF($BE35="futuro",-($BL35-BM35)*$BD35,0) -> -100507.25 | BU35: =IF($BE35="futuro",-($BL35-BN35)*$BD35,0) -> -201014.5 | BV35: =IF($BE35="futuro",-($BL35-BO35)*$BD35,0) -> -301521.74 | BW35: =IF(AND($BH35="CC",($BC35-BI35)<0),(BI35-$BC35)*$BD35, IF(AND($BH35="VC",($BC35-BI35)<0),($BC35-BI35)*-$BD35, IF(AND($BH35="CP",($BC35-BI35)>0),(BI35-$BC35)*$BD35*-1, IF(AND($BH35="VP",($BC35-BI35)>0),(BI35-$BC35)*$BD35*-1,0)))) -> 0 | BX35: =IF(AND($BH35="CC",($BC35-BJ35)<0),(BJ35-$BC35)*$BD35, IF(AND($BH35="VC",($BC35-BJ35)<0),($BC35-BJ35)*-$BD35, IF(AND($BH35="CP",($BC35-BJ35)>0),(BJ35-$BC35)*$BD35*-1, IF(AND($BH35="VP",($BC35-BJ35)>0),(BJ35-$BC35)*$BD35*-1,0)))) -> 0 | BY35: =IF(AND($BH35="CC",($BC35-BK35)<0),(BK35-$BC35)*$BD35, IF(AND($BH35="VC",($BC35-BK35)<0),($BC35-BK35)*-$BD35, IF(AND($BH35="CP",($BC35-BK35)>0),(BK35-$BC35)*$BD35*-1, IF(AND($BH35="VP",($BC35-BK35)>0),(BK35-$BC35)*$BD35*-1,0)))) -> 0 | BZ35: =IF(AND($BH35="CC",($BC35-BL35)<0),(BL35-$BC35)*$BD35, IF(AND($BH35="VC",($BC35-BL35)<0),($BC35-BL35)*-$BD35, IF(AND($BH35="CP",($BC35-BL35)>0),(BL35-$BC35)*$BD35*-1, IF(AND($BH35="VP",($BC35-BL35)>0),(BL35-$BC35)*$BD35*-1,0)))) -> 0 | CA35: =IF(AND($BH35="CC",($BC35-BM35)<0),(BM35-$BC35)*$BD35, IF(AND($BH35="VC",($BC35-BM35)<0),($BC35-BM35)*-$BD35, IF(AND($BH35="CP",($BC35-BM35)>0),(BM35-$BC35)*$BD35*-1, IF(AND($BH35="VP",($BC35-BM35)>0),(BM35-$BC35)*$BD35*-1,0)))) -> 0 | CB35: =IF(AND($BH35="CC",($BC35-BN35)<0),(BN35-$BC35)*$BD35, IF(AND($BH35="VC",($BC35-BN35)<0),($BC35-BN35)*-$BD35, IF(AND($BH35="CP",($BC35-BN35)>0),(BN35-$BC35)*$BD35*-1, IF(AND($BH35="VP",($BC35-BN35)>0),(BN35-$BC35)*$BD35*-1,0)))) -> 0 | CC35: =IF(AND($BH35="CC",($BC35-BO35)<0),(BO35-$BC35)*$BD35, IF(AND($BH35="VC",($BC35-BO35)<0),($BC35-BO35)*-$BD35, IF(AND($BH35="CP",($BC35-BO35)>0),(BO35-$BC35)*$BD35*-1, IF(AND($BH35="VP",($BC35-BO35)>0),(BO35-$BC35)*$BD35*-1,0)))) -> 0 | CD35: =IF(AND($BH35="CC",($BC35-BI35)<0),$BD35*1, IF(AND($BH35="VC",($BC35-BI35)<0),$BD35*1, IF(AND($BH35="CP",($BC35-BI35)>0),$BD35*-1, IF(AND($BH35="VP",($BC35-BI35)>0),$BD35*-1,0)))) -> 0 | CE35: =IF(AND($BH35="CC",($BC35-BJ35)<0),$BD35*1, IF(AND($BH35="VC",($BC35-BJ35)<0),$BD35*1, IF(AND($BH35="CP",($BC35-BJ35)>0),$BD35*-1, IF(AND($BH35="VP",($BC35-BJ35)>0),$BD35*-1,0)))) -> 0 | CF35: =IF(AND($BH35="CC",($BC35-BK35)<0),$BD35*1, IF(AND($BH35="VC",($BC35-BK35)<0),$BD35*1, IF(AND($BH35="CP",($BC35-BK35)>0),$BD35*-1, IF(AND($BH35="VP",($BC35-BK35)>0),$BD35*-1,0)))) -> 0 | CG35: =IF(AND($BH35="CC",($BC35-BL35)<0),$BD35*1, IF(AND($BH35="VC",($BC35-BL35)<0),$BD35*1, IF(AND($BH35="CP",($BC35-BL35)>0),$BD35*-1, IF(AND($BH35="VP",($BC35-BL35)>0),$BD35*-1,0)))) -> 0 | CH35: =IF(AND($BH35="CC",($BC35-BM35)<0),$BD35*1, IF(AND($BH35="VC",($BC35-BM35)<0),$BD35*1, IF(AND($BH35="CP",($BC35-BM35)>0),$BD35*-1, IF(AND($BH35="VP",($BC35-BM35)>0),$BD35*-1,0)))) -> 0 | CI35: =IF(AND($BH35="CC",($BC35-BN35)<0),$BD35*1, IF(AND($BH35="VC",($BC35-BN35)<0),$BD35*1, IF(AND($BH35="CP",($BC35-BN35)>0),$BD35*-1, IF(AND($BH35="VP",($BC35-BN35)>0),$BD35*-1,0)))) -> 0 | CJ35: =IF(AND($BH35="CC",($BC35-BO35)<0),$BD35*1, IF(AND($BH35="VC",($BC35-BO35)<0),$BD35*1, IF(AND($BH35="CP",($BC35-BO35)>0),$BD35*-1, IF(AND($BH35="VP",($BC35-BO35)>0),$BD35*-1,0)))) -> 0 | CK35: =Tabla3[[#This Row],[Tns]] -> -2449.44 | CL35: =IF(ISERROR(VLOOKUP(VALUE(E35),'Clientes CBOT'!A:A,1,0)),"VER","ok") -> ok
A36: P | B36: R | C36: 766 | D36: 0 | E36: 20176 | F36: C | H36: F1 | I36: .AS-0000026E | J36: 3128 | K36: 2 | L36: 20000 | M36: MAY 26 SOYBEANS | N36: 11.14 | O36: 20251028 | Q36: 202605 | S36: F | U36: 0 | V36: 0 | X36: FYO ACOPIO SA | Z36: 20251028 | AA36: 1 | AB36: 1A | AC36: S- | AF36: 11.14000000 | AL36: 0 | AM36: 2.0000 | AN36: USD | AO36: -27500 | AP36: 1116750000 | AQ36: 0 | AR36: 50000 | AS36: 5J28 RNo0 | AT36: 116113128 | AU36: 0,0000 | AV36: S | AW36: CBT | AX36: Comdty | AY36: Soja | AZ36: =IF(VLOOKUP(AY36,Conversor!B:C,2,0)="HS",0.01,VLOOKUP(AY36,Conversor!B:C,2,0)) -> 0.36743 | BA36: =IF(BG36="v",-AM36/10000,AL36/10000) -> -2 | BB36: =IF(AQ36=0,AP36/1000000*AZ36,AQ36/1000000*AZ36) -> 410.32745 | BC36: =U36/1000000*AZ36 -> 0 | BD36: =IF(OR(E36="FUTUR",E36="f20176"),0,VLOOKUP(AY36,Conversor!G:I,3,0)*BA36) -> -272.16 | BE36: =IF(LEFT(M36,4)="call","Call",IF(LEFT(M36,3)="put","Put","Futuro")) -> Futuro | BF36: =IF(BE36="futuro","no","si") -> no | BG36: =IF(AL36=0,"V","C") -> V | BH36: =IF(BE36="futuro","",CONCATENATE(BG36,LEFT(BE36,1))) | BI36: =$BB36*(1+BI$2) -> 287.22922 | BJ36: =$BB36*(1+BJ$2) -> 328.26196 | BK36: =$BB36*(1+BK$2) -> 369.29471 | BL36: =$BB36*(1+BL$2) -> 410.32745 | BM36: =$BB36*(1+BM$2) -> 451.3602 | BN36: =$BB36*(1+BN$2) -> 492.39294 | BO36: =$BB36*(1+BO$2) -> 533.42569 | BP36: =IF($BE36="futuro",-($BL36-BI36)*$BD36,0) -> 33502.416 | BQ36: =IF($BE36="futuro",-($BL36-BJ36)*$BD36,0) -> 22334.944 | BR36: =IF($BE36="futuro",-($BL36-BK36)*$BD36,0) -> 11167.472 | BS36: =IF($BE36="futuro",-($BL36-BL36)*$BD36,0) -> 0 | BT36: =IF($BE36="futuro",-($BL36-BM36)*$BD36,0) -> -11167.472 | BU36: =IF($BE36="futuro",-($BL36-BN36)*$BD36,0) -> -22334.944 | BV36: =IF($BE36="futuro",-($BL36-BO36)*$BD36,0) -> -33502.416 | BW36: =IF(AND($BH36="CC",($BC36-BI36)<0),(BI36-$BC36)*$BD36, IF(AND($BH36="VC",($BC36-BI36)<0),($BC36-BI36)*-$BD36, IF(AND($BH36="CP",($BC36-BI36)>0),(BI36-$BC36)*$BD36*-1, IF(AND($BH36="VP",($BC36-BI36)>0),(BI36-$BC36)*$BD36*-1,0)))) -> 0 | BX36: =IF(AND($BH36="CC",($BC36-BJ36)<0),(BJ36-$BC36)*$BD36, IF(AND($BH36="VC",($BC36-BJ36)<0),($BC36-BJ36)*-$BD36, IF(AND($BH36="CP",($BC36-BJ36)>0),(BJ36-$BC36)*$BD36*-1, IF(AND($BH36="VP",($BC36-BJ36)>0),(BJ36-$BC36)*$BD36*-1,0)))) -> 0 | BY36: =IF(AND($BH36="CC",($BC36-BK36)<0),(BK36-$BC36)*$BD36, IF(AND($BH36="VC",($BC36-BK36)<0),($BC36-BK36)*-$BD36, IF(AND($BH36="CP",($BC36-BK36)>0),(BK36-$BC36)*$BD36*-1, IF(AND($BH36="VP",($BC36-BK36)>0),(BK36-$BC36)*$BD36*-1,0)))) -> 0 | BZ36: =IF(AND($BH36="CC",($BC36-BL36)<0),(BL36-$BC36)*$BD36, IF(AND($BH36="VC",($BC36-BL36)<0),($BC36-BL36)*-$BD36, IF(AND($BH36="CP",($BC36-BL36)>0),(BL36-$BC36)*$BD36*-1, IF(AND($BH36="VP",($BC36-BL36)>0),(BL36-$BC36)*$BD36*-1,0)))) -> 0 | CA36: =IF(AND($BH36="CC",($BC36-BM36)<0),(BM36-$BC36)*$BD36, IF(AND($BH36="VC",($BC36-BM36)<0),($BC36-BM36)*-$BD36, IF(AND($BH36="CP",($BC36-BM36)>0),(BM36-$BC36)*$BD36*-1, IF(AND($BH36="VP",($BC36-BM36)>0),(BM36-$BC36)*$BD36*-1,0)))) -> 0 | CB36: =IF(AND($BH36="CC",($BC36-BN36)<0),(BN36-$BC36)*$BD36, IF(AND($BH36="VC",($BC36-BN36)<0),($BC36-BN36)*-$BD36, IF(AND($BH36="CP",($BC36-BN36)>0),(BN36-$BC36)*$BD36*-1, IF(AND($BH36="VP",($BC36-BN36)>0),(BN36-$BC36)*$BD36*-1,0)))) -> 0 | CC36: =IF(AND($BH36="CC",($BC36-BO36)<0),(BO36-$BC36)*$BD36, IF(AND($BH36="VC",($BC36-BO36)<0),($BC36-BO36)*-$BD36, IF(AND($BH36="CP",($BC36-BO36)>0),(BO36-$BC36)*$BD36*-1, IF(AND($BH36="VP",($BC36-BO36)>0),(BO36-$BC36)*$BD36*-1,0)))) -> 0 | CD36: =IF(AND($BH36="CC",($BC36-BI36)<0),$BD36*1, IF(AND($BH36="VC",($BC36-BI36)<0),$BD36*1, IF(AND($BH36="CP",($BC36-BI36)>0),$BD36*-1, IF(AND($BH36="VP",($BC36-BI36)>0),$BD36*-1,0)))) -> 0 | CE36: =IF(AND($BH36="CC",($BC36-BJ36)<0),$BD36*1, IF(AND($BH36="VC",($BC36-BJ36)<0),$BD36*1, IF(AND($BH36="CP",($BC36-BJ36)>0),$BD36*-1, IF(AND($BH36="VP",($BC36-BJ36)>0),$BD36*-1,0)))) -> 0 | CF36: =IF(AND($BH36="CC",($BC36-BK36)<0),$BD36*1, IF(AND($BH36="VC",($BC36-BK36)<0),$BD36*1, IF(AND($BH36="CP",($BC36-BK36)>0),$BD36*-1, IF(AND($BH36="VP",($BC36-BK36)>0),$BD36*-1,0)))) -> 0 | CG36: =IF(AND($BH36="CC",($BC36-BL36)<0),$BD36*1, IF(AND($BH36="VC",($BC36-BL36)<0),$BD36*1, IF(AND($BH36="CP",($BC36-BL36)>0),$BD36*-1, IF(AND($BH36="VP",($BC36-BL36)>0),$BD36*-1,0)))) -> 0 | CH36: =IF(AND($BH36="CC",($BC36-BM36)<0),$BD36*1, IF(AND($BH36="VC",($BC36-BM36)<0),$BD36*1, IF(AND($BH36="CP",($BC36-BM36)>0),$BD36*-1, IF(AND($BH36="VP",($BC36-BM36)>0),$BD36*-1,0)))) -> 0 | CI36: =IF(AND($BH36="CC",($BC36-BN36)<0),$BD36*1, IF(AND($BH36="VC",($BC36-BN36)<0),$BD36*1, IF(AND($BH36="CP",($BC36-BN36)>0),$BD36*-1, IF(AND($BH36="VP",($BC36-BN36)>0),$BD36*-1,0)))) -> 0 | CJ36: =IF(AND($BH36="CC",($BC36-BO36)<0),$BD36*1, IF(AND($BH36="VC",($BC36-BO36)<0),$BD36*1, IF(AND($BH36="CP",($BC36-BO36)>0),$BD36*-1, IF(AND($BH36="VP",($BC36-BO36)>0),$BD36*-1,0)))) -> 0 | CK36: =Tabla3[[#This Row],[Tns]] -> -272.16 | CL36: =IF(ISERROR(VLOOKUP(VALUE(E36),'Clientes CBOT'!A:A,1,0)),"VER","ok") -> ok
... A38: P | B38: R | C38: 766 | D38: 0 | E38: 20176 | F38: C | H38: F1 | I38: .AS-0000026E | J38: 2378 | K38: 2 | L38: 60000 | M38: MAY 26 SOYBEANS | N38: 11.18 1/4 | O38: 20251028 | Q38: 202605 | S38: F | U38: 0 | V38: 0 | X38: FYO ACOPIO SA | Z38: 20251028 | AA38: 1 | AB38: 1A | AC38: S- | AF38: 11.18250000 | AL38: 0 | AM38: 6.0000 | AN38: USD | AO38: 45000 | AP38: 1116750000 | AQ38: 0 | AR38: 50000 | AS38: 5J28 P7C0 | AT38: 116112378 | AU38: 0,0000 | AV38: S | AW38: CBT | AX38: Comdty | AY38: Soja | AZ38: =IF(VLOOKUP(AY38,Conversor!B:C,2,0)="HS",0.01,VLOOKUP(AY38,Conversor!B:C,2,0)) -> 0.36743 | BA38: =IF(BG38="v",-AM38/10000,AL38/10000) -> -6 | BB38: =IF(AQ38=0,AP38/1000000*AZ38,AQ38/1000000*AZ38) -> 410.32745 | BC38: =U38/1000000*AZ38 -> 0 | BD38: =IF(OR(E38="FUTUR",E38="f20176"),0,VLOOKUP(AY38,Conversor!G:I,3,0)*BA38) -> -816.48 | BE38: =IF(LEFT(M38,4)="call","Call",IF(LEFT(M38,3)="put","Put","Futuro")) -> Futuro | BF38: =IF(BE38="futuro","no","si") -> no | BG38: =IF(AL38=0,"V","C") -> V | BH38: =IF(BE38="futuro","",CONCATENATE(BG38,LEFT(BE38,1))) | BI38: =$BB38*(1+BI$2) -> 287.22922 | BJ38: =$BB38*(1+BJ$2) -> 328.26196 | BK38: =$BB38*(1+BK$2) -> 369.29471 | BL38: =$BB38*(1+BL$2) -> 410.32745 | BM38: =$BB38*(1+BM$2) -> 451.3602 | BN38: =$BB38*(1+BN$2) -> 492.39294 | BO38: =$BB38*(1+BO$2) -> 533.42569 | BP38: =IF($BE38="futuro",-($BL38-BI38)*$BD38,0) -> 100507.25 | BQ38: =IF($BE38="futuro",-($BL38-BJ38)*$BD38,0) -> 67004.832 | BR38: =IF($BE38="futuro",-($BL38-BK38)*$BD38,0) -> 33502.416 | BS38: =IF($BE38="futuro",-($BL38-BL38)*$BD38,0) -> 0 | BT38: =IF($BE38="futuro",-($BL38-BM38)*$BD38,0) -> -33502.416 | BU38: =IF($BE38="futuro",-($BL38-BN38)*$BD38,0) -> -67004.832 | BV38: =IF($BE38="futuro",-($BL38-BO38)*$BD38,0) -> -100507.25 | BW38: =IF(AND($BH38="CC",($BC38-BI38)<0),(BI38-$BC38)*$BD38, IF(AND($BH38="VC",($BC38-BI38)<0),($BC38-BI38)*-$BD38, IF(AND($BH38="CP",($BC38-BI38)>0),(BI38-$BC38)*$BD38*-1, IF(AND($BH38="VP",($BC38-BI38)>0),(BI38-$BC38)*$BD38*-1,0)))) -> 0 | BX38: =IF(AND($BH38="CC",($BC38-BJ38)<0),(BJ38-$BC38)*$BD38, IF(AND($BH38="VC",($BC38-BJ38)<0),($BC38-BJ38)*-$BD38, IF(AND($BH38="CP",($BC38-BJ38)>0),(BJ38-$BC38)*$BD38*-1, IF(AND($BH38="VP",($BC38-BJ38)>0),(BJ38-$BC38)*$BD38*-1,0)))) -> 0 | BY38: =IF(AND($BH38="CC",($BC38-BK38)<0),(BK38-$BC38)*$BD38, IF(AND($BH38="VC",($BC38-BK38)<0),($BC38-BK38)*-$BD38, IF(AND($BH38="CP",($BC38-BK38)>0),(BK38-$BC38)*$BD38*-1, IF(AND($BH38="VP",($BC38-BK38)>0),(BK38-$BC38)*$BD38*-1,0)))) -> 0 | BZ38: =IF(AND($BH38="CC",($BC38-BL38)<0),(BL38-$BC38)*$BD38, IF(AND($BH38="VC",($BC38-BL38)<0),($BC38-BL38)*-$BD38, IF(AND($BH38="CP",($BC38-BL38)>0),(BL38-$BC38)*$BD38*-1, IF(AND($BH38="VP",($BC38-BL38)>0),(BL38-$BC38)*$BD38*-1,0)))) -> 0 | CA38: =IF(AND($BH38="CC",($BC38-BM38)<0),(BM38-$BC38)*$BD38, IF(AND($BH38="VC",($BC38-BM38)<0),($BC38-BM38)*-$BD38, IF(AND($BH38="CP",($BC38-BM38)>0),(BM38-$BC38)*$BD38*-1, IF(AND($BH38="VP",($BC38-BM38)>0),(BM38-$BC38)*$BD38*-1,0)))) -> 0 | CB38: =IF(AND($BH38="CC",($BC38-BN38)<0),(BN38-$BC38)*$BD38, IF(AND($BH38="VC",($BC38-BN38)<0),($BC38-BN38)*-$BD38, IF(AND($BH38="CP",($BC38-BN38)>0),(BN38-$BC38)*$BD38*-1, IF(AND($BH38="VP",($BC38-BN38)>0),(BN38-$BC38)*$BD38*-1,0)))) -> 0 | CC38: =IF(AND($BH38="CC",($BC38-BO38)<0),(BO38-$BC38)*$BD38, IF(AND($BH38="VC",($BC38-BO38)<0),($BC38-BO38)*-$BD38, IF(AND($BH38="CP",($BC38-BO38)>0),(BO38-$BC38)*$BD38*-1, IF(AND($BH38="VP",($BC38-BO38)>0),(BO38-$BC38)*$BD38*-1,0)))) -> 0 | CD38: =IF(AND($BH38="CC",($BC38-BI38)<0),$BD38*1, IF(AND($BH38="VC",($BC38-BI38)<0),$BD38*1, IF(AND($BH38="CP",($BC38-BI38)>0),$BD38*-1, IF(AND($BH38="VP",($BC38-BI38)>0),$BD38*-1,0)))) -> 0 | CE38: =IF(AND($BH38="CC",($BC38-BJ38)<0),$BD38*1, IF(AND($BH38="VC",($BC38-BJ38)<0),$BD38*1, IF(AND($BH38="CP",($BC38-BJ38)>0),$BD38*-1, IF(AND($BH38="VP",($BC38-BJ38)>0),$BD38*-1,0)))) -> 0 | CF38: =IF(AND($BH38="CC",($BC38-BK38)<0),$BD38*1, IF(AND($BH38="VC",($BC38-BK38)<0),$BD38*1, IF(AND($BH38="CP",($BC38-BK38)>0),$BD38*-1, IF(AND($BH38="VP",($BC38-BK38)>0),$BD38*-1,0)))) -> 0 | CG38: =IF(AND($BH38="CC",($BC38-BL38)<0),$BD38*1, IF(AND($BH38="VC",($BC38-BL38)<0),$BD38*1, IF(AND($BH38="CP",($BC38-BL38)>0),$BD38*-1, IF(AND($BH38="VP",($BC38-BL38)>0),$BD38*-1,0)))) -> 0 | CH38: =IF(AND($BH38="CC",($BC38-BM38)<0),$BD38*1, IF(AND($BH38="VC",($BC38-BM38)<0),$BD38*1, IF(AND($BH38="CP",($BC38-BM38)>0),$BD38*-1, IF(AND($BH38="VP",($BC38-BM38)>0),$BD38*-1,0)))) -> 0 | CI38: =IF(AND($BH38="CC",($BC38-BN38)<0),$BD38*1, IF(AND($BH38="VC",($BC38-BN38)<0),$BD38*1, IF(AND($BH38="CP",($BC38-BN38)>0),$BD38*-1, IF(AND($BH38="VP",($BC38-BN38)>0),$BD38*-1,0)))) -> 0 | CJ38: =IF(AND($BH38="CC",($BC38-BO38)<0),$BD38*1, IF(AND($BH38="VC",($BC38-BO38)<0),$BD38*1, IF(AND($BH38="CP",($BC38-BO38)>0),$BD38*-1, IF(AND($BH38="VP",($BC38-BO38)>0),$BD38*-1,0)))) -> 0 | CK38: =Tabla3[[#This Row],[Tns]] -> -816.48 | CL38: =IF(ISERROR(VLOOKUP(VALUE(E38),'Clientes CBOT'!A:A,1,0)),"VER","ok") -> ok
A39: P | B39: R | C39: 766 | D39: 0 | E39: 20176 | F39: C | H39: F1 | I39: .AS-0000026E | J39: 4277 | K39: 2 | L39: 30000 | M39: MAY 26 SOYBEANS | N39: 11.20 3/4 | O39: 20251028 | Q39: 202605 | S39: F | U39: 0 | V39: 0 | X39: FYO ACOPIO SA | Z39: 20251028 | AA39: 1 | AB39: 1A | AC39: S- | AF39: 11.20750000 | AL39: 0 | AM39: 3.0000 | AN39: USD | AO39: 60000 | AP39: 1116750000 | AQ39: 0 | AR39: 50000 | AS39: 5J28 z9S0 | AT39: 116104277 | AU39: 0,0000 | AV39: S | AW39: CBT | AX39: Comdty | AY39: Soja | AZ39: =IF(VLOOKUP(AY39,Conversor!B:C,2,0)="HS",0.1,VLOOKUP(AY39,Conversor!B:C,2,0)) -> 0.36743 | BA39: =IF(BG39="v",-AM39/10000,AL39/10000) -> -3 | BB39: =IF(AQ39=0,AP39/1000000*AZ39,AQ39/1000000*AZ39) -> 410.32745 | BC39: =U39/1000000*AZ39 -> 0 | BD39: =IF(OR(E39="FUTUR",E39="f20176"),0,VLOOKUP(AY39,Conversor!G:I,3,0)*BA39) -> -408.24 | BE39: =IF(LEFT(M39,4)="call","Call",IF(LEFT(M39,3)="put","Put","Futuro")) -> Futuro | BF39: =IF(BE39="futuro","no","si") -> no | BG39: =IF(AL39=0,"V","C") -> V | BH39: =IF(BE39="futuro","",CONCATENATE(BG39,LEFT(BE39,1))) | BI39: =$BB39*(1+BI$2) -> 287.22922 | BJ39: =$BB39*(1+BJ$2) -> 328.26196 | BK39: =$BB39*(1+BK$2) -> 369.29471 | BL39: =$BB39*(1+BL$2) -> 410.32745 | BM39: =$BB39*(1+BM$2) -> 451.3602 | BN39: =$BB39*(1+BN$2) -> 492.39294 | BO39: =$BB39*(1+BO$2) -> 533.42569 | BP39: =IF($BE39="futuro",-($BL39-BI39)*$BD39,0) -> 50253.624 | BQ39: =IF($BE39="futuro",-($BL39-BJ39)*$BD39,0) -> 33502.416 | BR39: =IF($BE39="futuro",-($BL39-BK39)*$BD39,0) -> 16751.208 | BS39: =IF($BE39="futuro",-($BL39-BL39)*$BD39,0) -> 0 | BT39: =IF($BE39="futuro",-($BL39-BM39)*$BD39,0) -> -16751.208 | BU39: =IF($BE39="futuro",-($BL39-BN39)*$BD39,0) -> -33502.416 | BV39: =IF($BE39="futuro",-($BL39-BO39)*$BD39,0) -> -50253.624 | BW39: =IF(AND($BH39="CC",($BC39-BI39)<0),(BI39-$BC39)*$BD39, IF(AND($BH39="VC",($BC39-BI39)<0),($BC39-BI39)*-$BD39, IF(AND($BH39="CP",($BC39-BI39)>0),(BI39-$BC39)*$BD39*-1, IF(AND($BH39="VP",($BC39-BI39)>0),(BI39-$BC39)*$BD39*-1,0)))) -> 0 | BX39: =IF(AND($BH39="CC",($BC39-BJ39)<0),(BJ39-$BC39)*$BD39, IF(AND($BH39="VC",($BC39-BJ39)<0),($BC39-BJ39)*-$BD39, IF(AND($BH39="CP",($BC39-BJ39)>0),(BJ39-$BC39)*$BD39*-1, IF(AND($BH39="VP",($BC39-BJ39)>0),(BJ39-$BC39)*$BD39*-1,0)))) -> 0 | BY39: =IF(AND($BH39="CC",($BC39-BK39)<0),(BK39-$BC39)*$BD39, IF(AND($BH39="VC",($BC39-BK39)<0),($BC39-BK39)*-$BD39, IF(AND($BH39="CP",($BC39-BK39)>0),(BK39-$BC39)*$BD39*-1, IF(AND($BH39="VP",($BC39-BK39)>0),(BK39-$BC39)*$BD39*-1,0)))) -> 0 | BZ39: =IF(AND($BH39="CC",($BC39-BL39)<0),(BL39-$BC39)*$BD39, IF(AND($BH39="VC",($BC39-BL39)<0),($BC39-BL39)*-$BD39, IF(AND($BH39="CP",($BC39-BL39)>0),(BL39-$BC39)*$BD39*-1, IF(AND($BH39="VP",($BC39-BL39)>0),(BL39-$BC39)*$BD39*-1,0)))) -> 0 | CA39: =IF(AND($BH39="CC",($BC39-BM39)<0),(BM39-$BC39)*$BD39, IF(AND($BH39="VC",($BC39-BM39)<0),($BC39-BM39)*-$BD39, IF(AND($BH39="CP",($BC39-BM39)>0),(BM39-$BC39)*$BD39*-1, IF(AND($BH39="VP",($BC39-BM39)>0),(BM39-$BC39)*$BD39*-1,0)))) -> 0 | CB39: =IF(AND($BH39="CC",($BC39-BN39)<0),(BN39-$BC39)*$BD39, IF(AND($BH39="VC",($BC39-BN39)<0),($BC39-BN39)*-$BD39, IF(AND($BH39="CP",($BC39-BN39)>0),(BN39-$BC39)*$BD39*-1, IF(AND($BH39="VP",($BC39-BN39)>0),(BN39-$BC39)*$BD39*-1,0)))) -> 0 | CC39: =IF(AND($BH39="CC",($BC39-BO39)<0),(BO39-$BC39)*$BD39, IF(AND($BH39="VC",($BC39-BO39)<0),($BC39-BO39)*-$BD39, IF(AND($BH39="CP",($BC39-BO39)>0),(BO39-$BC39)*$BD39*-1, IF(AND($BH39="VP",($BC39-BO39)>0),(BO39-$BC39)*$BD39*-1,0)))) -> 0 | CD39: =IF(AND($BH39="CC",($BC39-BI39)<0),$BD39*1, IF(AND($BH39="VC",($BC39-BI39)<0),$BD39*1, IF(AND($BH39="CP",($BC39-BI39)>0),$BD39*-1, IF(AND($BH39="VP",($BC39-BI39)>0),$BD39*-1,0)))) -> 0 | CE39: =IF(AND($BH39="CC",($BC39-BJ39)<0),$BD39*1, IF(AND($BH39="VC",($BC39-BJ39)<0),$BD39*1, IF(AND($BH39="CP",($BC39-BJ39)>0),$BD39*-1, IF(AND($BH39="VP",($BC39-BJ39)>0),$BD39*-1,0)))) -> 0 | CF39: =IF(AND($BH39="CC",($BC39-BK39)<0),$BD39*1, IF(AND($BH39="VC",($BC39-BK39)<0),$BD39*1, IF(AND($BH39="CP",($BC39-BK39)>0),$BD39*-1, IF(AND($BH39="VP",($BC39-BK39)>0),$BD39*-1,0)))) -> 0 | CG39: =IF(AND($BH39="CC",($BC39-BL39)<0),$BD39*1, IF(AND($BH39="VC",($BC39-BL39)<0),$BD39*1, IF(AND($BH39="CP",($BC39-BL39)>0),$BD39*-1, IF(AND($BH39="VP",($BC39-BL39)>0),$BD39*-1,0)))) -> 0 | CH39: =IF(AND($BH39="CC",($BC39-BM39)<0),$BD39*1, IF(AND($BH39="VC",($BC39-BM39)<0),$BD39*1, IF(AND($BH39="CP",($BC39-BM39)>0),$BD39*-1, IF(AND($BH39="VP",($BC39-BM39)>0),$BD39*-1,0)))) -> 0 | CI39: =IF(AND($BH39="CC",($BC39-BN39)<0),$BD39*1, IF(AND($BH39="VC",($BC39-BN39)<0),$BD39*1, IF(AND($BH39="CP",($BC39-BN39)>0),$BD39*-1, IF(AND($BH39="VP",($BC39-BN39)>0),$BD39*-1,0)))) -> 0 | CJ39: =IF(AND($BH39="CC",($BC39-BO39)<0),$BD39*1, IF(AND($BH39="VC",($BC39-BO39)<0),$BD39*1, IF(AND($BH39="CP",($BC39-BO39)>0),$BD39*-1, IF(AND($BH39="VP",($BC39-BO39)>0),$BD39*-1,0)))) -> 0 | CK39: =Tabla3[[#This Row],[Tns]] -> -408.24 | CL39: =IF(ISERROR(VLOOKUP(VALUE(E39),'Clientes CBOT'!A:A,1,0)),"VER","ok") -> ok
A40: P | B40: R | C40: 766 | D40: 0 | E40: 20176 | F40: C | H40: F1 | I40: .AS-0000026E | J40: 5114 | K40: 2 | L40: 30000 | M40: MAY 26 SOYBEANS | N40: 11.18 1/4 | O40: 20251030 | Q40: 202605 | S40: F | U40: 0 | V40: 0 | X40: FYO ACOPIO SA | Z40: 20251030 | AA40: 1 | AB40: 1A | AC40: S- | AF40: 11.18250000 | AL40: 0 | AM40: 3.0000 | AN40: USD | AO40: 22500 | AP40: 1116750000 | AQ40: 0 | AR40: 50000 | AS40: 5J30 Apn0 | AT40: 116135114 | AU40: 0,0000 | AV40: S | AW40: CBT | AX40: Comdty | AY40: Soja | AZ40: =IF(VLOOKUP(AY40,Conversor!B:C,2,0)="HS",0.01,VLOOKUP(AY40,Conversor!B:C,2,0)) -> 0.36743 | BA40: =IF(BG40="v",-AM40/10000,AL40/10000) -> -3 | BB40: =IF(AQ40=0,AP40/1000000*AZ40,AQ40/1000000*AZ40) -> 410.32745 | BC40: =U40/1000000*AZ40 -> 0 | BD40: =IF(OR(E40="FUTUR",E40="f20176"),0,VLOOKUP(AY40,Conversor!G:I,3,0)*BA40) -> -408.24 | BE40: =IF(LEFT(M40,4)="call","Call",IF(LEFT(M40,3)="put","Put","Futuro")) -> Futuro | BF40: =IF(BE40="futuro","no","si") -> no | BG40: =IF(AL40=0,"V","C") -> V | BH40: =IF(BE40="futuro","",CONCATENATE(BG40,LEFT(BE40,1))) | BI40: =$BB40*(1+BI$2) -> 287.22922 | BJ40: =$BB40*(1+BJ$2) -> 328.26196 | BK40: =$BB40*(1+BK$2) -> 369.29471 | BL40: =$BB40*(1+BL$2) -> 410.32745 | BM40: =$BB40*(1+BM$2) -> 451.3602 | BN40: =$BB40*(1+BN$2) -> 492.39294 | BO40: =$BB40*(1+BO$2) -> 533.42569 | BP40: =IF($BE40="futuro",-($BL40-BI40)*$BD40,0) -> 50253.624 | BQ40: =IF($BE40="futuro",-($BL40-BJ40)*$BD40,0) -> 33502.416 | BR40: =IF($BE40="futuro",-($BL40-BK40)*$BD40,0) -> 16751.208 | BS40: =IF($BE40="futuro",-($BL40-BL40)*$BD40,0) -> 0 | BT40: =IF($BE40="futuro",-($BL40-BM40)*$BD40,0) -> -16751.208 | BU40: =IF($BE40="futuro",-($BL40-BN40)*$BD40,0) -> -33502.416 | BV40: =IF($BE40="futuro",-($BL40-BO40)*$BD40,0) -> -50253.624 | BW40: =IF(AND($BH40="CC",($BC40-BI40)<0),(BI40-$BC40)*$BD40, IF(AND($BH40="VC",($BC40-BI40)<0),($BC40-BI40)*-$BD40, IF(AND($BH40="CP",($BC40-BI40)>0),(BI40-$BC40)*$BD40*-1, IF(AND($BH40="VP",($BC40-BI40)>0),(BI40-$BC40)*$BD40*-1,0)))) -> 0 | BX40: =IF(AND($BH40="CC",($BC40-BJ40)<0),(BJ40-$BC40)*$BD40, IF(AND($BH40="VC",($BC40-BJ40)<0),($BC40-BJ40)*-$BD40, IF(AND($BH40="CP",($BC40-BJ40)>0),(BJ40-$BC40)*$BD40*-1, IF(AND($BH40="VP",($BC40-BJ40)>0),(BJ40-$BC40)*$BD40*-1,0)))) -> 0 | BY40: =IF(AND($BH40="CC",($BC40-BK40)<0),(BK40-$BC40)*$BD40, IF(AND($BH40="VC",($BC40-BK40)<0),($BC40-BK40)*-$BD40, IF(AND($BH40="CP",($BC40-BK40)>0),(BK40-$BC40)*$BD40*-1, IF(AND($BH40="VP",($BC40-BK40)>0),(BK40-$BC40)*$BD40*-1,0)))) -> 0 | BZ40: =IF(AND($BH40="CC",($BC40-BL40)<0),(BL40-$BC40)*$BD40, IF(AND($BH40="VC",($BC40-BL40)<0),($BC40-BL40)*-$BD40, IF(AND($BH40="CP",($BC40-BL40)>0),(BL40-$BC40)*$BD40*-1, IF(AND($BH40="VP",($BC40-BL40)>0),(BL40-$BC40)*$BD40*-1,0)))) -> 0 | CA40: =IF(AND($BH40="CC",($BC40-BM40)<0),(BM40-$BC40)*$BD40, IF(AND($BH40="VC",($BC40-BM40)<0),($BC40-BM40)*-$BD40, IF(AND($BH40="CP",($BC40-BM40)>0),(BM40-$BC40)*$BD40*-1, IF(AND($BH40="VP",($BC40-BM40)>0),(BM40-$BC40)*$BD40*-1,0)))) -> 0 | CB40: =IF(AND($BH40="CC",($BC40-BN40)<0),(BN40-$BC40)*$BD40, IF(AND($BH40="VC",($BC40-BN40)<0),($BC40-BN40)*-$BD40, IF(AND($BH40="CP",($BC40-BN40)>0),(BN40-$BC40)*$BD40*-1, IF(AND($BH40="VP",($BC40-BN40)>0),(BN40-$BC40)*$BD40*-1,0)))) -> 0 | CC40: =IF(AND($BH40="CC",($BC40-BO40)<0),(BO40-$BC40)*$BD40, IF(AND($BH40="VC",($BC40-BO40)<0),($BC40-BO40)*-$BD40, IF(AND($BH40="CP",($BC40-BO40)>0),(BO40-$BC40)*$BD40*-1, IF(AND($BH40="VP",($BC40-BO40)>0),(BO40-$BC40)*$BD40*-1,0)))) -> 0 | CD40: =IF(AND($BH40="CC",($BC40-BI40)<0),$BD40*1, IF(AND($BH40="VC",($BC40-BI40)<0),$BD40*1, IF(AND($BH40="CP",($BC40-BI40)>0),$BD40*-1, IF(AND($BH40="VP",($BC40-BI40)>0),$BD40*-1,0)))) -> 0 | CE40: =IF(AND($BH40="CC",($BC40-BJ40)<0),$BD40*1, IF(AND($BH40="VC",($BC40-BJ40)<0),$BD40*1, IF(AND($BH40="CP",($BC40-BJ40)>0),$BD40*-1, IF(AND($BH40="VP",($BC40-BJ40)>0),$BD40*-1,0)))) -> 0 | CF40: =IF(AND($BH40="CC",($BC40-BK40)<0),$BD40*1, IF(AND($BH40="VC",($BC40-BK40)<0),$BD40*1, IF(AND($BH40="CP",($BC40-BK40)>0),$BD40*-1, IF(AND($BH40="VP",($BC40-BK40)>0),$BD40*-1,0)))) -> 0 | CG40: =IF(AND($BH40="CC",($BC40-BL40)<0),$BD40*1, IF(AND($BH40="VC",($BC40-BL40)<0),$BD40*1, IF(AND($BH40="CP",($BC40-BL40)>0),$BD40*-1, IF(AND($BH40="VP",($BC40-BL40)>0),$BD40*-1,0)))) -> 0 | CH40: =IF(AND($BH40="CC",($BC40-BM40)<0),$BD40*1, IF(AND($BH40="VC",($BC40-BM40)<0),$BD40*1, IF(AND($BH40="CP",($BC40-BM40)>0),$BD40*-1, IF(AND($BH40="VP",($BC40-BM40)>0),$BD40*-1,0)))) -> 0 | CI40: =IF(AND($BH40="CC",($BC40-BN40)<0),$BD40*1, IF(AND($BH40="VC",($BC40-BN40)<0),$BD40*1, IF(AND($BH40="CP",($BC40-BN40)>0),$BD40*-1, IF(AND($BH40="VP",($BC40-BN40)>0),$BD40*-1,0)))) -> 0 | CJ40: =IF(AND($BH40="CC",($BC40-BO40)<0),$BD40*1, IF(AND($BH40="VC",($BC40-BO40)<0),$BD40*1, IF(AND($BH40="CP",($BC40-BO40)>0),$BD40*-1, IF(AND($BH40="VP",($BC40-BO40)>0),$BD40*-1,0)))) -> 0 | CK40: =Tabla3[[#This Row],[Tns]] -> -408.24 | CL40: =IF(ISERROR(VLOOKUP(VALUE(E40),'Clientes CBOT'!A:A,1,0)),"VER","ok") -> ok
A41: P | B41: R | C41: 766 | D41: 0 | E41: 20176 | F41: C | H41: F1 | I41: .AS-0000026E | J41: 2920 | K41: 2 | L41: 30000 | M41: MAY 26 SOYBEANS | N41: 11.30 3/4 | O41: 20251031 | Q41: 202605 | S41: F | U41: 0 | V41: 0 | X41: FYO ACOPIO SA | Z41: 20251031 | AA41: 1 | AB41: 1A | AC41: S- | AF41: 11.30750000 | AL41: 0 | AM41: 3.0000 | AN41: USD | AO41: 210000 | AP41: 1116750000 | AQ41: 0 | AR41: 50000 | AS41: 5J31 I5E0 | AT41: 116152920 | AU41: 0,0000 | AV41: S | AW41: CBT | AX41: Comdty | AY41: Soja | AZ41: =IF(VLOOKUP(AY41,Conversor!B:C,2,0)="HS",0.01,VLOOKUP(AY41,Conversor!B:C,2,0)) -> 0.36743 | BA41: =IF(BG41="v",-AM41/10000,AL41/10000) -> -3 | BB41: =IF(AQ41=0,AP41/1000000*AZ41,AQ41/1000000*AZ41) -> 410.32745 | BC41: =U41/1000000*AZ41 -> 0 | BD41: =IF(OR(E41="FUTUR",E41="f20176"),0,VLOOKUP(AY41,Conversor!G:I,3,0)*BA41) -> -408.24 | BE41: =IF(LEFT(M41,4)="call","Call",IF(LEFT(M41,3)="put","Put","Futuro")) -> Futuro | BF41: =IF(BE41="futuro","no","si") -> no | BG41: =IF(AL41=0,"V","C") -> V | BH41: =IF(BE41="futuro","",CONCATENATE(BG41,LEFT(BE41,1))) | BI41: =$BB41*(1+BI$2) -> 287.22922 | BJ41: =$BB41*(1+BJ$2) -> 328.26196 | BK41: =$BB41*(1+BK$2) -> 369.29471 | BL41: =$BB41*(1+BL$2) -> 410.32745 | BM41: =$BB41*(1+BM$2) -> 451.3602 | BN41: =$BB41*(1+BN$2) -> 492.39294 | BO41: =$BB41*(1+BO$2) -> 533.42569 | BP41: =IF($BE41="futuro",-($BL41-BI41)*$BD41,0) -> 50253.624 | BQ41: =IF($BE41="futuro",-($BL41-BJ41)*$BD41,0) -> 33502.416 | BR41: =IF($BE41="futuro",-($BL41-BK41)*$BD41,0) -> 16751.208 | BS41: =IF($BE41="futuro",-($BL41-BL41)*$BD41,0) -> 0 | BT41: =IF($BE41="futuro",-($BL41-BM41)*$BD41,0) -> -16751.208 | BU41: =IF($BE41="futuro",-($BL41-BN41)*$BD41,0) -> -33502.416 | BV41: =IF($BE41="futuro",-($BL41-BO41)*$BD41,0) -> -50253.624 | BW41: =IF(AND($BH41="CC",($BC41-BI41)<0),(BI41-$BC41)*$BD41, IF(AND($BH41="VC",($BC41-BI41)<0),($BC41-BI41)*-$BD41, IF(AND($BH41="CP",($BC41-BI41)>0),(BI41-$BC41)*$BD41*-1, IF(AND($BH41="VP",($BC41-BI41)>0),(BI41-$BC41)*$BD41*-1,0)))) -> 0 | BX41: =IF(AND($BH41="CC",($BC41-BJ41)<0),(BJ41-$BC41)*$BD41, IF(AND($BH41="VC",($BC41-BJ41)<0),($BC41-BJ41)*-$BD41, IF(AND($BH41="CP",($BC41-BJ41)>0),(BJ41-$BC41)*$BD41*-1, IF(AND($BH41="VP",($BC41-BJ41)>0),(BJ41-$BC41)*$BD41*-1,0)))) -> 0 | BY41: =IF(AND($BH41="CC",($BC41-BK41)<0),(BK41-$BC41)*$BD41, IF(AND($BH41="VC",($BC41-BK41)<0),($BC41-BK41)*-$BD41, IF(AND($BH41="CP",($BC41-BK41)>0),(BK41-$BC41)*$BD41*-1, IF(AND($BH41="VP",($BC41-BK41)>0),(BK41-$BC41)*$BD41*-1,0)))) -> 0 | BZ41: =IF(AND($BH41="CC",($BC41-BL41)<0),(BL41-$BC41)*$BD41, IF(AND($BH41="VC",($BC41-BL41)<0),($BC41-BL41)*-$BD41, IF(AND($BH41="CP",($BC41-BL41)>0),(BL41-$BC41)*$BD41*-1, IF(AND($BH41="VP",($BC41-BL41)>0),(BL41-$BC41)*$BD41*-1,0)))) -> 0 | CA41: =IF(AND($BH41="CC",($BC41-BM41)<0),(BM41-$BC41)*$BD41, IF(AND($BH41="VC",($BC41-BM41)<0),($BC41-BM41)*-$BD41, IF(AND($BH41="CP",($BC41-BM41)>0),(BM41-$BC41)*$BD41*-1, IF(AND($BH41="VP",($BC41-BM41)>0),(BM41-$BC41)*$BD41*-1,0)))) -> 0 | CB41: =IF(AND($BH41="CC",($BC41-BN41)<0),(BN41-$BC41)*$BD41, IF(AND($BH41="VC",($BC41-BN41)<0),($BC41-BN41)*-$BD41, IF(AND($BH41="CP",($BC41-BN41)>0),(BN41-$BC41)*$BD41*-1, IF(AND($BH41="VP",($BC41-BN41)>0),(BN41-$BC41)*$BD41*-1,0)))) -> 0 | CC41: =IF(AND($BH41="CC",($BC41-BO41)<0),(BO41-$BC41)*$BD41, IF(AND($BH41="VC",($BC41-BO41)<0),($BC41-BO41)*-$BD41, IF(AND($BH41="CP",($BC41-BO41)>0),(BO41-$BC41)*$BD41*-1, IF(AND($BH41="VP",($BC41-BO41)>0),(BO41-$BC41)*$BD41*-1,0)))) -> 0 | CD41: =IF(AND($BH41="CC",($BC41-BI41)<0),$BD41*1, IF(AND($BH41="VC",($BC41-BI41)<0),$BD41*1, IF(AND($BH41="CP",($BC41-BI41)>0),$BD41*-1, IF(AND($BH41="VP",($BC41-BI41)>0),$BD41*-1,0)))) -> 0 | CE41: =IF(AND($BH41="CC",($BC41-BJ41)<0),$BD41*1, IF(AND($BH41="VC",($BC41-BJ41)<0),$BD41*1, IF(AND($BH41="CP",($BC41-BJ41)>0),$BD41*-1, IF(AND($BH41="VP",($BC41-BJ41)>0),$BD41*-1,0)))) -> 0 | CF41: =IF(AND($BH41="CC",($BC41-BK41)<0),$BD41*1, IF(AND($BH41="VC",($BC41-BK41)<0),$BD41*1, IF(AND($BH41="CP",($BC41-BK41)>0),$BD41*-1, IF(AND($BH41="VP",($BC41-BK41)>0),$BD41*-1,0)))) -> 0 | CG41: =IF(AND($BH41="CC",($BC41-BL41)<0),$BD41*1, IF(AND($BH41="VC",($BC41-BL41)<0),$BD41*1, IF(AND($BH41="CP",($BC41-BL41)>0),$BD41*-1, IF(AND($BH41="VP",($BC41-BL41)>0),$BD41*-1,0)))) -> 0 | CH41: =IF(AND($BH41="CC",($BC41-BM41)<0),$BD41*1, IF(AND($BH41="VC",($BC41-BM41)<0),$BD41*1, IF(AND($BH41="CP",($BC41-BM41)>0),$BD41*-1, IF(AND($BH41="VP",($BC41-BM41)>0),$BD41*-1,0)))) -> 0 | CI41: =IF(AND($BH41="CC",($BC41-BN41)<0),$BD41*1, IF(AND($BH41="VC",($BC41-BN41)<0),$BD41*1, IF(AND($BH41="CP",($BC41-BN41)>0),$BD41*-1, IF(AND($BH41="VP",($BC41-BN41)>0),$BD41*-1,0)))) -> 0 | CJ41: =IF(AND($BH41="CC",($BC41-BO41)<0),$BD41*1, IF(AND($BH41="VC",($BC41-BO41)<0),$BD41*1, IF(AND($BH41="CP",($BC41-BO41)>0),$BD41*-1, IF(AND($BH41="VP",($BC41-BO41)>0),$BD41*-1,0)))) -> 0 | CK41: =Tabla3[[#This Row],[Tns]] -> -408.24 | CL41: =IF(ISERROR(VLOOKUP(VALUE(E41),'Clientes CBOT'!A:A,1,0)),"VER","ok") -> ok
A42: P | B42: R | C42: 766 | D42: 0 | E42: 20176 | F42: C | H42: F1 | I42: .AS-0000026E | J42: 69 | K42: 2 | L42: 370000 | M42: MAY 26 SOYBEANS | N42: 11.35 3/4 | O42: 20251103 | Q42: 202605 | S42: F | U42: 0 | V42: 0 | X42: FYO ACOPIO SA | Z42: 20251103 | AA42: 1 | AB42: 1A | AC42: S- | AF42: 11.35750000 | AL42: 0 | AM42: 37.0000 | AN42: USD | AO42: 3515000 | AP42: 1116750000 | AQ42: 0 | AR42: 50000 | AS42: 5K03 BS90 | AT42: 116160069 | AU42: 0,0000 | AV42: S | AW42: CBT | AX42: Comdty | AY42: Soja | AZ42: =IF(VLOOKUP(AY42,Conversor!B:C,2,0)="HS",0.01,VLOOKUP(AY42,Conversor!B:C,2,0)) -> 0.36743 | BA42: =IF(BG42="v",-AM42/10000,AL42/10000) -> -37 | BB42: =IF(AQ42=0,AP42/1000000*AZ42,AQ42/1000000*AZ42) -> 410.32745 | BC42: =U42/1000000*AZ42 -> 0 | BD42: =IF(OR(E42="FUTUR",E42="f20176"),0,VLOOKUP(AY42,Conversor!G:I,3,0)*BA42) -> -5034.96 | BE42: =IF(LEFT(M42,4)="call","Call",IF(LEFT(M42,3)="put","Put","Futuro")) -> Futuro | BF42: =IF(BE42="futuro","no","si") -> no | BG42: =IF(AL42=0,"V","C") -> V | BH42: =IF(BE42="futuro","",CONCATENATE(BG42,LEFT(BE42,1))) | BI42: =$BB42*(1+BI$2) -> 287.22922 | BJ42: =$BB42*(1+BJ$2) -> 328.26196 | BK42: =$BB42*(1+BK$2) -> 369.29471 | BL42: =$BB42*(1+BL$2) -> 410.32745 | BM42: =$BB42*(1+BM$2) -> 451.3602 | BN42: =$BB42*(1+BN$2) -> 492.39294 | BO42: =$BB42*(1+BO$2) -> 533.42569 | BP42: =IF($BE42="futuro",-($BL42-BI42)*$BD42,0) -> 619794.69 | BQ42: =IF($BE42="futuro",-($BL42-BJ42)*$BD42,0) -> 413196.46 | BR42: =IF($BE42="futuro",-($BL42-BK42)*$BD42,0) -> 206598.23 | BS42: =IF($BE42="futuro",-($BL42-BL42)*$BD42,0) -> 0 | BT42: =IF($BE42="futuro",-($BL42-BM42)*$BD42,0) -> -206598.23 | BU42: =IF($BE42="futuro",-($BL42-BN42)*$BD42,0) -> -413196.46 | BV42: =IF($BE42="futuro",-($BL42-BO42)*$BD42,0) -> -619794.69 | BW42: =IF(AND($BH42="CC",($BC42-BI42)<0),(BI42-$BC42)*$BD42, IF(AND($BH42="VC",($BC42-BI42)<0),($BC42-BI42)*-$BD42, IF(AND($BH42="CP",($BC42-BI42)>0),(BI42-$BC42)*$BD42*-1, IF(AND($BH42="VP",($BC42-BI42)>0),(BI42-$BC42)*$BD42*-1,0)))) -> 0 | BX42: =IF(AND($BH42="CC",($BC42-BJ42)<0),(BJ42-$BC42)*$BD42, IF(AND($BH42="VC",($BC42-BJ42)<0),($BC42-BJ42)*-$BD42, IF(AND($BH42="CP",($BC42-BJ42)>0),(BJ42-$BC42)*$BD42*-1, IF(AND($BH42="VP",($BC42-BJ42)>0),(BJ42-$BC42)*$BD42*-1,0)))) -> 0 | BY42: =IF(AND($BH42="CC",($BC42-BK42)<0),(BK42-$BC42)*$BD42, IF(AND($BH42="VC",($BC42-BK42)<0),($BC42-BK42)*-$BD42, IF(AND($BH42="CP",($BC42-BK42)>0),(BK42-$BC42)*$BD42*-1, IF(AND($BH42="VP",($BC42-BK42)>0),(BK42-$BC42)*$BD42*-1,0)))) -> 0 | BZ42: =IF(AND($BH42="CC",($BC42-BL42)<0),(BL42-$BC42)*$BD42, IF(AND($BH42="VC",($BC42-BL42)<0),($BC42-BL42)*-$BD42, IF(AND($BH42="CP",($BC42-BL42)>0),(BL42-$BC42)*$BD42*-1, IF(AND($BH42="VP",($BC42-BL42)>0),(BL42-$BC42)*$BD42*-1,0)))) -> 0 | CA42: =IF(AND($BH42="CC",($BC42-BM42)<0),(BM42-$BC42)*$BD42, IF(AND($BH42="VC",($BC42-BM42)<0),($BC42-BM42)*-$BD42, IF(AND($BH42="CP",($BC42-BM42)>0),(BM42-$BC42)*$BD42*-1, IF(AND($BH42="VP",($BC42-BM42)>0),(BM42-$BC42)*$BD42*-1,0)))) -> 0 | CB42: =IF(AND($BH42="CC",($BC42-BN42)<0),(BN42-$BC42)*$BD42, IF(AND($BH42="VC",($BC42-BN42)<0),($BC42-BN42)*-$BD42, IF(AND($BH42="CP",($BC42-BN42)>0),(BN42-$BC42)*$BD42*-1, IF(AND($BH42="VP",($BC42-BN42)>0),(BN42-$BC42)*$BD42*-1,0)))) -> 0 | CC42: =IF(AND($BH42="CC",($BC42-BO42)<0),(BO42-$BC42)*$BD42, IF(AND($BH42="VC",($BC42-BO42)<0),($BC42-BO42)*-$BD42, IF(AND($BH42="CP",($BC42-BO42)>0),(BO42-$BC42)*$BD42*-1, IF(AND($BH42="VP",($BC42-BO42)>0),(BO42-$BC42)*$BD42*-1,0)))) -> 0 | CD42: =IF(AND($BH42="CC",($BC42-BI42)<0),$BD42*1, IF(AND($BH42="VC",($BC42-BI42)<0),$BD42*1, IF(AND($BH42="CP",($BC42-BI42)>0),$BD42*-1, IF(AND($BH42="VP",($BC42-BI42)>0),$BD42*-1,0)))) -> 0 | CE42: =IF(AND($BH42="CC",($BC42-BJ42)<0),$BD42*1, IF(AND($BH42="VC",($BC42-BJ42)<0),$BD42*1, IF(AND($BH42="CP",($BC42-BJ42)>0),$BD42*-1, IF(AND($BH42="VP",($BC42-BJ42)>0),$BD42*-1,0)))) -> 0 | CF42: =IF(AND($BH42="CC",($BC42-BK42)<0),$BD42*1, IF(AND($BH42="VC",($BC42-BK42)<0),$BD42*1, IF(AND($BH42="CP",($BC42-BK42)>0),$BD42*-1, IF(AND($BH42="VP",($BC42-BK42)>0),$BD42*-1,0)))) -> 0 | CG42: =IF(AND($BH42="CC",($BC42-BL42)<0),$BD42*1, IF(AND($BH42="VC",($BC42-BL42)<0),$BD42*1, IF(AND($BH42="CP",($BC42-BL42)>0),$BD42*-1, IF(AND($BH42="VP",($BC42-BL42)>0),$BD42*-1,0)))) -> 0 | CH42: =IF(AND($BH42="CC",($BC42-BM42)<0),$BD42*1, IF(AND($BH42="VC",($BC42-BM42)<0),$BD42*1, IF(AND($BH42="CP",($BC42-BM42)>0),$BD42*-1, IF(AND($BH42="VP",($BC42-BM42)>0),$BD42*-1,0)))) -> 0 | CI42: =IF(AND($BH42="CC",($BC42-BN42)<0),$BD42*1, IF(AND($BH42="VC",($BC42-BN42)<0),$BD42*1, IF(AND($BH42="CP",($BC42-BN42)>0),$BD42*-1, IF(AND($BH42="VP",($BC42-BN42)>0),$BD42*-1,0)))) -> 0 | CJ42: =IF(AND($BH42="CC",($BC42-BO42)<0),$BD42*1, IF(AND($BH42="VC",($BC42-BO42)<0),$BD42*1, IF(AND($BH42="CP",($BC42-BO42)>0),$BD42*-1, IF(AND($BH42="VP",($BC42-BO42)>0),$BD42*-1,0)))) -> 0 | CK42: =Tabla3[[#This Row],[Tns]] -> -5034.96 | CL42: =IF(ISERROR(VLOOKUP(VALUE(E42),'Clientes CBOT'!A:A,1,0)),"VER","ok") -> ok
A43: P | B43: R | C43: 766 | D43: 0 | E43: 20176 | F43: C | H43: F1 | I43: .AS-0000026E | J43: 444 | K43: 2 | L43: 740000 | M43: MAY 26 SOYBEANS | N43: 11.38 1/2 | O43: 20251103 | Q43: 202605 | S43: F | U43: 0 | V43: 0 | X43: FYO ACOPIO SA | Z43: 20251103 | AA43: 1 | AB43: 1A | AC43: S- | AF43: 11.38500000 | AL43: 0 | AM43: 74.0000 | AN43: USD | AO43: 8047500 | AP43: 1116750000 | AQ43: 0 | AR43: 50000 | AS43: 5K03 CYE0 | AT43: 116160444 | AU43: 0,0000 | AV43: S | AW43: CBT | AX43: Comdty | AY43: Soja | AZ43: =IF(VLOOKUP(AY43,Conversor!B:C,2,0)="HS",0.01,VLOOKUP(AY43,Conversor!B:C,2,0)) -> 0.36743 | BA43: =IF(BG43="v",-AM43/10000,AL43/10000) -> -74 | BB43: =IF(AQ43=0,AP43/1000000*AZ43,AQ43/1000000*AZ43) -> 410.32745 | BC43: =U43/1000000*AZ43 -> 0 | BD43: =IF(OR(E43="FUTUR",E43="f20176"),0,VLOOKUP(AY43,Conversor!G:I,3,0)*BA43) -> -10069.92 | BE43: =IF(LEFT(M43,4)="call","Call",IF(LEFT(M43,3)="put","Put","Futuro")) -> Futuro | BF43: =IF(BE43="futuro","no","si") -> no | BG43: =IF(AL43=0,"V","C") -> V | BH43: =IF(BE43="futuro","",CONCATENATE(BG43,LEFT(BE43,1))) | BI43: =$BB43*(1+BI$2) -> 287.22922 | BJ43: =$BB43*(1+BJ$2) -> 328.26196 | BK43: =$BB43*(1+BK$2) -> 369.29471 | BL43: =$BB43*(1+BL$2) -> 410.32745 | BM43: =$BB43*(1+BM$2) -> 451.3602 | BN43: =$BB43*(1+BN$2) -> 492.39294 | BO43: =$BB43*(1+BO$2) -> 533.42569 | BP43: =IF($BE43="futuro",-($BL43-BI43)*$BD43,0) -> 1239589.4 | BQ43: =IF($BE43="futuro",-($BL43-BJ43)*$BD43,0) -> 826392.92 | BR43: =IF($BE43="futuro",-($BL43-BK43)*$BD43,0) -> 413196.46 | BS43: =IF($BE43="futuro",-($BL43-BL43)*$BD43,0) -> 0 | BT43: =IF($BE43="futuro",-($BL43-BM43)*$BD43,0) -> -413196.46 | BU43: =IF($BE43="futuro",-($BL43-BN43)*$BD43,0) -> -826392.92 | BV43: =IF($BE43="futuro",-($BL43-BO43)*$BD43,0) -> -1239589.4 | BW43: =IF(AND($BH43="CC",($BC43-BI43)<0),(BI43-$BC43)*$BD43, IF(AND($BH43="VC",($BC43-BI43)<0),($BC43-BI43)*-$BD43, IF(AND($BH43="CP",($BC43-BI43)>0),(BI43-$BC43)*$BD43*-1, IF(AND($BH43="VP",($BC43-BI43)>0),(BI43-$BC43)*$BD43*-1,0)))) -> 0 | BX43: =IF(AND($BH43="CC",($BC43-BJ43)<0),(BJ43-$BC43)*$BD43, IF(AND($BH43="VC",($BC43-BJ43)<0),($BC43-BJ43)*-$BD43, IF(AND($BH43="CP",($BC43-BJ43)>0),(BJ43-$BC43)*$BD43*-1, IF(AND($BH43="VP",($BC43-BJ43)>0),(BJ43-$BC43)*$BD43*-1,0)))) -> 0 | BY43: =IF(AND($BH43="CC",($BC43-BK43)<0),(BK43-$BC43)*$BD43, IF(AND($BH43="VC",($BC43-BK43)<0),($BC43-BK43)*-$BD43, IF(AND($BH43="CP",($BC43-BK43)>0),(BK43-$BC43)*$BD43*-1, IF(AND($BH43="VP",($BC43-BK43)>0),(BK43-$BC43)*$BD43*-1,0)))) -> 0 | BZ43: =IF(AND($BH43="CC",($BC43-BL43)<0),(BL43-$BC43)*$BD43, IF(AND($BH43="VC",($BC43-BL43)<0),($BC43-BL43)*-$BD43, IF(AND($BH43="CP",($BC43-BL43)>0),(BL43-$BC43)*$BD43*-1, IF(AND($BH43="VP",($BC43-BL43)>0),(BL43-$BC43)*$BD43*-1,0)))) -> 0 | CA43: =IF(AND($BH43="CC",($BC43-BM43)<0),(BM43-$BC43)*$BD43, IF(AND($BH43="VC",($BC43-BM43)<0),($BC43-BM43)*-$BD43, IF(AND($BH43="CP",($BC43-BM43)>0),(BM43-$BC43)*$BD43*-1, IF(AND($BH43="VP",($BC43-BM43)>0),(BM43-$BC43)*$BD43*-1,0)))) -> 0 | CB43: =IF(AND($BH43="CC",($BC43-BN43)<0),(BN43-$BC43)*$BD43, IF(AND($BH43="VC",($BC43-BN43)<0),($BC43-BN43)*-$BD43, IF(AND($BH43="CP",($BC43-BN43)>0),(BN43-$BC43)*$BD43*-1, IF(AND($BH43="VP",($BC43-BN43)>0),(BN43-$BC43)*$BD43*-1,0)))) -> 0 | CC43: =IF(AND($BH43="CC",($BC43-BO43)<0),(BO43-$BC43)*$BD43, IF(AND($BH43="VC",($BC43-BO43)<0),($BC43-BO43)*-$BD43, IF(AND($BH43="CP",($BC43-BO43)>0),(BO43-$BC43)*$BD43*-1, IF(AND($BH43="VP",($BC43-BO43)>0),(BO43-$BC43)*$BD43*-1,0)))) -> 0 | CD43: =IF(AND($BH43="CC",($BC43-BI43)<0),$BD43*1, IF(AND($BH43="VC",($BC43-BI43)<0),$BD43*1, IF(AND($BH43="CP",($BC43-BI43)>0),$BD43*-1, IF(AND($BH43="VP",($BC43-BI43)>0),$BD43*-1,0)))) -> 0 | CE43: =IF(AND($BH43="CC",($BC43-BJ43)<0),$BD43*1, IF(AND($BH43="VC",($BC43-BJ43)<0),$BD43*1, IF(AND($BH43="CP",($BC43-BJ43)>0),$BD43*-1, IF(AND($BH43="VP",($BC43-BJ43)>0),$BD43*-1,0)))) -> 0 | CF43: =IF(AND($BH43="CC",($BC43-BK43)<0),$BD43*1, IF(AND($BH43="VC",($BC43-BK43)<0),$BD43*1, IF(AND($BH43="CP",($BC43-BK43)>0),$BD43*-1, IF(AND($BH43="VP",($BC43-BK43)>0),$BD43*-1,0)))) -> 0 | CG43: =IF(AND($BH43="CC",($BC43-BL43)<0),$BD43*1, IF(AND($BH43="VC",($BC43-BL43)<0),$BD43*1, IF(AND($BH43="CP",($BC43-BL43)>0),$BD43*-1, IF(AND($BH43="VP",($BC43-BL43)>0),$BD43*-1,0)))) -> 0 | CH43: =IF(AND($BH43="CC",($BC43-BM43)<0),$BD43*1, IF(AND($BH43="VC",($BC43-BM43)<0),$BD43*1, IF(AND($BH43="CP",($BC43-BM43)>0),$BD43*-1, IF(AND($BH43="VP",($BC43-BM43)>0),$BD43*-1,0)))) -> 0 | CI43: =IF(AND($BH43="CC",($BC43-BN43)<0),$BD43*1, IF(AND($BH43="VC",($BC43-BN43)<0),$BD43*1, IF(AND($BH43="CP",($BC43-BN43)>0),$BD43*-1, IF(AND($BH43="VP",($BC43-BN43)>0),$BD43*-1,0)))) -> 0 | CJ43: =IF(AND($BH43="CC",($BC43-BO43)<0),$BD43*1, IF(AND($BH43="VC",($BC43-BO43)<0),$BD43*1, IF(AND($BH43="CP",($BC43-BO43)>0),$BD43*-1, IF(AND($BH43="VP",($BC43-BO43)>0),$BD43*-1,0)))) -> 0 | CK43: =Tabla3[[#This Row],[Tns]] -> -10069.92 | CL43: =IF(ISERROR(VLOOKUP(VALUE(E43),'Clientes CBOT'!A:A,1,0)),"VER","ok") -> ok
A44: P | B44: R | C44: 766 | D44: 0 | E44: 20176 | F44: C | H44: F1 | I44: .AS-0000026E | J44: 3938 | K44: 2 | L44: 30000 | M44: MAY 26 SOYBEANS | N44: 11.49 | O44: 20251103 | Q44: 202605 | S44: F | U44: 0 | V44: 0 | X44: FYO ACOPIO SA | Z44: 20251103 | AA44: 1 | AB44: 1A | AC44: S- | AF44: 11.49000000 | AL44: 0 | AM44: 3.0000 | AN44: USD | AO44: 483750 | AP44: 1116750000 | AQ44: 0 | AR44: 50000 | AS44: 5K03 MrD0 | AT44: 116163938 | AU44: 0,0000 | AV44: S | AW44: CBT | AX44: Comdty | AY44: Soja | AZ44: =IF(VLOOKUP(AY44,Conversor!B:C,2,0)="HS",0.01,VLOOKUP(AY44,Conversor!B:C,2,0)) -> 0.36743 | BA44: =IF(BG44="v",-AM44/10000,AL44/10000) -> -3 | BB44: =IF(AQ44=0,AP44/1000000*AZ44,AQ44/1000000*AZ44) -> 410.32745 | BC44: =U44/1000000*AZ44 -> 0 | BD44: =IF(OR(E44="FUTUR",E44="f20176"),0,VLOOKUP(AY44,Conversor!G:I,3,0)*BA44) -> -408.24 | BE44: =IF(LEFT(M44,4)="call","Call",IF(LEFT(M44,3)="put","Put","Futuro")) -> Futuro | BF44: =IF(BE44="futuro","no","si") -> no | BG44: =IF(AL44=0,"V","C") -> V | BH44: =IF(BE44="futuro","",CONCATENATE(BG44,LEFT(BE44,1))) | BI44: =$BB44*(1+BI$2) -> 287.22922 | BJ44: =$BB44*(1+BJ$2) -> 328.26196 | BK44: =$BB44*(1+BK$2) -> 369.29471 | BL44: =$BB44*(1+BL$2) -> 410.32745 | BM44: =$BB44*(1+BM$2) -> 451.3602 | BN44: =$BB44*(1+BN$2) -> 492.39294 | BO44: =$BB44*(1+BO$2) -> 533.42569 | BP44: =IF($BE44="futuro",-($BL44-BI44)*$BD44,0) -> 50253.624 | BQ44: =IF($BE44="futuro",-($BL44-BJ44)*$BD44,0) -> 33502.416 | BR44: =IF($BE44="futuro",-($BL44-BK44)*$BD44,0) -> 16751.208 | BS44: =IF($BE44="futuro",-($BL44-BL44)*$BD44,0) -> 0 | BT44: =IF($BE44="futuro",-($BL44-BM44)*$BD44,0) -> -16751.208 | BU44: =IF($BE44="futuro",-($BL44-BN44)*$BD44,0) -> -33502.416 | BV44: =IF($BE44="futuro",-($BL44-BO44)*$BD44,0) -> -50253.624 | BW44: =IF(AND($BH44="CC",($BC44-BI44)<0),(BI44-$BC44)*$BD44, IF(AND($BH44="VC",($BC44-BI44)<0),($BC44-BI44)*-$BD44, IF(AND($BH44="CP",($BC44-BI44)>0),(BI44-$BC44)*$BD44*-1, IF(AND($BH44="VP",($BC44-BI44)>0),(BI44-$BC44)*$BD44*-1,0)))) -> 0 | BX44: =IF(AND($BH44="CC",($BC44-BJ44)<0),(BJ44-$BC44)*$BD44, IF(AND($BH44="VC",($BC44-BJ44)<0),($BC44-BJ44)*-$BD44, IF(AND($BH44="CP",($BC44-BJ44)>0),(BJ44-$BC44)*$BD44*-1, IF(AND($BH44="VP",($BC44-BJ44)>0),(BJ44-$BC44)*$BD44*-1,0)))) -> 0 | BY44: =IF(AND($BH44="CC",($BC44-BK44)<0),(BK44-$BC44)*$BD44, IF(AND($BH44="VC",($BC44-BK44)<0),($BC44-BK44)*-$BD44, IF(AND($BH44="CP",($BC44-BK44)>0),(BK44-$BC44)*$BD44*-1, IF(AND($BH44="VP",($BC44-BK44)>0),(BK44-$BC44)*$BD44*-1,0)))) -> 0 | BZ44: =IF(AND($BH44="CC",($BC44-BL44)<0),(BL44-$BC44)*$BD44, IF(AND($BH44="VC",($BC44-BL44)<0),($BC44-BL44)*-$BD44, IF(AND($BH44="CP",($BC44-BL44)>0),(BL44-$BC44)*$BD44*-1, IF(AND($BH44="VP",($BC44-BL44)>0),(BL44-$BC44)*$BD44*-1,0)))) -> 0 | CA44: =IF(AND($BH44="CC",($BC44-BM44)<0),(BM44-$BC44)*$BD44, IF(AND($BH44="VC",($BC44-BM44)<0),($BC44-BM44)*-$BD44, IF(AND($BH44="CP",($BC44-BM44)>0),(BM44-$BC44)*$BD44*-1, IF(AND($BH44="VP",($BC44-BM44)>0),(BM44-$BC44)*$BD44*-1,0)))) -> 0 | CB44: =IF(AND($BH44="CC",($BC44-BN44)<0),(BN44-$BC44)*$BD44, IF(AND($BH44="VC",($BC44-BN44)<0),($BC44-BN44)*-$BD44, IF(AND($BH44="CP",($BC44-BN44)>0),(BN44-$BC44)*$BD44*-1, IF(AND($BH44="VP",($BC44-BN44)>0),(BN44-$BC44)*$BD44*-1,0)))) -> 0 | CC44: =IF(AND($BH44="CC",($BC44-BO44)<0),(BO44-$BC44)*$BD44, IF(AND($BH44="VC",($BC44-BO44)<0),($BC44-BO44)*-$BD44, IF(AND($BH44="CP",($BC44-BO44)>0),(BO44-$BC44)*$BD44*-1, IF(AND($BH44="VP",($BC44-BO44)>0),(BO44-$BC44)*$BD44*-1,0)))) -> 0 | CD44: =IF(AND($BH44="CC",($BC44-BI44)<0),$BD44*1, IF(AND($BH44="VC",($BC44-BI44)<0),$BD44*1, IF(AND($BH44="CP",($BC44-BI44)>0),$BD44*-1, IF(AND($BH44="VP",($BC44-BI44)>0),$BD44*-1,0)))) -> 0 | CE44: =IF(AND($BH44="CC",($BC44-BJ44)<0),$BD44*1, IF(AND($BH44="VC",($BC44-BJ44)<0),$BD44*1, IF(AND($BH44="CP",($BC44-BJ44)>0),$BD44*-1, IF(AND($BH44="VP",($BC44-BJ44)>0),$BD44*-1,0)))) -> 0 | CF44: =IF(AND($BH44="CC",($BC44-BK44)<0),$BD44*1, IF(AND($BH44="VC",($BC44-BK44)<0),$BD44*1, IF(AND($BH44="CP",($BC44-BK44)>0),$BD44*-1, IF(AND($BH44="VP",($BC44-BK44)>0),$BD44*-1,0)))) -> 0 | CG44: =IF(AND($BH44="CC",($BC44-BL44)<0),$BD44*1, IF(AND($BH44="VC",($BC44-BL44)<0),$BD44*1, IF(AND($BH44="CP",($BC44-BL44)>0),$BD44*-1, IF(AND($BH44="VP",($BC44-BL44)>0),$BD44*-1,0)))) -> 0 | CH44: =IF(AND($BH44="CC",($BC44-BM44)<0),$BD44*1, IF(AND($BH44="VC",($BC44-BM44)<0),$BD44*1, IF(AND($BH44="CP",($BC44-BM44)>0),$BD44*-1, IF(AND($BH44="VP",($BC44-BM44)>0),$BD44*-1,0)))) -> 0 | CI44: =IF(AND($BH44="CC",($BC44-BN44)<0),$BD44*1, IF(AND($BH44="VC",($BC44-BN44)<0),$BD44*1, IF(AND($BH44="CP",($BC44-BN44)>0),$BD44*-1, IF(AND($BH44="VP",($BC44-BN44)>0),$BD44*-1,0)))) -> 0 | CJ44: =IF(AND($BH44="CC",($BC44-BO44)<0),$BD44*1, IF(AND($BH44="VC",($BC44-BO44)<0),$BD44*1, IF(AND($BH44="CP",($BC44-BO44)>0),$BD44*-1, IF(AND($BH44="VP",($BC44-BO44)>0),$BD44*-1,0)))) -> 0 | CK44: =Tabla3[[#This Row],[Tns]] -> -408.24 | CL44: =IF(ISERROR(VLOOKUP(VALUE(E44),'Clientes CBOT'!A:A,1,0)),"VER","ok") -> ok
A45: P | B45: R | C45: 766 | D45: 0 | E45: 20176 | F45: C | H45: F1 | I45: .AS-0000026E | J45: 3449 | K45: 2 | L45: 150000 | M45: MAY 26 SOYBEANS | N45: 11.33 | O45: 20251104 | Q45: 202605 | S45: F | U45: 0 | V45: 0 | X45: FYO ACOPIO SA | Z45: 20251104 | AA45: 1 | AB45: 1A | AC45: S- | AF45: 11.33000000 | AL45: 0 | AM45: 15.0000 | AN45: USD | AO45: 1218750 | AP45: 1116750000 | AQ45: 0 | AR45: 50000 | AS45: 5K04 J560 | AT45: 116173449 | AU45: 0,0000 | AV45: S | AW45: CBT | AX45: Comdty | AY45: Soja | AZ45: =IF(VLOOKUP(AY45,Conversor!B:C,2,0)="HS",0.01,VLOOKUP(AY45,Conversor!B:C,2,0)) -> 0.36743 | BA45: =IF(BG45="v",-AM45/10000,AL45/10000) -> -15 | BB45: =IF(AQ45=0,AP45/1000000*AZ45,AQ45/1000000*AZ45) -> 410.32745 | BC45: =U45/1000000*AZ45 -> 0 | BD45: =IF(OR(E45="FUTUR",E45="f20176"),0,VLOOKUP(AY45,Conversor!G:I,3,0)*BA45) -> -2041.2 | BE45: =IF(LEFT(M45,4)="call","Call",IF(LEFT(M45,3)="put","Put","Futuro")) -> Futuro | BF45: =IF(BE45="futuro","no","si") -> no | BG45: =IF(AL45=0,"V","C") -> V | BH45: =IF(BE45="futuro","",CONCATENATE(BG45,LEFT(BE45,1))) | BI45: =$BB45*(1+BI$2) -> 287.22922 | BJ45: =$BB45*(1+BJ$2) -> 328.26196 | BK45: =$BB45*(1+BK$2) -> 369.29471 | BL45: =$BB45*(1+BL$2) -> 410.32745 | BM45: =$BB45*(1+BM$2) -> 451.3602 | BN45: =$BB45*(1+BN$2) -> 492.39294 | BO45: =$BB45*(1+BO$2) -> 533.42569 | BP45: =IF($BE45="futuro",-($BL45-BI45)*$BD45,0) -> 251268.12 | BQ45: =IF($BE45="futuro",-($BL45-BJ45)*$BD45,0) -> 167512.08 | BR45: =IF($BE45="futuro",-($BL45-BK45)*$BD45,0) -> 83756.04 | BS45: =IF($BE45="futuro",-($BL45-BL45)*$BD45,0) -> 0 | BT45: =IF($BE45="futuro",-($BL45-BM45)*$BD45,0) -> -83756.04 | BU45: =IF($BE45="futuro",-($BL45-BN45)*$BD45,0) -> -167512.08 | BV45: =IF($BE45="futuro",-($BL45-BO45)*$BD45,0) -> -251268.12 | BW45: =IF(AND($BH45="CC",($BC45-BI45)<0),(BI45-$BC45)*$BD45, IF(AND($BH45="VC",($BC45-BI45)<0),($BC45-BI45)*-$BD45, IF(AND($BH45="CP",($BC45-BI45)>0),(BI45-$BC45)*$BD45*-1, IF(AND($BH45="VP",($BC45-BI45)>0),(BI45-$BC45)*$BD45*-1,0)))) -> 0 | BX45: =IF(AND($BH45="CC",($BC45-BJ45)<0),(BJ45-$BC45)*$BD45, IF(AND($BH45="VC",($BC45-BJ45)<0),($BC45-BJ45)*-$BD45, IF(AND($BH45="CP",($BC45-BJ45)>0),(BJ45-$BC45)*$BD45*-1, IF(AND($BH45="VP",($BC45-BJ45)>0),(BJ45-$BC45)*$BD45*-1,0)))) -> 0 | BY45: =IF(AND($BH45="CC",($BC45-BK45)<0),(BK45-$BC45)*$BD45, IF(AND($BH45="VC",($BC45-BK45)<0),($BC45-BK45)*-$BD45, IF(AND($BH45="CP",($BC45-BK45)>0),(BK45-$BC45)*$BD45*-1, IF(AND($BH45="VP",($BC45-BK45)>0),(BK45-$BC45)*$BD45*-1,0)))) -> 0 | BZ45: =IF(AND($BH45="CC",($BC45-BL45)<0),(BL45-$BC45)*$BD45, IF(AND($BH45="VC",($BC45-BL45)<0),($BC45-BL45)*-$BD45, IF(AND($BH45="CP",($BC45-BL45)>0),(BL45-$BC45)*$BD45*-1, IF(AND($BH45="VP",($BC45-BL45)>0),(BL45-$BC45)*$BD45*-1,0)))) -> 0 | CA45: =IF(AND($BH45="CC",($BC45-BM45)<0),(BM45-$BC45)*$BD45, IF(AND($BH45="VC",($BC45-BM45)<0),($BC45-BM45)*-$BD45, IF(AND($BH45="CP",($BC45-BM45)>0),(BM45-$BC45)*$BD45*-1, IF(AND($BH45="VP",($BC45-BM45)>0),(BM45-$BC45)*$BD45*-1,0)))) -> 0 | CB45: =IF(AND($BH45="CC",($BC45-BN45)<0),(BN45-$BC45)*$BD45, IF(AND($BH45="VC",($BC45-BN45)<0),($BC45-BN45)*-$BD45, IF(AND($BH45="CP",($BC45-BN45)>0),(BN45-$BC45)*$BD45*-1, IF(AND($BH45="VP",($BC45-BN45)>0),(BN45-$BC45)*$BD45*-1,0)))) -> 0 | CC45: =IF(AND($BH45="CC",($BC45-BO45)<0),(BO45-$BC45)*$BD45, IF(AND($BH45="VC",($BC45-BO45)<0),($BC45-BO45)*-$BD45, IF(AND($BH45="CP",($BC45-BO45)>0),(BO45-$BC45)*$BD45*-1, IF(AND($BH45="VP",($BC45-BO45)>0),(BO45-$BC45)*$BD45*-1,0)))) -> 0 | CD45: =IF(AND($BH45="CC",($BC45-BI45)<0),$BD45*1, IF(AND($BH45="VC",($BC45-BI45)<0),$BD45*1, IF(AND($BH45="CP",($BC45-BI45)>0),$BD45*-1, IF(AND($BH45="VP",($BC45-BI45)>0),$BD45*-1,0)))) -> 0 | CE45: =IF(AND($BH45="CC",($BC45-BJ45)<0),$BD45*1, IF(AND($BH45="VC",($BC45-BJ45)<0),$BD45*1, IF(AND($BH45="CP",($BC45-BJ45)>0),$BD45*-1, IF(AND($BH45="VP",($BC45-BJ45)>0),$BD45*-1,0)))) -> 0 | CF45: =IF(AND($BH45="CC",($BC45-BK45)<0),$BD45*1, IF(AND($BH45="VC",($BC45-BK45)<0),$BD45*1, IF(AND($BH45="CP",($BC45-BK45)>0),$BD45*-1, IF(AND($BH45="VP",($BC45-BK45)>0),$BD45*-1,0)))) -> 0 | CG45: =IF(AND($BH45="CC",($BC45-BL45)<0),$BD45*1, IF(AND($BH45="VC",($BC45-BL45)<0),$BD45*1, IF(AND($BH45="CP",($BC45-BL45)>0),$BD45*-1, IF(AND($BH45="VP",($BC45-BL45)>0),$BD45*-1,0)))) -> 0 | CH45: =IF(AND($BH45="CC",($BC45-BM45)<0),$BD45*1, IF(AND($BH45="VC",($BC45-BM45)<0),$BD45*1, IF(AND($BH45="CP",($BC45-BM45)>0),$BD45*-1, IF(AND($BH45="VP",($BC45-BM45)>0),$BD45*-1,0)))) -> 0 | CI45: =IF(AND($BH45="CC",($BC45-BN45)<0),$BD45*1, IF(AND($BH45="VC",($BC45-BN45)<0),$BD45*1, IF(AND($BH45="CP",($BC45-BN45)>0),$BD45*-1, IF(AND($BH45="VP",($BC45-BN45)>0),$BD45*-1,0)))) -> 0 | CJ45: =IF(AND($BH45="CC",($BC45-BO45)<0),$BD45*1, IF(AND($BH45="VC",($BC45-BO45)<0),$BD45*1, IF(AND($BH45="CP",($BC45-BO45)>0),$BD45*-1, IF(AND($BH45="VP",($BC45-BO45)>0),$BD45*-1,0)))) -> 0 | CK45: =Tabla3[[#This Row],[Tns]] -> -2041.2 | CL45: =IF(ISERROR(VLOOKUP(VALUE(E45),'Clientes CBOT'!A:A,1,0)),"VER","ok") -> ok
A46: P | B46: R | C46: 766 | D46: 0 | E46: 20176 | F46: C | H46: F1 | I46: .AS-0000026E | J46: 3862 | K46: 2 | L46: 370000 | M46: MAY 26 SOYBEANS | N46: 11.71 | O46: 20251117 | Q46: 202605 | S46: F | U46: 0 | V46: 0 | X46: FYO ACOPIO SA | Z46: 20251117 | AA46: 1 | AB46: 1A | AC46: S- | AF46: 11.71000000 | AL46: 0 | AM46: 37.0000 | AN46: USD | AO46: 10036250 | AP46: 1116750000 | AQ46: 0 | AR46: 50000 | AS46: 5K17 FFT0 | AT46: 116283862 | AU46: 0,0000 | AV46: S | AW46: CBT | AX46: Comdty | AY46: Soja | AZ46: =IF(VLOOKUP(AY46,Conversor!B:C,2,0)="HS",0.01,VLOOKUP(AY46,Conversor!B:C,2,0)) -> 0.36743 | BA46: =IF(BG46="v",-AM46/10000,AL46/10000) -> -37 | BB46: =IF(AQ46=0,AP46/1000000*AZ46,AQ46/1000000*AZ46) -> 410.32745 | BC46: =U46/1000000*AZ46 -> 0 | BD46: =IF(OR(E46="FUTUR",E46="f20176"),0,VLOOKUP(AY46,Conversor!G:I,3,0)*BA46) -> -5034.96 | BE46: =IF(LEFT(M46,4)="call","Call",IF(LEFT(M46,3)="put","Put","Futuro")) -> Futuro | BF46: =IF(BE46="futuro","no","si") -> no | BG46: =IF(AL46=0,"V","C") -> V | BH46: =IF(BE46="futuro","",CONCATENATE(BG46,LEFT(BE46,1))) | BI46: =$BB46*(1+BI$2) -> 287.22922 | BJ46: =$BB46*(1+BJ$2) -> 328.26196 | BK46: =$BB46*(1+BK$2) -> 369.29471 | BL46: =$BB46*(1+BL$2) -> 410.32745 | BM46: =$BB46*(1+BM$2) -> 451.3602 | BN46: =$BB46*(1+BN$2) -> 492.39294 | BO46: =$BB46*(1+BO$2) -> 533.42569 | BP46: =IF($BE46="futuro",-($BL46-BI46)*$BD46,0) -> 619794.69 | BQ46: =IF($BE46="futuro",-($BL46-BJ46)*$BD46,0) -> 413196.46 | BR46: =IF($BE46="futuro",-($BL46-BK46)*$BD46,0) -> 206598.23 | BS46: =IF($BE46="futuro",-($BL46-BL46)*$BD46,0) -> 0 | BT46: =IF($BE46="futuro",-($BL46-BM46)*$BD46,0) -> -206598.23 | BU46: =IF($BE46="futuro",-($BL46-BN46)*$BD46,0) -> -413196.46 | BV46: =IF($BE46="futuro",-($BL46-BO46)*$BD46,0) -> -619794.69 | BW46: =IF(AND($BH46="CC",($BC46-BI46)<0),(BI46-$BC46)*$BD46, IF(AND($BH46="VC",($BC46-BI46)<0),($BC46-BI46)*-$BD46, IF(AND($BH46="CP",($BC46-BI46)>0),(BI46-$BC46)*$BD46*-1, IF(AND($BH46="VP",($BC46-BI46)>0),(BI46-$BC46)*$BD46*-1,0)))) -> 0 | BX46: =IF(AND($BH46="CC",($BC46-BJ46)<0),(BJ46-$BC46)*$BD46, IF(AND($BH46="VC",($BC46-BJ46)<0),($BC46-BJ46)*-$BD46, IF(AND($BH46="CP",($BC46-BJ46)>0),(BJ46-$BC46)*$BD46*-1, IF(AND($BH46="VP",($BC46-BJ46)>0),(BJ46-$BC46)*$BD46*-1,0)))) -> 0 | BY46: =IF(AND($BH46="CC",($BC46-BK46)<0),(BK46-$BC46)*$BD46, IF(AND($BH46="VC",($BC46-BK46)<0),($BC46-BK46)*-$BD46, IF(AND($BH46="CP",($BC46-BK46)>0),(BK46-$BC46)*$BD46*-1, IF(AND($BH46="VP",($BC46-BK46)>0),(BK46-$BC46)*$BD46*-1,0)))) -> 0 | BZ46: =IF(AND($BH46="CC",($BC46-BL46)<0),(BL46-$BC46)*$BD46, IF(AND($BH46="VC",($BC46-BL46)<0),($BC46-BL46)*-$BD46, IF(AND($BH46="CP",($BC46-BL46)>0),(BL46-$BC46)*$BD46*-1, IF(AND($BH46="VP",($BC46-BL46)>0),(BL46-$BC46)*$BD46*-1,0)))) -> 0 | CA46: =IF(AND($BH46="CC",($BC46-BM46)<0),(BM46-$BC46)*$BD46, IF(AND($BH46="VC",($BC46-BM46)<0),($BC46-BM46)*-$BD46, IF(AND($BH46="CP",($BC46-BM46)>0),(BM46-$BC46)*$BD46*-1, IF(AND($BH46="VP",($BC46-BM46)>0),(BM46-$BC46)*$BD46*-1,0)))) -> 0 | CB46: =IF(AND($BH46="CC",($BC46-BN46)<0),(BN46-$BC46)*$BD46, IF(AND($BH46="VC",($BC46-BN46)<0),($BC46-BN46)*-$BD46, IF(AND($BH46="CP",($BC46-BN46)>0),(BN46-$BC46)*$BD46*-1, IF(AND($BH46="VP",($BC46-BN46)>0),(BN46-$BC46)*$BD46*-1,0)))) -> 0 | CC46: =IF(AND($BH46="CC",($BC46-BO46)<0),(BO46-$BC46)*$BD46, IF(AND($BH46="VC",($BC46-BO46)<0),($BC46-BO46)*-$BD46, IF(AND($BH46="CP",($BC46-BO46)>0),(BO46-$BC46)*$BD46*-1, IF(AND($BH46="VP",($BC46-BO46)>0),(BO46-$BC46)*$BD46*-1,0)))) -> 0 | CD46: =IF(AND($BH46="CC",($BC46-BI46)<0),$BD46*1, IF(AND($BH46="VC",($BC46-BI46)<0),$BD46*1, IF(AND($BH46="CP",($BC46-BI46)>0),$BD46*-1, IF(AND($BH46="VP",($BC46-BI46)>0),$BD46*-1,0)))) -> 0 | CE46: =IF(AND($BH46="CC",($BC46-BJ46)<0),$BD46*1, IF(AND($BH46="VC",($BC46-BJ46)<0),$BD46*1, IF(AND($BH46="CP",($BC46-BJ46)>0),$BD46*-1, IF(AND($BH46="VP",($BC46-BJ46)>0),$BD46*-1,0)))) -> 0 | CF46: =IF(AND($BH46="CC",($BC46-BK46)<0),$BD46*1, IF(AND($BH46="VC",($BC46-BK46)<0),$BD46*1, IF(AND($BH46="CP",($BC46-BK46)>0),$BD46*-1, IF(AND($BH46="VP",($BC46-BK46)>0),$BD46*-1,0)))) -> 0 | CG46: =IF(AND($BH46="CC",($BC46-BL46)<0),$BD46*1, IF(AND($BH46="VC",($BC46-BL46)<0),$BD46*1, IF(AND($BH46="CP",($BC46-BL46)>0),$BD46*-1, IF(AND($BH46="VP",($BC46-BL46)>0),$BD46*-1,0)))) -> 0 | CH46: =IF(AND($BH46="CC",($BC46-BM46)<0),$BD46*1, IF(AND($BH46="VC",($BC46-BM46)<0),$BD46*1, IF(AND($BH46="CP",($BC46-BM46)>0),$BD46*-1, IF(AND($BH46="VP",($BC46-BM46)>0),$BD46*-1,0)))) -> 0 | CI46: =IF(AND($BH46="CC",($BC46-BN46)<0),$BD46*1, IF(AND($BH46="VC",($BC46-BN46)<0),$BD46*1, IF(AND($BH46="CP",($BC46-BN46)>0),$BD46*-1, IF(AND($BH46="VP",($BC46-BN46)>0),$BD46*-1,0)))) -> 0 | CJ46: =IF(AND($BH46="CC",($BC46-BO46)<0),$BD46*1, IF(AND($BH46="VC",($BC46-BO46)<0),$BD46*1, IF(AND($BH46="CP",($BC46-BO46)>0),$BD46*-1, IF(AND($BH46="VP",($BC46-BO46)>0),$BD46*-1,0)))) -> 0 | CK46: =Tabla3[[#This Row],[Tns]] -> -5034.96 | CL46: =IF(ISERROR(VLOOKUP(VALUE(E46),'Clientes CBOT'!A:A,1,0)),"VER","ok") -> ok
A47: P | B47: R | C47: 766 | D47: 0 | E47: 20176 | F47: C | H47: F1 | I47: .AS-0000026E | J47: 6895 | K47: 2 | L47: 150000 | M47: MAY 26 SOYBEANS | N47: 11.68 | O47: 20251118 | Q47: 202605 | S47: F | U47: 0 | V47: 0 | X47: FYO ACOPIO SA | Z47: 20251118 | AA47: 1 | AB47: 1A | AC47: S- | AF47: 11.68000000 | AL47: 0 | AM47: 15.0000 | AN47: USD | AO47: 3843750 | AP47: 1116750000 | AQ47: 0 | AR47: 50000 | AS47: 5K18 P410 | AT47: 116296895 | AU47: 0,0000 | AV47: S | AW47: CBT | AX47: Comdty | AY47: Soja | AZ47: =IF(VLOOKUP(AY47,Conversor!B:C,2,0)="HS",0.01,VLOOKUP(AY47,Conversor!B:C,2,0)) -> 0.36743 | BA47: =IF(BG47="v",-AM47/10000,AL47/10000) -> -15 | BB47: =IF(AQ47=0,AP47/1000000*AZ47,AQ47/1000000*AZ47) -> 410.32745 | BC47: =U47/1000000*AZ47 -> 0 | BD47: =IF(OR(E47="FUTUR",E47="f20176"),0,VLOOKUP(AY47,Conversor!G:I,3,0)*BA47) -> -2041.2 | BE47: =IF(LEFT(M47,4)="call","Call",IF(LEFT(M47,3)="put","Put","Futuro")) -> Futuro | BF47: =IF(BE47="futuro","no","si") -> no | BG47: =IF(AL47=0,"V","C") -> V | BH47: =IF(BE47="futuro","",CONCATENATE(BG47,LEFT(BE47,1))) | BI47: =$BB47*(1+BI$2) -> 287.22922 | BJ47: =$BB47*(1+BJ$2) -> 328.26196 | BK47: =$BB47*(1+BK$2) -> 369.29471 | BL47: =$BB47*(1+BL$2) -> 410.32745 | BM47: =$BB47*(1+BM$2) -> 451.3602 | BN47: =$BB47*(1+BN$2) -> 492.39294 | BO47: =$BB47*(1+BO$2) -> 533.42569 | BP47: =IF($BE47="futuro",-($BL47-BI47)*$BD47,0) -> 251268.12 | BQ47: =IF($BE47="futuro",-($BL47-BJ47)*$BD47,0) -> 167512.08 | BR47: =IF($BE47="futuro",-($BL47-BK47)*$BD47,0) -> 83756.04 | BS47: =IF($BE47="futuro",-($BL47-BL47)*$BD47,0) -> 0 | BT47: =IF($BE47="futuro",-($BL47-BM47)*$BD47,0) -> -83756.04 | BU47: =IF($BE47="futuro",-($BL47-BN47)*$BD47,0) -> -167512.08 | BV47: =IF($BE47="futuro",-($BL47-BO47)*$BD47,0) -> -251268.12 | BW47: =IF(AND($BH47="CC",($BC47-BI47)<0),(BI47-$BC47)*$BD47, IF(AND($BH47="VC",($BC47-BI47)<0),($BC47-BI47)*-$BD47, IF(AND($BH47="CP",($BC47-BI47)>0),(BI47-$BC47)*$BD47*-1, IF(AND($BH47="VP",($BC47-BI47)>0),(BI47-$BC47)*$BD47*-1,0)))) -> 0 | BX47: =IF(AND($BH47="CC",($BC47-BJ47)<0),(BJ47-$BC47)*$BD47, IF(AND($BH47="VC",($BC47-BJ47)<0),($BC47-BJ47)*-$BD47, IF(AND($BH47="CP",($BC47-BJ47)>0),(BJ47-$BC47)*$BD47*-1, IF(AND($BH47="VP",($BC47-BJ47)>0),(BJ47-$BC47)*$BD47*-1,0)))) -> 0 | BY47: =IF(AND($BH47="CC",($BC47-BK47)<0),(BK47-$BC47)*$BD47, IF(AND($BH47="VC",($BC47-BK47)<0),($BC47-BK47)*-$BD47, IF(AND($BH47="CP",($BC47-BK47)>0),(BK47-$BC47)*$BD47*-1, IF(AND($BH47="VP",($BC47-BK47)>0),(BK47-$BC47)*$BD47*-1,0)))) -> 0 | BZ47: =IF(AND($BH47="CC",($BC47-BL47)<0),(BL47-$BC47)*$BD47, IF(AND($BH47="VC",($BC47-BL47)<0),($BC47-BL47)*-$BD47, IF(AND($BH47="CP",($BC47-BL47)>0),(BL47-$BC47)*$BD47*-1, IF(AND($BH47="VP",($BC47-BL47)>0),(BL47-$BC47)*$BD47*-1,0)))) -> 0 | CA47: =IF(AND($BH47="CC",($BC47-BM47)<0),(BM47-$BC47)*$BD47, IF(AND($BH47="VC",($BC47-BM47)<0),($BC47-BM47)*-$BD47, IF(AND($BH47="CP",($BC47-BM47)>0),(BM47-$BC47)*$BD47*-1, IF(AND($BH47="VP",($BC47-BM47)>0),(BM47-$BC47)*$BD47*-1,0)))) -> 0 | CB47: =IF(AND($BH47="CC",($BC47-BN47)<0),(BN47-$BC47)*$BD47, IF(AND($BH47="VC",($BC47-BN47)<0),($BC47-BN47)*-$BD47, IF(AND($BH47="CP",($BC47-BN47)>0),(BN47-$BC47)*$BD47*-1, IF(AND($BH47="VP",($BC47-BN47)>0),(BN47-$BC47)*$BD47*-1,0)))) -> 0 | CC47: =IF(AND($BH47="CC",($BC47-BO47)<0),(BO47-$BC47)*$BD47, IF(AND($BH47="VC",($BC47-BO47)<0),($BC47-BO47)*-$BD47, IF(AND($BH47="CP",($BC47-BO47)>0),(BO47-$BC47)*$BD47*-1, IF(AND($BH47="VP",($BC47-BO47)>0),(BO47-$BC47)*$BD47*-1,0)))) -> 0 | CD47: =IF(AND($BH47="CC",($BC47-BI47)<0),$BD47*1, IF(AND($BH47="VC",($BC47-BI47)<0),$BD47*1, IF(AND($BH47="CP",($BC47-BI47)>0),$BD47*-1, IF(AND($BH47="VP",($BC47-BI47)>0),$BD47*-1,0)))) -> 0 | CE47: =IF(AND($BH47="CC",($BC47-BJ47)<0),$BD47*1, IF(AND($BH47="VC",($BC47-BJ47)<0),$BD47*1, IF(AND($BH47="CP",($BC47-BJ47)>0),$BD47*-1, IF(AND($BH47="VP",($BC47-BJ47)>0),$BD47*-1,0)))) -> 0 | CF47: =IF(AND($BH47="CC",($BC47-BK47)<0),$BD47*1, IF(AND($BH47="VC",($BC47-BK47)<0),$BD47*1, IF(AND($BH47="CP",($BC47-BK47)>0),$BD47*-1, IF(AND($BH47="VP",($BC47-BK47)>0),$BD47*-1,0)))) -> 0 | CG47: =IF(AND($BH47="CC",($BC47-BL47)<0),$BD47*1, IF(AND($BH47="VC",($BC47-BL47)<0),$BD47*1, IF(AND($BH47="CP",($BC47-BL47)>0),$BD47*-1, IF(AND($BH47="VP",($BC47-BL47)>0),$BD47*-1,0)))) -> 0 | CH47: =IF(AND($BH47="CC",($BC47-BM47)<0),$BD47*1, IF(AND($BH47="VC",($BC47-BM47)<0),$BD47*1, IF(AND($BH47="CP",($BC47-BM47)>0),$BD47*-1, IF(AND($BH47="VP",($BC47-BM47)>0),$BD47*-1,0)))) -> 0 | CI47: =IF(AND($BH47="CC",($BC47-BN47)<0),$BD47*1, IF(AND($BH47="VC",($BC47-BN47)<0),$BD47*1, IF(AND($BH47="CP",($BC47-BN47)>0),$BD47*-1, IF(AND($BH47="VP",($BC47-BN47)>0),$BD47*-1,0)))) -> 0 | CJ47: =IF(AND($BH47="CC",($BC47-BO47)<0),$BD47*1, IF(AND($BH47="VC",($BC47-BO47)<0),$BD47*1, IF(AND($BH47="CP",($BC47-BO47)>0),$BD47*-1, IF(AND($BH47="VP",($BC47-BO47)>0),$BD47*-1,0)))) -> 0 | CK47: =Tabla3[[#This Row],[Tns]] -> -2041.2 | CL47: =IF(ISERROR(VLOOKUP(VALUE(E47),'Clientes CBOT'!A:A,1,0)),"VER","ok") -> ok
A48: P | B48: R | C48: 766 | D48: 0 | E48: 20176 | F48: C | H48: F1 | I48: .AS-0000026G | J48: 7940 | K48: 2 | L48: 220000 | M48: JUL 26 SOYBEANS | N48: 11.38 | O48: 20251106 | Q48: 202607 | S48: F | U48: 0 | V48: 0 | X48: FYO ACOPIO SA | Z48: 20251106 | AA48: 1 | AB48: 1A | AC48: S- | AF48: 11.38000000 | AL48: 0 | AM48: 22.0000 | AN48: USD | AO48: 1347500 | AP48: 1125750000 | AQ48: 0 | AR48: 50000 | AS48: 5K06 L5D0 | AT48: 116197940 | AU48: 0,0000 | AV48: S | AW48: CBT | AX48: Comdty | AY48: Soja | AZ48: =IF(VLOOKUP(AY48,Conversor!B:C,2,0)="HS",0.01,VLOOKUP(AY48,Conversor!B:C,2,0)) -> 0.36743 | BA48: =IF(BG48="v",-AM48/10000,AL48/10000) -> -22 | BB48: =IF(AQ48=0,AP48/1000000*AZ48,AQ48/1000000*AZ48) -> 413.63432 | BC48: =U48/1000000*AZ48 -> 0 | BD48: =IF(OR(E48="FUTUR",E48="f20176"),0,VLOOKUP(AY48,Conversor!G:I,3,0)*BA48) -> -2993.76 | BE48: =IF(LEFT(M48,4)="call","Call",IF(LEFT(M48,3)="put","Put","Futuro")) -> Futuro | BF48: =IF(BE48="futuro","no","si") -> no | BG48: =IF(AL48=0,"V","C") -> V | BH48: =IF(BE48="futuro","",CONCATENATE(BG48,LEFT(BE48,1))) | BI48: =$BB48*(1+BI$2) -> 289.54403 | BJ48: =$BB48*(1+BJ$2) -> 330.90746 | BK48: =$BB48*(1+BK$2) -> 372.27089 | BL48: =$BB48*(1+BL$2) -> 413.63432 | BM48: =$BB48*(1+BM$2) -> 454.99775 | BN48: =$BB48*(1+BN$2) -> 496.36119 | BO48: =$BB48*(1+BO$2) -> 537.72462 | BP48: =IF($BE48="futuro",-($BL48-BI48)*$BD48,0) -> 371496.57 | BQ48: =IF($BE48="futuro",-($BL48-BJ48)*$BD48,0) -> 247664.38 | BR48: =IF($BE48="futuro",-($BL48-BK48)*$BD48,0) -> 123832.19 | BS48: =IF($BE48="futuro",-($BL48-BL48)*$BD48,0) -> 0 | BT48: =IF($BE48="futuro",-($BL48-BM48)*$BD48,0) -> -123832.19 | BU48: =IF($BE48="futuro",-($BL48-BN48)*$BD48,0) -> -247664.38 | BV48: =IF($BE48="futuro",-($BL48-BO48)*$BD48,0) -> -371496.57 | BW48: =IF(AND($BH48="CC",($BC48-BI48)<0),(BI48-$BC48)*$BD48, IF(AND($BH48="VC",($BC48-BI48)<0),($BC48-BI48)*-$BD48, IF(AND($BH48="CP",($BC48-BI48)>0),(BI48-$BC48)*$BD48*-1, IF(AND($BH48="VP",($BC48-BI48)>0),(BI48-$BC48)*$BD48*-1,0)))) -> 0 | BX48: =IF(AND($BH48="CC",($BC48-BJ48)<0),(BJ48-$BC48)*$BD48, IF(AND($BH48="VC",($BC48-BJ48)<0),($BC48-BJ48)*-$BD48, IF(AND($BH48="CP",($BC48-BJ48)>0),(BJ48-$BC48)*$BD48*-1, IF(AND($BH48="VP",($BC48-BJ48)>0),(BJ48-$BC48)*$BD48*-1,0)))) -> 0 | BY48: =IF(AND($BH48="CC",($BC48-BK48)<0),(BK48-$BC48)*$BD48, IF(AND($BH48="VC",($BC48-BK48)<0),($BC48-BK48)*-$BD48, IF(AND($BH48="CP",($BC48-BK48)>0),(BK48-$BC48)*$BD48*-1, IF(AND($BH48="VP",($BC48-BK48)>0),(BK48-$BC48)*$BD48*-1,0)))) -> 0 | BZ48: =IF(AND($BH48="CC",($BC48-BL48)<0),(BL48-$BC48)*$BD48, IF(AND($BH48="VC",($BC48-BL48)<0),($BC48-BL48)*-$BD48, IF(AND($BH48="CP",($BC48-BL48)>0),(BL48-$BC48)*$BD48*-1, IF(AND($BH48="VP",($BC48-BL48)>0),(BL48-$BC48)*$BD48*-1,0)))) -> 0 | CA48: =IF(AND($BH48="CC",($BC48-BM48)<0),(BM48-$BC48)*$BD48, IF(AND($BH48="VC",($BC48-BM48)<0),($BC48-BM48)*-$BD48, IF(AND($BH48="CP",($BC48-BM48)>0),(BM48-$BC48)*$BD48*-1, IF(AND($BH48="VP",($BC48-BM48)>0),(BM48-$BC48)*$BD48*-1,0)))) -> 0 | CB48: =IF(AND($BH48="CC",($BC48-BN48)<0),(BN48-$BC48)*$BD48, IF(AND($BH48="VC",($BC48-BN48)<0),($BC48-BN48)*-$BD48, IF(AND($BH48="CP",($BC48-BN48)>0),(BN48-$BC48)*$BD48*-1, IF(AND($BH48="VP",($BC48-BN48)>0),(BN48-$BC48)*$BD48*-1,0)))) -> 0 | CC48: =IF(AND($BH48="CC",($BC48-BO48)<0),(BO48-$BC48)*$BD48, IF(AND($BH48="VC",($BC48-BO48)<0),($BC48-BO48)*-$BD48, IF(AND($BH48="CP",($BC48-BO48)>0),(BO48-$BC48)*$BD48*-1, IF(AND($BH48="VP",($BC48-BO48)>0),(BO48-$BC48)*$BD48*-1,0)))) -> 0 | CD48: =IF(AND($BH48="CC",($BC48-BI48)<0),$BD48*1, IF(AND($BH48="VC",($BC48-BI48)<0),$BD48*1, IF(AND($BH48="CP",($BC48-BI48)>0),$BD48*-1, IF(AND($BH48="VP",($BC48-BI48)>0),$BD48*-1,0)))) -> 0 | CE48: =IF(AND($BH48="CC",($BC48-BJ48)<0),$BD48*1, IF(AND($BH48="VC",($BC48-BJ48)<0),$BD48*1, IF(AND($BH48="CP",($BC48-BJ48)>0),$BD48*-1, IF(AND($BH48="VP",($BC48-BJ48)>0),$BD48*-1,0)))) -> 0 | CF48: =IF(AND($BH48="CC",($BC48-BK48)<0),$BD48*1, IF(AND($BH48="VC",($BC48-BK48)<0),$BD48*1, IF(AND($BH48="CP",($BC48-BK48)>0),$BD48*-1, IF(AND($BH48="VP",($BC48-BK48)>0),$BD48*-1,0)))) -> 0 | CG48: =IF(AND($BH48="CC",($BC48-BL48)<0),$BD48*1, IF(AND($BH48="VC",($BC48-BL48)<0),$BD48*1, IF(AND($BH48="CP",($BC48-BL48)>0),$BD48*-1, IF(AND($BH48="VP",($BC48-BL48)>0),$BD48*-1,0)))) -> 0 | CH48: =IF(AND($BH48="CC",($BC48-BM48)<0),$BD48*1, IF(AND($BH48="VC",($BC48-BM48)<0),$BD48*1, IF(AND($BH48="CP",($BC48-BM48)>0),$BD48*-1, IF(AND($BH48="VP",($BC48-BM48)>0),$BD48*-1,0)))) -> 0 | CI48: =IF(AND($BH48="CC",($BC48-BN48)<0),$BD48*1, IF(AND($BH48="VC",($BC48-BN48)<0),$BD48*1, IF(AND($BH48="CP",($BC48-BN48)>0),$BD48*-1, IF(AND($BH48="VP",($BC48-BN48)>0),$BD48*-1,0)))) -> 0 | CJ48: =IF(AND($BH48="CC",($BC48-BO48)<0),$BD48*1, IF(AND($BH48="VC",($BC48-BO48)<0),$BD48*1, IF(AND($BH48="CP",($BC48-BO48)>0),$BD48*-1, IF(AND($BH48="VP",($BC48-BO48)>0),$BD48*-1,0)))) -> 0 | CK48: =Tabla3[[#This Row],[Tns]] -> -2993.76 | CL48: =IF(ISERROR(VLOOKUP(VALUE(E48),'Clientes CBOT'!A:A,1,0)),"VER","ok") -> ok
A49: P | B49: R | C49: 766 | D49: 0 | E49: 20176 | F49: C | H49: F1 | I49: .AW-0000026C | J49: 3585 | K49: 2 | L49: 40000 | M49: MAR 26 WHEAT | N49: 5.40 1/4 | O49: 20251126 | Q49: 202603 | S49: F | U49: 0 | V49: 0 | X49: FYO ACOPIO SA | Z49: 20251126 | AA49: 1 | AB49: 1A | AC49: W- | AF49: 5.40250000 | AL49: 0 | AM49: 4.0000 | AN49: USD | AO49: 110000 | AP49: 534750000 | AQ49: 0 | AR49: 50000 | AS49: 5K26 OWv0 | AT49: 116373585 | AU49: 0,0000 | AV49: W | AW49: CBT | AX49: Comdty | AY49: Trigo | AZ49: =IF(VLOOKUP(AY49,Conversor!B:C,2,0)="HS",0.01,VLOOKUP(AY49,Conversor!B:C,2,0)) -> 0.36743 | BA49: =IF(BG49="v",-AM49/10000,AL49/10000) -> -4 | BB49: =IF(AQ49=0,AP49/1000000*AZ49,AQ49/1000000*AZ49) -> 196.48319 | BC49: =U49/1000000*AZ49 -> 0 | BD49: =IF(OR(E49="FUTUR",E49="f20176"),0,VLOOKUP(AY49,Conversor!G:I,3,0)*BA49) -> -544.32 | BE49: =IF(LEFT(M49,4)="call","Call",IF(LEFT(M49,3)="put","Put","Futuro")) -> Futuro | BF49: =IF(BE49="futuro","no","si") -> no | BG49: =IF(AL49=0,"V","C") -> V | BH49: =IF(BE49="futuro","",CONCATENATE(BG49,LEFT(BE49,1))) | BI49: =$BB49*(1+BI$2) -> 137.53823 | BJ49: =$BB49*(1+BJ$2) -> 157.18655 | BK49: =$BB49*(1+BK$2) -> 176.83487 | BL49: =$BB49*(1+BL$2) -> 196.48319 | BM49: =$BB49*(1+BM$2) -> 216.13151 | BN49: =$BB49*(1+BN$2) -> 235.77983 | BO49: =$BB49*(1+BO$2) -> 255.42815 | BP49: =IF($BE49="futuro",-($BL49-BI49)*$BD49,0) -> 32084.919 | BQ49: =IF($BE49="futuro",-($BL49-BJ49)*$BD49,0) -> 21389.946 | BR49: =IF($BE49="futuro",-($BL49-BK49)*$BD49,0) -> 10694.973 | BS49: =IF($BE49="futuro",-($BL49-BL49)*$BD49,0) -> 0 | BT49: =IF($BE49="futuro",-($BL49-BM49)*$BD49,0) -> -10694.973 | BU49: =IF($BE49="futuro",-($BL49-BN49)*$BD49,0) -> -21389.946 | BV49: =IF($BE49="futuro",-($BL49-BO49)*$BD49,0) -> -32084.919 | BW49: =IF(AND($BH49="CC",($BC49-BI49)<0),(BI49-$BC49)*$BD49, IF(AND($BH49="VC",($BC49-BI49)<0),($BC49-BI49)*-$BD49, IF(AND($BH49="CP",($BC49-BI49)>0),(BI49-$BC49)*$BD49*-1, IF(AND($BH49="VP",($BC49-BI49)>0),(BI49-$BC49)*$BD49*-1,0)))) -> 0 | BX49: =IF(AND($BH49="CC",($BC49-BJ49)<0),(BJ49-$BC49)*$BD49, IF(AND($BH49="VC",($BC49-BJ49)<0),($BC49-BJ49)*-$BD49, IF(AND($BH49="CP",($BC49-BJ49)>0),(BJ49-$BC49)*$BD49*-1, IF(AND($BH49="VP",($BC49-BJ49)>0),(BJ49-$BC49)*$BD49*-1,0)))) -> 0 | BY49: =IF(AND($BH49="CC",($BC49-BK49)<0),(BK49-$BC49)*$BD49, IF(AND($BH49="VC",($BC49-BK49)<0),($BC49-BK49)*-$BD49, IF(AND($BH49="CP",($BC49-BK49)>0),(BK49-$BC49)*$BD49*-1, IF(AND($BH49="VP",($BC49-BK49)>0),(BK49-$BC49)*$BD49*-1,0)))) -> 0 | BZ49: =IF(AND($BH49="CC",($BC49-BL49)<0),(BL49-$BC49)*$BD49, IF(AND($BH49="VC",($BC49-BL49)<0),($BC49-BL49)*-$BD49, IF(AND($BH49="CP",($BC49-BL49)>0),(BL49-$BC49)*$BD49*-1, IF(AND($BH49="VP",($BC49-BL49)>0),(BL49-$BC49)*$BD49*-1,0)))) -> 0 | CA49: =IF(AND($BH49="CC",($BC49-BM49)<0),(BM49-$BC49)*$BD49, IF(AND($BH49="VC",($BC49-BM49)<0),($BC49-BM49)*-$BD49, IF(AND($BH49="CP",($BC49-BM49)>0),(BM49-$BC49)*$BD49*-1, IF(AND($BH49="VP",($BC49-BM49)>0),(BM49-$BC49)*$BD49*-1,0)))) -> 0 | CB49: =IF(AND($BH49="CC",($BC49-BN49)<0),(BN49-$BC49)*$BD49, IF(AND($BH49="VC",($BC49-BN49)<0),($BC49-BN49)*-$BD49, IF(AND($BH49="CP",($BC49-BN49)>0),(BN49-$BC49)*$BD49*-1, IF(AND($BH49="VP",($BC49-BN49)>0),(BN49-$BC49)*$BD49*-1,0)))) -> 0 | CC49: =IF(AND($BH49="CC",($BC49-BO49)<0),(BO49-$BC49)*$BD49, IF(AND($BH49="VC",($BC49-BO49)<0),($BC49-BO49)*-$BD49, IF(AND($BH49="CP",($BC49-BO49)>0),(BO49-$BC49)*$BD49*-1, IF(AND($BH49="VP",($BC49-BO49)>0),(BO49-$BC49)*$BD49*-1,0)))) -> 0 | CD49: =IF(AND($BH49="CC",($BC49-BI49)<0),$BD49*1, IF(AND($BH49="VC",($BC49-BI49)<0),$BD49*1, IF(AND($BH49="CP",($BC49-BI49)>0),$BD49*-1, IF(AND($BH49="VP",($BC49-BI49)>0),$BD49*-1,0)))) -> 0 | CE49: =IF(AND($BH49="CC",($BC49-BJ49)<0),$BD49*1, IF(AND($BH49="VC",($BC49-BJ49)<0),$BD49*1, IF(AND($BH49="CP",($BC49-BJ49)>0),$BD49*-1, IF(AND($BH49="VP",($BC49-BJ49)>0),$BD49*-1,0)))) -> 0 | CF49: =IF(AND($BH49="CC",($BC49-BK49)<0),$BD49*1, IF(AND($BH49="VC",($BC49-BK49)<0),$BD49*1, IF(AND($BH49="CP",($BC49-BK49)>0),$BD49*-1, IF(AND($BH49="VP",($BC49-BK49)>0),$BD49*-1,0)))) -> 0 | CG49: =IF(AND($BH49="CC",($BC49-BL49)<0),$BD49*1, IF(AND($BH49="VC",($BC49-BL49)<0),$BD49*1, IF(AND($BH49="CP",($BC49-BL49)>0),$BD49*-1, IF(AND($BH49="VP",($BC49-BL49)>0),$BD49*-1,0)))) -> 0 | CH49: =IF(AND($BH49="CC",($BC49-BM49)<0),$BD49*1, IF(AND($BH49="VC",($BC49-BM49)<0),$BD49*1, IF(AND($BH49="CP",($BC49-BM49)>0),$BD49*-1, IF(AND($BH49="VP",($BC49-BM49)>0),$BD49*-1,0)))) -> 0 | CI49: =IF(AND($BH49="CC",($BC49-BN49)<0),$BD49*1, IF(AND($BH49="VC",($BC49-BN49)<0),$BD49*1, IF(AND($BH49="CP",($BC49-BN49)>0),$BD49*-1, IF(AND($BH49="VP",($BC49-BN49)>0),$BD49*-1,0)))) -> 0 | CJ49: =IF(AND($BH49="CC",($BC49-BO49)<0),$BD49*1, IF(AND($BH49="VC",($BC49-BO49)<0),$BD49*1, IF(AND($BH49="CP",($BC49-BO49)>0),$BD49*-1, IF(AND($BH49="VP",($BC49-BO49)>0),$BD49*-1,0)))) -> 0 | CK49: =Tabla3[[#This Row],[Tns]] -> -544.32 | CL49: =IF(ISERROR(VLOOKUP(VALUE(E49),'Clientes CBOT'!A:A,1,0)),"VER","ok") -> ok
A50: P | B50: R | C50: 766 | D50: 0 | E50: 20176 | F50: C | H50: F1 | I50: .AW-0000026C | J50: 3585 | K50: 2 | L50: 10000 | M50: MAR 26 WHEAT | N50: 5.41 | O50: 20251126 | Q50: 202603 | S50: F | U50: 0 | V50: 0 | X50: FYO ACOPIO SA | Z50: 20251126 | AA50: 1 | AB50: 1A | AC50: W- | AF50: 5.41000000 | AL50: 0 | AM50: 1.0000 | AN50: USD | AO50: 31250 | AP50: 534750000 | AQ50: 0 | AR50: 50000 | AS50: 5K26 OHh0 | AT50: 116373585 | AU50: 0,0000 | AV50: W | AW50: CBT | AX50: Comdty | AY50: Trigo | AZ50: =IF(VLOOKUP(AY50,Conversor!B:C,2,0)="HS",0.01,VLOOKUP(AY50,Conversor!B:C,2,0)) -> 0.36743 | BA50: =IF(BG50="v",-AM50/10000,AL50/10000) -> -1 | BB50: =IF(AQ50=0,AP50/1000000*AZ50,AQ50/1000000*AZ50) -> 196.48319 | BC50: =U50/1000000*AZ50 -> 0 | BD50: =IF(OR(E50="FUTUR",E50="f20176"),0,VLOOKUP(AY50,Conversor!G:I,3,0)*BA50) -> -136.08 | BE50: =IF(LEFT(M50,4)="call","Call",IF(LEFT(M50,3)="put","Put","Futuro")) -> Futuro | BF50: =IF(BE50="futuro","no","si") -> no | BG50: =IF(AL50=0,"V","C") -> V | BH50: =IF(BE50="futuro","",CONCATENATE(BG50,LEFT(BE50,1))) | BI50: =$BB50*(1+BI$2) -> 137.53823 | BJ50: =$BB50*(1+BJ$2) -> 157.18655 | BK50: =$BB50*(1+BK$2) -> 176.83487 | BL50: =$BB50*(1+BL$2) -> 196.48319 | BM50: =$BB50*(1+BM$2) -> 216.13151 | BN50: =$BB50*(1+BN$2) -> 235.77983 | BO50: =$BB50*(1+BO$2) -> 255.42815 | BP50: =IF($BE50="futuro",-($BL50-BI50)*$BD50,0) -> 8021.2299 | BQ50: =IF($BE50="futuro",-($BL50-BJ50)*$BD50,0) -> 5347.4866 | BR50: =IF($BE50="futuro",-($BL50-BK50)*$BD50,0) -> 2673.7433 | BS50: =IF($BE50="futuro",-($BL50-BL50)*$BD50,0) -> 0 | BT50: =IF($BE50="futuro",-($BL50-BM50)*$BD50,0) -> -2673.7433 | BU50: =IF($BE50="futuro",-($BL50-BN50)*$BD50,0) -> -5347.4866 | BV50: =IF($BE50="futuro",-($BL50-BO50)*$BD50,0) -> -8021.2299 | BW50: =IF(AND($BH50="CC",($BC50-BI50)<0),(BI50-$BC50)*$BD50, IF(AND($BH50="VC",($BC50-BI50)<0),($BC50-BI50)*-$BD50, IF(AND($BH50="CP",($BC50-BI50)>0),(BI50-$BC50)*$BD50*-1, IF(AND($BH50="VP",($BC50-BI50)>0),(BI50-$BC50)*$BD50*-1,0)))) -> 0 | BX50: =IF(AND($BH50="CC",($BC50-BJ50)<0),(BJ50-$BC50)*$BD50, IF(AND($BH50="VC",($BC50-BJ50)<0),($BC50-BJ50)*-$BD50, IF(AND($BH50="CP",($BC50-BJ50)>0),(BJ50-$BC50)*$BD50*-1, IF(AND($BH50="VP",($BC50-BJ50)>0),(BJ50-$BC50)*$BD50*-1,0)))) -> 0 | BY50: =IF(AND($BH50="CC",($BC50-BK50)<0),(BK50-$BC50)*$BD50, IF(AND($BH50="VC",($BC50-BK50)<0),($BC50-BK50)*-$BD50, IF(AND($BH50="CP",($BC50-BK50)>0),(BK50-$BC50)*$BD50*-1, IF(AND($BH50="VP",($BC50-BK50)>0),(BK50-$BC50)*$BD50*-1,0)))) -> 0 | BZ50: =IF(AND($BH50="CC",($BC50-BL50)<0),(BL50-$BC50)*$BD50, IF(AND($BH50="VC",($BC50-BL50)<0),($BC50-BL50)*-$BD50, IF(AND($BH50="CP",($BC50-BL50)>0),(BL50-$BC50)*$BD50*-1, IF(AND($BH50="VP",($BC50-BL50)>0),(BL50-$BC50)*$BD50*-1,0)))) -> 0 | CA50: =IF(AND($BH50="CC",($BC50-BM50)<0),(BM50-$BC50)*$BD50, IF(AND($BH50="VC",($BC50-BM50)<0),($BC50-BM50)*-$BD50, IF(AND($BH50="CP",($BC50-BM50)>0),(BM50-$BC50)*$BD50*-1, IF(AND($BH50="VP",($BC50-BM50)>0),(BM50-$BC50)*$BD50*-1,0)))) -> 0 | CB50: =IF(AND($BH50="CC",($BC50-BN50)<0),(BN50-$BC50)*$BD50, IF(AND($BH50="VC",($BC50-BN50)<0),($BC50-BN50)*-$BD50, IF(AND($BH50="CP",($BC50-BN50)>0),(BN50-$BC50)*$BD50*-1, IF(AND($BH50="VP",($BC50-BN50)>0),(BN50-$BC50)*$BD50*-1,0)))) -> 0 | CC50: =IF(AND($BH50="CC",($BC50-BO50)<0),(BO50-$BC50)*$BD50, IF(AND($BH50="VC",($BC50-BO50)<0),($BC50-BO50)*-$BD50, IF(AND($BH50="CP",($BC50-BO50)>0),(BO50-$BC50)*$BD50*-1, IF(AND($BH50="VP",($BC50-BO50)>0),(BO50-$BC50)*$BD50*-1,0)))) -> 0 | CD50: =IF(AND($BH50="CC",($BC50-BI50)<0),$BD50*1, IF(AND($BH50="VC",($BC50-BI50)<0),$BD50*1, IF(AND($BH50="CP",($BC50-BI50)>0),$BD50*-1, IF(AND($BH50="VP",($BC50-BI50)>0),$BD50*-1,0)))) -> 0 | CE50: =IF(AND($BH50="CC",($BC50-BJ50)<0),$BD50*1, IF(AND($BH50="VC",($BC50-BJ50)<0),$BD50*1, IF(AND($BH50="CP",($BC50-BJ50)>0),$BD50*-1, IF(AND($BH50="VP",($BC50-BJ50)>0),$BD50*-1,0)))) -> 0 | CF50: =IF(AND($BH50="CC",($BC50-BK50)<0),$BD50*1, IF(AND($BH50="VC",($BC50-BK50)<0),$BD50*1, IF(AND($BH50="CP",($BC50-BK50)>0),$BD50*-1, IF(AND($BH50="VP",($BC50-BK50)>0),$BD50*-1,0)))) -> 0 | CG50: =IF(AND($BH50="CC",($BC50-BL50)<0),$BD50*1, IF(AND($BH50="VC",($BC50-BL50)<0),$BD50*1, IF(AND($BH50="CP",($BC50-BL50)>0),$BD50*-1, IF(AND($BH50="VP",($BC50-BL50)>0),$BD50*-1,0)))) -> 0 | CH50: =IF(AND($BH50="CC",($BC50-BM50)<0),$BD50*1, IF(AND($BH50="VC",($BC50-BM50)<0),$BD50*1, IF(AND($BH50="CP",($BC50-BM50)>0),$BD50*-1, IF(AND($BH50="VP",($BC50-BM50)>0),$BD50*-1,0)))) -> 0 | CI50: =IF(AND($BH50="CC",($BC50-BN50)<0),$BD50*1, IF(AND($BH50="VC",($BC50-BN50)<0),$BD50*1, IF(AND($BH50="CP",($BC50-BN50)>0),$BD50*-1, IF(AND($BH50="VP",($BC50-BN50)>0),$BD50*-1,0)))) -> 0 | CJ50: =IF(AND($BH50="CC",($BC50-BO50)<0),$BD50*1, IF(AND($BH50="VC",($BC50-BO50)<0),$BD50*1, IF(AND($BH50="CP",($BC50-BO50)>0),$BD50*-1, IF(AND($BH50="VP",($BC50-BO50)>0),$BD50*-1,0)))) -> 0 | CK50: =Tabla3[[#This Row],[Tns]] -> -136.08 | CL50: =IF(ISERROR(VLOOKUP(VALUE(E50),'Clientes CBOT'!A:A,1,0)),"VER","ok") -> ok
